Workbook

Sheet Sheet3
A1: Validation_Requried | B1: Y
A3: Count of PoC (TrnDtl) | C3: Source | M3: Consist | N3: Equipment | O3: Location | P3: Mechanical | Q3: Miles | R3: Time | S3: TonneMiles | T3: Train | U3: Waybill | V3: Weight
A4: Table | B4: Dimension | C4: BMR | D4: BrandNew | E4: TrnCnstDtl | F4: TrnLvlSmry | G4: Grand Total | L4: Validity | O4: Y | P4: Y | T4: Y | U4: Y | V4: Y
A5: Train_Detail | B5: Consist | D5: 1 | E5: 1 | F5: 1 | G5: 3 | L5: Completeness | O5: Y
B6: Equipment | D6: 13 | E6: 5 | G6: 18 | L6: Consistency | M6: Y
B7: Location | C7: 6 | D7: 8 | F7: 6 | G7: 20 | L7: Integrity | O7: Y | S7: Y
B8: Mechanical | F8: 1 | G8: 1 | L8: Timeliness | R8: Y | S8: Y
B9: Miles | F9: 9 | G9: 9 | L9: Currency | O9: Y | R9: Y | S9: Y
B10: Time | D10: 1 | E10: 1 | F10: 5 | G10: 7 | L10: Reasonableness | N10: Y | P10: Y
B11: TonneMiles | F11: 3 | G11: 3 | L11: Uniqueness | M11: Y
B12: Train | D12: 3 | G12: 3 | L12: Accuracy | M12: Y | O12: Y | Q12: Y | S12: Y | V12: Y
B13: Waybill | D13: 9 | E13: 13 | G13: 22
B14: Weight | F14: 2 | G14: 2
A15: Train_Detail Total | C15: 6 | D15: 35 | E15: 20 | F15: 27 | G15: 88
A16: Train_Summary | B16: Consist | D16: 1 | F16: 4 | G16: 5
B17: Equipment | D17: 1 | F17: 3 | G17: 4
B18: Location | C18: 6 | D18: 8 | F18: 6 | G18: 20
B19: Mechanical | F19: 1 | G19: 1
B20: Miles | C20: 2 | F20: 9 | G20: 11
B21: Time | D21: 1 | F21: 5 | G21: 6
B22: TonneMiles | F22: 2 | G22: 2
B23: Train | D23: 2 | G23: 2
B24: Weight | F24: 2 | G24: 2
A25: Train_Summary Total | C25: 8 | D25: 13 | F25: 32 | G25: 53
A26: Grand Total | C26: 14 | D26: 48 | E26: 20 | F26: 59 | G26: 141
A30: Validation_Requried | B30: Y
A32: Dimension | B32: Count of PoC (TrnDtl) | M32: Validity | N32: Completeness | O32: Consistency | P32: Integrity | Q32: Timeliness | R32: Currency | S32: Reasonableness | T32: Uniqueness | U32: Accuracy
A33: Consist | B33: 8 | L33: Consist | O33: Y | T33: Y | U33: Y
A34: Equipment | B34: 22 | L34: Equipment | S34: Y
A35: Location | B35: 40 | L35: Location | M35: Y | N35: Y | P35: Y | R35: Y | U35: Y
A36: Mechanical | B36: 2 | L36: Mechanical | M36: Y | S36: Y
A37: Miles | B37: 20 | L37: Miles | U37: Y
A38: Time | B38: 13 | L38: Time | Q38: Y | R38: Y
A39: TonneMiles | B39: 5 | L39: TonneMiles | P39: Y | Q39: Y | R39: Y | U39: Y
A40: Train | B40: 5 | L40: Train | M40: Y
A41: Waybill | B41: 22 | L41: Waybill | M41: Y
A42: Weight | B42: 4 | L42: Weight | M42: Y | U42: Y
A43: Grand Total | B43: 141
A51: Validation_Requried | B51: Y
A53: Count of PoC (TrnDtl) | C53: Source
A54: Table | B54: Dimension | C54: BMR | D54: BrandNew | E54: TrnCnstDtl | F54: TrnLvlSmry | G54: Grand Total
A55: Train_Detail | B55: Consist | D55: 1 | E55: 1 | F55: 1 | G55: 3
B56: Equipment | D56: 13 | E56: 5 | G56: 18
B57: Location | C57: 6 | D57: 8 | F57: 6 | G57: 20
B58: Mechanical | F58: 1 | G58: 1
B59: Miles | F59: 9 | G59: 9
B60: Time | D60: 1 | E60: 1 | F60: 5 | G60: 7
B61: TonneMiles | F61: 3 | G61: 3
B62: Train | D62: 3 | G62: 3
B63: Waybill | D63: 9 | E63: 13 | G63: 22
B64: Weight | F64: 2 | G64: 2
A65: Train_Detail Total | C65: 6 | D65: 35 | E65: 20 | F65: 27 | G65: 88
A66: Train_Summary | B66: Consist | D66: 1 | F66: 4 | G66: 5
B67: Equipment | D67: 1 | F67: 3 | G67: 4
B68: Location | C68: 6 | D68: 8 | F68: 6 | G68: 20
B69: Mechanical | F69: 1 | G69: 1
B70: Miles | C70: 2 | F70: 9 | G70: 11
B71: Time | D71: 1 | F71: 5 | G71: 6
B72: TonneMiles | F72: 2 | G72: 2
B73: Train | D73: 2 | G73: 2
B74: Weight | F74: 2 | G74: 2
A75: Train_Summary Total | C75: 8 | D75: 13 | F75: 32 | G75: 53
A76: Grand Total | C76: 14 | D76: 48 | E76: 20 | F76: 59 | G76: 141

Sheet Proposed Data Tables (2 tables)
A1: Table | B1: SEQ | C1: Code | D1: Source | E1: Validation_Priority | F1: Validation_Requried | G1: PoC (TrnDtl) | H1: Dimension | I1: Field_Type | J1: Field_Name | K1: Validation_Logic_Approach | L1: Data Dictionary | M1: Example or Methodology | N1: Active Data? (Y/N) | O1: Source Schema.Table.Column Name // Vicky's Comments | P1: Future Sources | Q1: Transformations / Validation / If/else | R1: ExpectedResult | S1: Count of NULl | T1: Count of TTL Rows | U1: % of NULL
A2: Train_Detail | B2: 1 | C2: Train142 | D2: BrandNew | E2: LOW | F2: N | G2: Y | H2: Time | J2: Train Year | L2: Calendar year of the actual departure from origin for this train instance. | M2: 2025 | N2: Y | O2: eqpmv.eqpmv_rfeqp_mvmnt_event.report_tms | Q2: Y | R2: N/A
A3: Train_Detail | B3: 2 | C3: Train143 | D3: BrandNew | E3: LOW | F3: N | G3: Y | H3: Time | J3: Train Quarter | L3: Quarter that a train departed from its origin | M3: 1 | N3: Y | O3: eqpmv.eqpmv_rfeqp_mvmnt_event.report_tms | Q3: Y | R3: N/A
A4: Train_Detail | B4: 3 | C4: Train144 | D4: BrandNew | E4: LOW | F4: N | G4: Y | H4: Time | J4: Train Month | L4: Month that a train departed from its origin | M4: 2 | N4: Y | O4: eqpmv.eqpmv_rfeqp_mvmnt_event.report_tms | Q4: Y | R4: N/A
A5: Train_Detail | B5: 4 | C5: Train145 | D5: BrandNew | E5: LOW | F5: N | G5: Y | H5: Time | J5: Train Day | L5: Day that a train departed from its origin | M5: 25 | N5: Y | O5: eqpmv.eqpmv_rfeqp_mvmnt_event.report_tms | Q5: Y | R5: N/A
A6: Train_Detail | B6: 5 | C6: Train009 | D6: TrnLvlSmry | E6: HIGH | F6: Y | G6: Y | H6: Time | J6: SADB_RECEIVING_DT | K6: Data Freshnesss: SADB_RECEIVING_DT = ARRIVE_TMS BY DATE | L6: Reporting time stamp for most recent events at the time train was reported | M6: 8/2/25 0:00 | N6: Y | O6: eqpmv.eqpmv_rfeqp_mvmnt_event lcmtv.lcmtv_mvmnt_event | Q6: N | R6: 1
A7: Train_Detail | B7: 6 | C7: Train001 | D7: TrnLvlSmry | E7: MEDIUM | F7: N | G7: Y | H7: System | J7: SRC_SYS | L7: Source systems such as KCS = MCS or CP = TYES | M7: KCS | N7: Y | O7: Exact Source not identified yet | Q7: N | R7: 1
A8: Train_Detail | B8: 7 | C8: Train048 | D8: TrnLvlSmry | E8: MEDIUM | F8: N | G8: Y | H8: Train | J8: TRAIN_SERIES | L8: Train series identifier | M8: 100 | N8: Y | O8: Derived from Train_Name | Q8: Y
A9: Train_Detail | B9: 8 | C9: Train050 | D9: TrnLvlSmry | E9: MEDIUM | F9: N | G9: Y | H9: Train | J9: TRAIN_SYMBOL | L9: Train symbol code | M9: 181 | N9: Y | O9: Derived from Train_Name | Q9: Y
A10: Train_Detail | B10: 9 | C10: Train011 | D10: TrnLvlSmry | E10: HIGH | F10: N | G10: Y | H10: Train | J10: TRAIN_NAME | L10: Train name | M10: 181-01 | N10: Y | O10: train.train_cnst_smry.train_nm | Q10: N | R10: 1
A11: Train_Detail | B11: 10 | C11: Train051 | D11: TrnLvlSmry | E11: MEDIUM | F11: N | G11: Y | H11: Train | J11: TRAIN_TYPE_CD | L11: Train type code | M11: FRT | N11: Y | O11: atm_train.train_plan.train_type_cd atm_train.optrn.train_type_cd | Q11: Y
A12: Train_Detail | B12: 11 | C12: Train052 | D12: TrnLvlSmry | E12: MEDIUM | F12: N | G12: Y | H12: Train | J12: TRAIN_KIND_CD | L12: Train kind code | M12: PRIM | N12: Y | O12: atm_train.train_plan.train_kind_cd atm_train.optrn.train_kind_cd | Q12: Y
A13: Train_Detail | B13: 12 | C13: Train059 | D13: BMR(Qlik) | E13: MEDIUM | F13: N | G13: Y | H13: Train | J13: TYPE | L13: Train operational type | M13: OP | N13: Y | O13: train.train_cnst_smry.train_nm | Q13: Y
A14: Train_Detail | B14: 13 | C14: Train013 | D14: TrnLvlSmry | E14: HIGH | F14: Y | G14: Y | H14: Location | J14: DEPART_FSAC | K14: 1. Segment Validation: ARRIVE_FSAC <> DEPART_FSAC 2. Network Coverage: List of Unique FSAC's by Titan_Nbr&Trn_Leg_ID should cover list of FSAC's from Linked Node Table (GIS teams) sequentially" - all intermediate stations as per Linked Node Table should be covered by sequence of segments | L14: Departure FSAC code | M14: 5770 | N14: Y | O14: trkfc.trkfc_trstn.fsac_cd /eqpmv.eqpmv_rfeqp_mvmnt_event.scac_cd | Q14: N | R14: 1
A15: Train_Detail | B15: 14 | C15: Train014 | D15: TrnLvlSmry | E15: HIGH | F15: Y | G15: Y | H15: Location | J15: ARRIVE_FSAC | K15: 1. Segment Validation: ARRIVE_FSAC <> DEPART_FSAC 2. Network Coverage: List of Unique FSAC's by Titan_Nbr&Trn_Leg_ID should cover list of FSAC's from Linked Node Table (GIS teams) sequentially" - all intermediate stations as per Linked Node Table should be covered by sequence of segments | L15: Arrival FSAC code | M15: 5772 | N15: Y | O15: trkfc.trkfc_trstn.fsac_cd /eqpmv.eqpmv_rfeqp_mvmnt_event.fsac_cd | P15: SADB | Q15: N | R15: 1
A16: Train_Detail | B16: 17 | C16: Train007 | D16: TrnLvlSmry | E16: HIGH | F16: Y | G16: Y | H16: Time | J16: ARRIVE_TMS | K16: Continuity: ARRIVE_TMS > DEPART TMS by Titan&Train_Leg_ID Row 1's ARRIVE_TMS <= Row 2's DEPART_TMS sorted by Titan&Train_Leg_ID&Mark_CD&EQPMTP_NBR and order by Arrivs_TMS ASC | L16: Arrival timestamp | M16: 45870.988 | N16: Y | O16: eqpmv.eqpmv_rfeqp_mvmnt_event.report_tms | Q16: N | R16: 1
A17: Train_Detail | B17: 18 | C17: Train008 | D17: TrnLvlSmry | E17: HIGH | F17: Y | G17: Y | H17: Time | J17: DEPART_TMS | K17: Continuity: ARRIVE_TMS > DEPART TMS by Titan&Train_Leg_ID Row 1's ARRIVE_TMS <= Row 2's DEPART_TMS sorted by Titan&Train_Leg_ID&Mark_CD&EQPMTP_NBR and order by Arrivs_TMS ASC | L17: Departure timestamp | M17: 45870.901 | N17: Y | O17: eqpmv.eqpmv_rfeqp_mvmnt_event.report_tms | Q17: Y | R17: 1
A18: Train_Detail | B18: 19 | C18: Train010 | D18: TrnLvlSmry | E18: HIGH | F18: N | G18: Y | H18: Train | J18: TITAN_NBR | L18: Titan number for train | M18: 942442 | N18: Y | O18: train.train_plan_leg.mtp_titan_nbr train.optrn_leg.mtp_titan_nbr | Q18: N | R18: 1
A19: Train_Detail | B19: 20 | C19: Train021 | D19: TrnLvlSmry | E19: HIGH | F19: Y | G19: Y | H19: Miles | J19: TRAIN_MILES | K19: 1. Train Speed for segment is between 0 and 80mph (regulation) by each segment 2. if EQPMT_MILES >0, TRAIN_MILES>0 3. if GTM=0, TRAIN_MILES=0 4. TRAIN_MILES <= LIVE_LOCO_MILES (because there will be at least 1 live loco to move a train) 5. Trend analysis for DoW (Last 8 weeks vs. yesterday) and L28 vs L7 by subdivision, district, division, region, and railine to detect +/- 20% value 6. Train mile = sum of lead locomotive miles | L19: Total train miles run by a lead locomotive | M19: 7.986 | N19: Y | O19: ctnapp.ctng_line_dn.gmtry | Q19: Y | R19: 1
A20: Train_Detail | B20: 21 | C20: Train026 | D20: TrnLvlSmry | E20: HIGH | F20: Y | G20: Y | H20: Miles | J20: CONTENT_TON_MILES | K20: if Load_Empty_IND = 'Y' and EQPTMT_MILES >0, then CONTENT_TON_MILES>0 | L20: Content ton miles | M20: 16043.874 | N20: Y | O20: train.train_cnst_dtl_rail_eqpt.net_weight_tons_qty
A21: Train_Detail | B21: 22 | C21: Train081 | D21: TrnCnstDtl | E21: HIGH | F21: Y | G21: Y | H21: Equipment | J21: TARE_WEIGHT_TONS_QTY | K21: >15 tons for Rail car, >100 tons for Loco (muse min /max from history for proxy test) | L21: Tare weight in tons | M21: 66 | N21: Y | O21: train.train_cnst_dtl_rail_eqpt.tare_weight_tons_qty | Q21: N
A22: Train_Detail | B22: 23 | C22: Train088 | D22: TrnCnstDtl | E22: HIGH | F22: Y | G22: Y | H22: Equipment | J22: NET_WEIGHT_TONS_QTY | K22: If Load_Empty_IND = L and >0, Pass, False | L22: Net weight in tons | M22: 104 | N22: Y | O22: train.train_cnst_dtl_rail_eqpt.net_weight_tons_qty | Q22: N
A23: Train_Detail | B23: 25 | C23: Train025 | D23: TrnLvlSmry | E23: HIGH | F23: Y | G23: Y | H23: Weight | J23: LOCO_FULL_WEIGHT | K23: LOCO_FULL_WEIGHT/TOTAL_UNITS is between 100 and 250 tons | L23: Locomotive full weight | M23: 424 | N23: Y | O23: lcmtv.lcmtv_emis.full_weight_qty | Q23: Y
A24: Train_Detail | B24: 25 | C24: Train027 | D24: TrnLvlSmry | E24: HIGH | F24: Y | G24: Y | H24: Weight | J24: TARE_TONS | K24: 1. if asset_type = 'Locomotive", TARE_TONS = LOCO_FULL_WEIGHT 2. if asset_type = 'Railcar", TARE_TONS is between 15 and 100 tons (flatcar to heavy equipment) | L24: Total tare tons | M24: 1598.45 | N24: Y | O24: lcmtv.lcmtv_emis.full_weight_qty train.train_cnst_dtl_rail_eqpt.tare_weight_tons_qty | Q24: Y
A25: Train_Detail | B25: 26 | C25: Train015 | D25: TrnLvlSmry | E25: HIGH | F25: Y | G25: Y | H25: Time | J25: TRAIN_HRS | K25: Resonableness in speed: TRAIN_MILES / TRAIN HOURS is between 0 and 80 (mph) | L25: Train hours | M25: 2 | N25: Y | O25: ctnapp.ctng_line_dn.gmtry mvmnt_type hard coded as 'lcmtv' or 'eqpmv' train.train_cnst_dtl_rail_eqpt.lead_lcmtv_ind train.train_cnst_dtl_rail_eqpt.lcmtv_cnst_status_cd | Q25: Y | R25: 1
A26: Train_Detail | B26: 27 | C26: Train016 | D26: TrnLvlSmry | E26: HIGH | F26: Y | G26: Y | H26: Time | J26: TRAIN_MINS | K26: Resonableness in speed: TRAIN_MILES / TRAIN HOURS is between 0 and 80 (mph) | L26: Train minutes | M26: 6.02 | N26: Y | O26: Derived from ARRIVAL_TMS, DEPARTURE_TMS, TOT_MILES, TRAIN_MILES | Q26: Y | R26: 1
A27: Train_Detail | B27: 28 | C27: Train020 | D27: TrnLvlSmry | E27: HIGH | F27: Y | G27: Y | H27: Miles | J27: EQPMT_MILES | K27: if TRAIN_MILES>0, then EQPMT_MILES >0 | L27: Equipment miles | M27: 167.706 | N27: Y | O27: ctnapp.ctng_line_dn.gmtry | Q27: Y | R27: 1
A28: Train_Detail | B28: 29 | C28: Train028 | D28: TrnLvlSmry | E28: HIGH | F28: Y | G28: Y | H28: TonneMiles | J28: TARE_TON_MILES | K28: 1. TARE_TONS VALIDITY (loco between 100-250 tons, railcar between 10 and 100 tons) 2. Validation of TARE_TON_MILES (95% PROXIMITY NEEDED) (TARE_TONS X EQPMT_MILES (for Railcars)) + (TARE_TONS X LIVE_LOCO_MILES (for loco)) | L28: Tare ton miles | M28: 9379.158 | N28: Y | O28: lcmtv.lcmtv_emis.full_weight_qty train.train_cnst_dtl_rail_eqpt.tare_weight_tons_qty ctnapp.ctng_line_dn.gmtry | Q28: Y
A29: Train_Detail | B29: 30 | C29: Train029 | D29: TrnLvlSmry | E29: HIGH | F29: Y | G29: Y | H29: TonneMiles | I29: Calculated field | J29: GROSS_TON_MILES | K29: Use multiple ways to apply regression testing 1. Sum(Contents Tons + Tare Tons from railcars, live and deadhead locomotives) X Train Miles should be within 95% proximity to GROSS_TON_MILES (CONTENTS_TON_MILES + TARE_TON_MILES + DH_TARE_TON_MILES + LOCO_TARE_TON_MILES) 2. Historical consistency: check last 28 days' GTM/CONTENT_TON_MILE ratio by Suddivision vs. last 7 days (check variance over 20% (Absolute value based) 3. Historical trend: check subdivision level GTM average for the last 8 weeks' same Day of Week in comparison to yesterday's GTM excluding stat holidays (e.g. Xmas, Cinco De Mayo) 4. Train level estimates: TRAIN_NM based 5. TRAIN_MILES > 0, LIVE_LOC_MILES >0, and EQPMT_MILES >0 6. For railcar (by car by car) equipment mile should be within 95% proximity to lead locomotive miles 7. Trend analysis for DoW (Last 8 weeks vs. yesterday) and L28 vs L7 by subdivision, district, division, region, and railine to detect +/- 20% value | L29: Gross ton miles | M29: 25423.032 | N29: Y | O29: Derived from TARE_TON_MILES, DH_TARE_TON_MILES, CONTENT_TON_MILES | Q29: Y
A30: Train_Detail | B30: 31 | C30: Train023 | D30: TrnLvlSmry | E30: MEDIUM | F30: N | G30: Y | H30: TonneMiles | J30: DH_TARE_TON_MILES | L30: Deadhead tare ton miles | M30: 0 | N30: Y | O30: lcmtv.lcmtv_emis.full_weight_qty train.train_cnst_dtl_rail_eqpt.tare_weight_tons_qty ctnapp.ctng_line_dn.gmtry | Q30: Y
A31: Train_Detail | B31: 32 | C31: Train024 | D31: TrnLvlSmry | E31: HIGH | F31: Y | G31: Y | H31: TonneMiles | J31: LOCO_TARE_TON_MILES | K31: >0 | L31: Locomotive tare ton miles | M31: 3386.064 | N31: Y | O31: lcmtv.lcmtv_emis.full_weight_qty train.train_cnst_dtl_rail_eqpt.tare_weight_tons_qty ctnapp.ctng_line_dn.gmtry | Q31: Y
A32: Train_Detail | B32: 33 | C32: Train032 | D32: TrnLvlSmry | E32: HIGH | F32: Y | G32: Y | H32: Miles | J32: REV_CAR_MILES_LOADED | K32: if Load_Empty_IND = 'Y' and EQPTMT_MILES >0, then >0) Loaded railcars equipment miles (sum) | L32: Revenue car miles loaded | M32: 167.706 | N32: Y | O32: eqpmt.eqpmnt_aar_base.aar_car_cd train.train_cnst_dtl_rail_eqpt.net_weight_tons_qty ctnapp.ctng_line_dn.gmtry | Q32: Y
A33: Train_Detail | B33: 34 | C33: Train033 | D33: TrnLvlSmry | E33: HIGH | F33: Y | G33: Y | H33: Miles | J33: REV_CAR_MILES_EMPTY | K33: if Load_Empty_IND = 'N' and EQPTMT_MILES >0, then >0) non loaded railcars equipment miles (sum) | L33: Revenue car miles empty | M33: 0 | N33: Y | O33: eqpmt.eqpmnt_aar_base.aar_car_cd train.train_cnst_dtl_rail_eqpt.net_weight_tons_qty ctnapp.ctng_line_dn.gmtry | Q33: Y
A34: Train_Detail | B34: 35 | C34: Train034 | D34: TrnLvlSmry | E34: HIGH | F34: Y | G34: Y | H34: Miles | J34: LIVE_LOCO_MILES | K34: if TRAIN_MILES>0, then >0 | L34: Live locomotive miles | M34: 15.972 | N34: Y | O34: ctnapp.ctng_line_dn.gmtry dm_dim.gis_orgn_dstntn_mlg_by_stprv.miles | Q34: Y
A35: Train_Detail | B35: 36 | C35: Train035 | D35: TrnLvlSmry | E35: HIGH | F35: N | G35: Y | H35: Miles | J35: DH_LOCO_MILES | L35: Deadhead locomotive miles | M35: 0 | N35: Y | O35: ctnapp.ctng_line_dn.gmtry dm_dim.gis_orgn_dstntn_mlg_by_stprv.miles | Q35: Y | R35: ?
A36: Train_Detail | B36: 37 | C36: Train036 | D36: TrnLvlSmry | E36: HIGH | F36: Y | G36: Y | H36: Miles | J36: PASS_BUS_MILES | K36: if PASS_BUS_IND = 'Y' and EQPMT_MILES > 0, then PASS_BUS_MILES > 0 | L36: Passenger business miles | M36: 0 | N36: Y | O36: ctnapp.ctng_line_dn.gmtry dm_dim.gis_orgn_dstntn_mlg_by_stprv.miles | Q36: Y | R36: ?
A37: Train_Detail | B37: 38 | C37: Train037 | D37: TrnLvlSmry | E37: HIGH | F37: Y | G37: Y | H37: Miles | J37: WORK_CAR_MILES | K37: if WORK_CAR_IND = 'Y and EQPMT_MILES >0, then WORK_CAR_MILES >0 | L37: Work car miles | M37: 0 | N37: Y | O37: eqpmt.eqpmnt_aar_base.aar_car_cd ctnapp.ctng_line_dn.gmtry trkfc.trkfcg_sbdvsn.sbdvsn_id trkfc.trkfcg_fxpla_track_lctn_dn.rfrnc_low_miles_qty dm_dim.gis_orgn_dstntn_mlg_by_stprv.miles dm_dim.dim_subdvsn_zone.high_track_mile dm_dim.dim_subdvsn_zone.low_track_mile | Q37: Y
A38: Train_Detail | B38: 39 | C38: Train038 | D38: TrnLvlSmry | E38: LOW | F38: N | G38: X | H38: Miles | J38: CABOOSE_MILES | L38: Caboose miles | M38: 0 | N38: Y | O38: eqpmt.eqpmnt_aar_base.aar_car_cd ctnapp.ctng_line_dn.gmtry dm_dim.gis_orgn_dstntn_mlg_by_stprv.miles | Q38: Y
A39: Train_Detail | B39: 40 | C39: Train039 | D39: TrnLvlSmry | E39: HIGH | F39: Y | G39: Y | H39: Miles | J39: LIVE_LOCO_HP_MILES | K39: if TRAIN_MILES>0, LIVE_LOCO_HP_MILES >0 | L39: Live locomotive horsepower miles | M39: 69478.2 | N39: Y | O39: lcmtv.lcmtv_emis.hrspwr_qty ctnapp.ctng_line_dn.gmtry dm_dim.gis_orgn_dstntn_mlg_by_stprv.miles | Q39: Y
A40: Train_Detail | B40: 41 | C40: Train040 | D40: TrnLvlSmry | E40: MEDIUM | F40: N | G40: Y | H40: Miles | J40: DH_LOCO_HP_MILES | L40: Deadhead locomotive horsepower miles | M40: 0 | N40: Y | O40: lcmtv.lcmtv_emis.hrspwr_qty ctnapp.ctng_line_dn.gmtry dm_dim.gis_orgn_dstntn_mlg_by_stprv.miles | Q40: Y
A41: Train_Detail | B41: 42 | C41: Train041 | D41: TrnLvlSmry | E41: HIGH | F41: N | G41: Y | H41: Length | J41: LIVE_LOCO_FOOT_MILES | L41: Live locomotive foot miles | M41: 1224.52 | N41: Y | O41: eqpmt.eqpmnt_aar_base.otsd_length_qty ctnapp.ctng_line_dn.gmtry dm_dim.gis_orgn_dstntn_mlg_by_stprv.miles | Q41: Y
A42: Train_Detail | B42: 43 | C42: Train042 | D42: TrnLvlSmry | E42: HIGH | F42: N | G42: Y | H42: Length | J42: DH_LOCO_FOOT_MILES | L42: Deadhead locomotive foot miles | M42: 0 | N42: Y | O42: eqpmt.eqpmnt_aar_base.otsd_length_qty ctnapp.ctng_line_dn.gmtry dm_dim.gis_orgn_dstntn_mlg_by_stprv.miles | Q42: Y
A43: Train_Detail | B43: 44 | C43: Train043 | D43: TrnLvlSmry | E43: HIGH | F43: N | G43: Y | H43: Length | J43: CAR_FOOT_MILES | L43: Car foot miles | M43: 28790.861 | N43: Y | O43: eqpmt.eqpmnt_aar_base.otsd_length_qty | Q43: Y
A44: Train_Detail | B44: 45 | C44: Train044 | D44: TrnLvlSmry | E44: HIGH | F44: N | G44: Y | H44: Length | J44: TOTAL_TRAIN_FOOT_MILES | L44: Total train foot miles | M44: 30015.381 | N44: Y | O44: eqpmt.eqpmnt_aar_base.otsd_length_qty | Q44: Y
A45: Train_Detail | B45: 46 | C45: Train146 | D45: BrandNew | E45: LOW | F45: Y | G45: Y | H45: Time | J45: Train DoW | K45: Validity: 3 letter (MON/TUE/WED/THU/FRI/SAT/SUN) | L45: Day of the week that a train departed from its origin | M45: Based on DFLC TMS at Origin(Mon) | N45: Y | O45: eqpmv.eqpmv_rfeqp_mvmnt_event.report_tms | Q45: Y | R45: N/A
A46: Train_Detail | B46: 47 | C46: Train150 | D46: BrandNew | E46: HIGH | F46: Y | G46: Y | H46: Consist | J46: SQNC_NBR | K46: 1.# of equiments = maximum SQNC, Count of unique MARK_CD&EQPUN_NBR = MAX(SQNC_NBR) 2. Every single segment will have SQNC>0 3. SQNC = 1 should not be Asset_type = 'railcar' but 'locomotive' 4. Missing consist handling a. missing lead locomotive: bring back lead locomotive ID from previous FSAC point b. missing railcar consist: TBD | L46: Sequence of equipment from a train | M46: Current logic or enhacement | N46: Y | O46: train.train_cnst_dtl_rail_eqpt.sqnc_nbr | Q46: N | R46: N/A
A47: Train_Detail | B47: 48 | C47: Train070 | D47: TrnCnstDtl | E47: MEDIUM | F47: N | G47: Y | H47: Equipment | J47: MARK_CD | L47: Equipment mark code | M47: AOK | N47: Y | O47: train.train_cnst_dtl_rail_eqpt.mark_cd | Q47: N | R47: 1
A48: Train_Detail | B48: 49 | C48: Train071 | D48: TrnCnstDtl | E48: MEDIUM | F48: N | G48: Y | H48: Equipment | J48: EQPUN_NBR | L48: Equipment number | M48: 55688 | N48: Y | O48: train.train_cnst_dtl_rail_eqpt.eqpun_nbr | Q48: N | R48: 1
A49: Train_Detail | B49: 50 | C49: Train177 | D49: BrandNew | E49: MEDIUM | F49: Y | G49: Y | H49: Equipment | J49: Load_Empty_Ind | K49: L or E for Railcar, Loco will be E | L49: Load or empty indicator of equipment on a train | N49: Y | O49: eqpmv.eqpmv_rfeqp_mvmnt_event.load_empty_ind | R49: N/A
A50: Train_Detail | B50: 51 | C50: Train185 | D50: BrandNew | E50: HIGH | F50: Y | G50: Y | H50: Waybill | J50: Cycle_Serial_Nbr | K50: 1. if No CSN's found -> default value must be entered e.g. 9999999... or -9999999 2. CSN - under single shipment (Wybl_ID&Mark_CD&EQPUN_NBR), only one unique CSN's should be found 3. Multiple CSN's for single shipment -> gold-silver layer is designed to fix issues by using maximum CSN version number as current version ID on the Wybl 4. Single CSN's for multiple shipments -> gold-silver layer is designed to fix issues by creating a unique identifier such as ((A. CSN's+OriginFSAC+OrigDFLC_DT, B CSN's+Version#, C.CSN&CAR_ID&Orig_DFLC_DT D.CSN&TrainID&Titan) | L50: Shipment cycle serial number | M50: 667123456 | N50: Y | O50: SAP HANA if revenue waybills | R50: N/A
A51: Train_Detail | B51: 52 | C51: Train183 | D51: BrandNew | E51: HIGH | F51: Y | G51: Y | H51: Waybill | J51: WYBL_NBR | K51: if LOAD_EMPTY_IND = 'L', NOT NULL | L51: Waybill number | N51: Y | O51: SAP HANA if revenue waybills | R51: N/A
A52: Train_Detail | B52: 53 | C52: Train182 | D52: BrandNew | E52: HIGH | F52: Y | G52: Y | H52: Waybill | J52: Wybl_ID | K52: if LOAD_EMPTY_IND = 'L', NOT NULL | L52: Waybill internal ID | N52: Y | O52: SAP HANA if revenue waybills | R52: N/A
A53: Train_Detail | B53: 54 | C53: Train082 | D53: TrnCnstDtl | E53: LOW | F53: Y | G53: Y | H53: Waybill | J53: ORIGIN_SCAC_CD | K53: if LOAD_EMPTY_IND = 'L', NOT NULL | L53: Origin SCAC code | M53: KCSM | N53: Y | O53: train.train_cnst_dtl_rail_eqpt.origin_scac_cd | Q53: N
A54: Train_Detail | B54: 55 | C54: Train085 | D54: TrnCnstDtl | E54: LOW | F54: Y | G54: Y | H54: Waybill | J54: DSTNTN_SCAC_CD | K54: if LOAD_EMPTY_IND = 'L', NOT NULL | L54: Destination SCAC code | M54: CPRS | N54: Y | O54: train.train_cnst_dtl_rail_eqpt.dstntn_scac_cd | Q54: N
A55: Train_Detail | B55: 56 | C55: Train083 | D55: TrnCnstDtl | E55: MEDIUM | F55: Y | G55: Y | H55: Waybill | J55: ORIGIN_FSAC_CD | K55: if LOAD_EMPTY_IND = 'L', NOT NULL | L55: Origin FSAC code | M55: 426 | N55: Y | O55: train.train_cnst_dtl_rail_eqpt.origin_fsac_cd | Q55: N
A56: Train_Detail | B56: 57 | C56: Train086 | D56: TrnCnstDtl | E56: MEDIUM | F56: Y | G56: Y | H56: Waybill | J56: DSTNTN_FSAC_CD | K56: if LOAD_EMPTY_IND = 'L', NOT NULL | L56: Destination FSAC code | M56: 4541 | N56: Y | O56: train.train_cnst_dtl_rail_eqpt.dstntn_fsac_cd | Q56: N
A57: Train_Detail | B57: 58 | C57: Train173 | D57: BrandNew | E57: MEDIUM | F57: Y | G57: Y | H57: Waybill | J57: ORIGIN_STN_NM | K57: if LOAD_EMPTY_IND = 'L', NOT NULL | L57: Origin station name of equipment | N57: Y | O57: If this is shipment route origin at the car level, then we can leverage stnwyb_msg_dn | R57: N/A
A58: Train_Detail | B58: 59 | C58: Train174 | D58: BrandNew | E58: MEDIUM | F58: Y | G58: Y | H58: Waybill | J58: DSTNTN_STN_NM | K58: if LOAD_EMPTY_IND = 'L', NOT NULL | L58: Destination station name of equipment | N58: Y | O58: If this is shipment route origin at the car level, then we can leverage stnwyb_msg_dn | R58: N/A
A59: Train_Detail | B59: 60 | C59: Train084 | D59: TrnCnstDtl | E59: LOW | F59: Y | G59: Y | H59: Waybill | J59: ORIGIN_TRSTN_VRSN_NBR | K59: if LOAD_EMPTY_IND = 'L', NOT NULL | L59: Origin transition version number | M59: 3 | N59: Y | O59: train.train_cnst_dtl_rail_eqpt.origin_trstn_vrsn_nbr | Q59: N
A60: Train_Detail | B60: 61 | C60: Train087 | D60: TrnCnstDtl | E60: LOW | F60: Y | G60: Y | H60: Waybill | J60: DSTNTN_TRSTN_VRSN_NBR | K60: if LOAD_EMPTY_IND = 'L', NOT NULL | L60: Destination transition version number | M60: 10 | N60: Y | O60: train.train_cnst_dtl_rail_eqpt.dstntn_trstn_vrsn_nbr | Q60: N
A61: Train_Detail | B61: 62 | C61: Train092 | D61: TrnCnstDtl | E61: HIGH | F61: Y | G61: Y | H61: Waybill | J61: SHPR_CPRS_CSTMR_ID | K61: if LOAD_EMPTY_IND = 'L', NOT NULL | L61: Shipper customer ID | M61: CPINTSER | N61: Y | O61: train.train_cnst_dtl_rail_eqpt.shppr_cprs_cstmr_id | Q61: N
A62: Train_Detail | B62: 63 | C62: Train093 | D62: TrnCnstDtl | E62: HIGH | F62: Y | G62: Y | H62: Waybill | J62: CNSGN_CPRS_CSTMR_ID | K62: if LOAD_EMPTY_IND = 'L', NOT NULL | L62: Consignee customer ID | M62: CPINTSER | N62: Y | O62: train.train_cnst_dtl_rail_eqpt.cnsgn_cprs_cstmr_id | Q62: N
A63: Train_Detail | B63: 64 | C63: Train130 | D63: TrnCnstDtl | E63: HIGH | F63: Y | G63: Y | H63: Waybill | J63: CARE_OF_PARTY_CPRS_CSTMR_ID | K63: if LOAD_EMPTY_IND = 'L', NOT NULL | L63: Care of party customer ID | M63: NULL | N63: Y | O63: train.train_cnst_dtl_rail_eqpt.care_of_party_cprs_cstmr_id | Q63: N
A64: Train_Detail | B64: 65 | C64: Train089 | D64: TrnCnstDtl | E64: LOW | F64: Y | G64: Y | H64: Waybill | J64: CLRNC_PLATE_CD | K64: if LOAD_EMPTY_IND = 'L', NOT NULL | L64: Clearance plate code | M64: H | N64: Y | O64: train.train_cnst_dtl_rail_eqpt.clrnc_plate_cd | Q64: N
A65: Train_Detail | B65: 66 | C65: Train096 | D65: TrnCnstDtl | E65: HIGH | F65: Y | G65: Y | H65: Waybill | J65: STCC_CD | K65: if LOAD_EMPTY_IND = 'L', NOT NULL | L65: Standard Transportation Commodity Code | M65: 9980205 | N65: Y | O65: train.train_cnst_dtl_rail_eqpt.stcc_cd | Q65: N
A66: Train_Detail | B66: 67 | C66: Train186 | D66: BrandNew | E66: HIGH | F66: Y | G66: Y | H66: Waybill | J66: SUB-LOB | K66: if LOAD_EMPTY_IND = 'L', NOT NULL | L66: Detailed line of business | M66: PULP | N66: N/A | O66: Need to know source to ascertain whether this is active or not | R66: N/A
A67: Train_Detail | B67: 68 | C67: Train187 | D67: BrandNew | E67: HIGH | F67: Y | G67: Y | H67: Waybill | J67: LOB | K67: if LOAD_EMPTY_IND = 'L', NOT NULL | L67: Line of business | M67: FOREST_PRODUCTS | N67: N/A | O67: Can be pulled from SAP HANA | R67: N/A
A68: Train_Detail | B68: 69 | C68: Train097 | D68: TrnCnstDtl | E68: HIGH | F68: Y | G68: Y | H68: Waybill | J68: HZCMD_MTRL_RSPNS_CD | K68: if LOAD_EMPTY_IND = 'L', NOT NULL | L68: Hazardous material response code | M68: NULL | N68: Y | O68: train.train_cnst_dtl_rail_eqpt.hzcmd_mtrl_rspns_cd | Q68: N
A69: Train_Detail | B69: 71 | C69: Train094 | D69: TrnCnstDtl | E69: HIGH | F69: Y | G69: Y | H69: Waybill | J69: FSTWY_WYBL_NBR | K69: if LOAD_EMPTY_IND = 'L', NOT NULL | L69: First waybill number | M69: NULL | N69: Y | O69: train.train_cnst_dtl_rail_eqpt.fstwy_wybl_nbr | Q69: N
A70: Train_Detail | B70: 72 | C70: Train175 | D70: BrandNew | E70: HIGH | F70: Y | G70: Y | H70: Waybill | J70: *Revenue in CAD? (active version) | K70: if LOAD_EMPTY_IND = 'L', REVENUE > = 0 (NOT NULL) | L70: Revenue in Canadian funds | M70: Do we need to know how much revenue each train generates? | N70: N/A | O70: this is a good metric for business; if we need it, and we need, can we bring from existing data sources is the question as revenue may involve RMS, SAP-Finance, SAP FCC etc. | R70: N/A
A71: Train_Detail | B71: 73 | C71: Train188 | D71: BrandNew | E71: HIGH | F71: Y | G71: Y | H71: Waybill | J71: DG/HZD Indicator? | K71: if LOAD_EMPTY_IND = 'L', NOT NULL | L71: Dangerous or Hazardous content indicator | M71: NON HZD | N71: Y | O71: Lookup from dm_dim.dim_commodity with the stcc number | R71: N/A
A72: Train_Detail | B72: 74 | C72: Train189 | D72: BrandNew | E72: MEDIUM | F72: N | G72: Y | H72: Waybill | J72: REV_CAR_MILES_LOADED_IND | L72: Indicator for revenue car miles loaded | N72: N/A | R72: N/A
A73: Train_Detail | B73: 75 | C73: Train190 | D73: BrandNew | E73: MEDIUM | F73: N | G73: Y | H73: Waybill | J73: REV_CAR_MILES_EMPTY_IND | L73: Indicator for revenue car miles empty | N73: N/A | R73: N/A
A74: Train_Detail | B74: 84 | C74: Train139 | D74: TrnCnstDtl | E74: LOW | F74: N | G74: Y | H74: Waybill | J74: EQPMT_ASGNMN_ID | L74: Equipment assignment ID | M74: 5933239369 | N74: Y | O74: train.train_cnst_dtl_rail_eqpt.eqpmt_asgnmn_id | Q74: N
A75: Train_Detail | B75: 85 | C75: Train140 | D75: TrnCnstDtl | E75: MEDIUM | F75: N | G75: Y | H75: Waybill | J75: SHPMT_ID | L75: Shipment ID | M75: 5933239360 | N75: Y | O75: train.train_cnst_dtl_rail_eqpt.shpmt_id | Q75: N
A76: Train_Detail | B76: 86 | C76: Train126 | D76: TrnCnstDtl | E76: MEDIUM | F76: N | G76: Y | H76: Location | J76: CNST_CHNG_MVMNT_EVENT_ID | L76: Consist change movement event ID | M76: NULL | N76: Y | O76: train.train_cnst_dtl_rail_eqpt.cnst_chng_mvmnt_event_id | P76: SADB | Q76: N
A77: Train_Detail | B77: 87 | C77: Train127 | D77: TrnCnstDtl | E77: HIGH | F77: N | G77: Y | H77: Location | J77: CNST_CHNG_SCAC_CD | L77: Consist change SCAC code | M77: CPRS | N77: Y | O77: train.train_cnst_dtl_rail_eqpt.cnst_chng_scac_cd | P77: SADB | Q77: N
A78: Train_Detail | B78: 88 | C78: Train128 | D78: TrnCnstDtl | E78: HIGH | F78: N | G78: Y | H78: Location | J78: CNST_CHNG_FSAC_CD | L78: Consist change FSAC code | M78: 5770 | N78: Y | O78: train.train_cnst_dtl_rail_eqpt.cnst_chng_fsac_cd | P78: SADB | Q78: N
A79: Train_Detail | B79: 89 | C79: Train129 | D79: TrnCnstDtl | E79: MEDIUM | F79: N | G79: Y | H79: Location | J79: CNST_CHNG_TRSTN_VRSN_NBR | L79: Consist change transition version number | M79: 1 | N79: Y | O79: train.train_cnst_dtl_rail_eqpt.cnst_chng_trstn_vrsn_nbr | P79: SADB | Q79: N
A80: Train_Detail | B80: 90 | C80: Train141 | D80: TrnCnstDtl | E80: MEDIUM | F80: N | G80: Y | H80: Location | J80: CNST_LCM_OPRSTS_ID | L80: Consist LCM operations ID | M80: NULL | N80: Y | O80: train.train_cnst_dtl_rail_eqpt.cnst_lcm_oprsts_id | P80: SADB | Q80: N
A81: Train_Detail | B81: 91 | C81: Train045 | D81: TrnLvlSmry | E81: HIGH | F81: Y | G81: Y | H81: Location | J81: SUBDIVISION | K81: Both DEPART_FSAC and ARRIVE_FSAC belongs to correct location group | L81: Subdivision name | M81: LAREDO | N81: Y | O81: dm_dim.gis_orgn_dstntn_mlg_by_stprv.sbdvsn_nm | P81: MDM | Q81: N
A82: Train_Detail | B82: 92 | C82: Train058 | D82: BMR(Qlik) | E82: HIGH | F82: Y | G82: Y | H82: Location | J82: District | K82: Both DEPART_FSAC and ARRIVE_FSAC belongs to correct location group | L82: District name | M82: Southwest | N82: Y | O82: dm_dim.dim_subdvsn_zone | P82: MDM | Q82: N
A83: Train_Detail | B83: 93 | C83: Train054 | D83: TrnLvlSmry | E83: HIGH | F83: Y | G83: Y | H83: Location | J83: ZONE | K83: Both DEPART_FSAC and ARRIVE_FSAC belongs to correct location group | L83: Zone name | M83: SOUTHWEST | N83: Y | O83: dm_dim.dim_subdvsn_zone.zone dm_dim.dim_subdvsn .zone | P83: MDM | Q83: Y
A84: Train_Detail | B84: 94 | C84: Train047 | D84: TrnLvlSmry | E84: HIGH | F84: Y | G84: Y | H84: Location | J84: DIVISION | K84: Both DEPART_FSAC and ARRIVE_FSAC belongs to correct location group | L84: Division name | M84: South West | N84: Y | O84: dm_dim.dim_subdvsn_zone.division_nm dm_dim.dim_subdvsn .division_nm | P84: MDM | Q84: Y
A85: Train_Detail | B85: 95 | C85: Train046 | D85: TrnLvlSmry | E85: HIGH | F85: Y | G85: Y | H85: Location | J85: REGION | K85: Both DEPART_FSAC and ARRIVE_FSAC belongs to correct location group | L85: Region name | M85: Mexico | N85: Y | O85: dm_dim.dim_subdvsn_zone.region dm_dim.dim_subdvsn .region | P85: MDM | Q85: Y
A86: Train_Detail | B86: 96 | C86: Train057 | D86: BMR(Qlik) | E86: HIGH | F86: Y | G86: Y | H86: Location | J86: Country | K86: Both DEPART_FSAC and ARRIVE_FSAC belongs to correct location group | L86: Country name | M86: US | N86: Y | O86: trkfc.trkfc_trstn.fsac_cd dm_dim.dim_location | P86: SADB | Q86: N
A87: Train_Detail | B87: 97 | C87: Train055 | D87: BMR(Qlik) | E87: HIGH | F87: Y | G87: Y | H87: Location | J87: Company | K87: Both DEPART_FSAC and ARRIVE_FSAC belongs to correct location group | L87: Company name | M87: KCSR | N87: TBA | O87: Company name same as rail line
A88: Train_Detail | B88: 98 | C88: Train056 | D88: BMR(Qlik) | E88: HIGH | F88: Y | G88: Y | H88: Location | J88: RAIL_LINE | K88: Both DEPART_FSAC and ARRIVE_FSAC belongs to correct location group | L88: Rail line name | M88: KCSR | N88: Y | O88: dm_dim.dim_location | P88: MDM | Q88: N
A89: Train_Detail | B89: 99 | C89: Train098 | D89: TrnCnstDtl | E89: LOW | F89: N | G89: Y | H89: Location | J89: ON_JNCTN_SCAC_CD | L89: On junction SCAC code | M89: CPRS | N89: Y | O89: train.train_cnst_dtl_rail_eqpt.on_jnctn_scac_cd | P89: SADB | Q89: N
A90: Train_Detail | B90: 100 | C90: Train102 | D90: TrnCnstDtl | E90: LOW | F90: N | G90: Y | H90: Location | J90: OFF_JNCTN_SCAC_CD | L90: Off junction SCAC code | M90: CPRS | N90: Y | O90: train.train_cnst_dtl_rail_eqpt.off_jnctn_scac_cd | P90: SADB | Q90: N
A91: Train_Detail | B91: 101 | C91: Train099 | D91: TrnCnstDtl | E91: LOW | F91: N | G91: Y | H91: Location | J91: ON_JNCTN_FSAC_CD | L91: On junction FSAC code | M91: 5770 | N91: Y | O91: train.train_cnst_dtl_rail_eqpt.on_jnctn_fsac_cd | P91: SADB | Q91: N
A92: Train_Detail | B92: 102 | C92: Train103 | D92: TrnCnstDtl | E92: LOW | F92: N | G92: Y | H92: Location | J92: OFF_JNCTN_FSAC_CD | L92: Off junction FSAC code | M92: 4541 | N92: Y | O92: train.train_cnst_dtl_rail_eqpt.off_jnctn_fsac_cd | P92: SADB | Q92: N
A93: Train_Detail | B93: 103 | C93: Train100 | D93: TrnCnstDtl | E93: LOW | F93: N | G93: Y | H93: Location | J93: ON_JNCTN_TRSTN_VRSN_NBR | L93: On junction transition version number | M93: 1 | N93: Y | O93: train.train_cnst_dtl_rail_eqpt.on_jnctn_trstn_vrsn_nbr | P93: SADB | Q93: N
A94: Train_Detail | B94: 104 | C94: Train104 | D94: TrnCnstDtl | E94: LOW | F94: N | G94: Y | H94: Location | J94: OFF_JNCTN_TRSTN_VRSN_NBR | L94: Off junction transition version number | M94: 10 | N94: Y | O94: train.train_cnst_dtl_rail_eqpt.off_jnctn_trstn_vrsn_nbr | P94: SADB | Q94: N
A95: Train_Detail | B95: 105 | C95: Train101 | D95: TrnCnstDtl | E95: MEDIUM | F95: N | G95: Y | H95: Location | J95: RCVD_FROM_SCAC_CD | L95: Received from SCAC code | M95: KCSM | N95: Y | O95: train.train_cnst_dtl_rail_eqpt.rcvd_from_scac_cd | P95: SADB | Q95: N
A96: Train_Detail | B96: 106 | C96: Train105 | D96: TrnCnstDtl | E96: MEDIUM | F96: N | G96: Y | H96: Location | J96: DLVR_TO_SCAC_CD | L96: Deliver to SCAC code | M96: CPRS | N96: Y | O96: train.train_cnst_dtl_rail_eqpt.dlvr_to_scac_cd | P96: SADB | Q96: N
A97: Train_Detail | B97: 107 | C97: Train110 | D97: TrnCnstDtl | E97: MEDIUM | F97: N | G97: Y | H97: Location | J97: ORNTN_CD | L97: Orientation code | M97: NULL | N97: Y | O97: train.train_cnst_dtl_rail_eqpt.orntn_cd | P97: SADB | Q97: N
A98: Train_Detail | B98: 108 | C98: Train063 | D98: BMR(Qlik) | E98: HIGH | F98: Y | G98: Y | H98: Location | J98: Depart Station | K98: Depart Station <> Arrive Statoin in same row of data | L98: Departure station name | M98: LAREDO BRIDGE | N98: TBA | O98: Could be added in silver layer via lookup from dim_location | R98: 1
A99: Train_Detail | B99: 109 | C99: Train064 | D99: BMR(Qlik) | E99: HIGH | F99: Y | G99: Y | H99: Location | J99: Arrival Station | K99: Depart Station <> Arrive Statoin in same row of data | L99: Arrival station name | M99: LAREDO YARD | N99: TBA | O99: Could be added in silver layer via lookup from dim_location | R99: 1
A100: Train_Detail | B100: 110 | C100: Train151 | D100: BrandNew | E100: MEDIUM | F100: Y | G100: Y | H100: Location | J100: DEPART_RAIL_LINE | K100: DEPART_FSAC belongs to correct location dimension | L100: Rail line name of the station where train segment started | M100: KCSR | N100: Y | O100: Lookup from dim_location in silver layer | R100: N/A
...

Sheet NETWORK_COVERAGE
B1: PoC - Network Coverage
B3: Sub | C3: STATION | D3: SEGMENT | E3: DIRECTION | F3: FSAC | G3: MILES | H3: ELAPSED_HRS | I3: Time_Audit | J3: SPEED | K3: Speed Audit (0 - 80mph) | L3: AWS | M3: AWS Audit | N3: SADB & AZURE | O3: SADB Audit | P3: UNIONED NETWORK | Q3: Network Audit
B4: CASCADE | C4: VANCOUVER | E4: E | F4: 9700 | L4: X | M4: Fail | N4: Y | O4: Pass | P4: Y | Q4: Pass
B5: CASCADE | C5: DUNLEVY | D5: =C4&"-"&C5 -> VANCOUVER-DUNLEVY | E5: E | F5: 9768 | G5: 0.4 | H5: -0.02 | I5: Fail | J5: =G5/H5 -> -20 | K5: Fail | L5: Y | M5: Pass | N5: X | O5: Fail | P5: Y | Q5: Pass
B6: CASCADE | C6: HEATLEY | D6: =C5&"-"&C6 -> DUNLEVY-HEATLEY | E6: E | F6: 9769 | G6: 0.5 | H6: 0.04 | I6: Pass | J6: =G6/H6 -> 12.5 | K6: Pass | L6: Y | M6: Pass | N6: X | O6: Fail | P6: Y | Q6: Pass
B7: CASCADE | C7: WILLISTON | D7: =C6&"-"&C7 -> HEATLEY-WILLISTON | E7: E | F7: 9774 | G7: 0.9 | H7: 0.05 | I7: Pass | J7: =G7/H7 -> 18 | K7: Pass | L7: Y | M7: Pass | N7: X | O7: Fail | P7: Y | Q7: Pass
B8: CASCADE | C8: RENFREW | D8: =C7&"-"&C8 -> WILLISTON-RENFREW | E8: E | F8: 9781 | G8: 1 | H8: 0.02 | I8: Pass | J8: =G8/H8 -> 50 | K8: Pass | L8: Y | M8: Pass | N8: X | O8: Fail | P8: Y | Q8: Pass
B9: CASCADE | C9: SECOND NARROWS | D9: =C8&"-"&C9 -> RENFREW-SECOND NARROWS | E9: E | F9: 9705 | G9: 0.7 | H9: 0.02 | I9: Pass | J9: =G9/H9 -> 35 | K9: Pass | L9: Y | M9: Pass | N9: X | O9: Fail | P9: Y | Q9: Pass
B10: CASCADE | C10: BARNET | D10: =C9&"-"&C10 -> SECOND NARROWS-BARNET | E10: E | F10: 9695 | G10: 0.4 | H10: 0.02 | I10: Pass | J10: =G10/H10 -> 20 | K10: Pass | L10: Y | M10: Pass | N10: X | O10: Fail | P10: Y | Q10: Pass
B11: CASCADE | C11: CASSIN | D11: =C10&"-"&C11 -> BARNET-CASSIN | E11: E | F11: 9657 | G11: 0.9 | H11: 0.01 | I11: Pass | J11: =G11/H11 -> 90 | K11: Fail | L11: Y | M11: Pass | N11: X | O11: Fail | P11: Y | Q11: Pass
B12: CASCADE | C12: PORT MOODY | D12: =C11&"-"&C12 -> CASSIN-PORT MOODY | E12: E | F12: 9693 | G12: 0.1 | H12: 0.02 | I12: Pass | J12: =G12/H12 -> 5 | K12: Pass | L12: X | M12: Fail | N12: X | O12: Fail | P12: X | Q12: Fail
B13: CASCADE | C13: SETO | D13: =C12&"-"&C13 -> PORT MOODY-SETO | E13: E | F13: 9687 | G13: 0.2 | H13: 0.02 | I13: Pass | J13: =G13/H13 -> 10 | K13: Pass | L13: Y | M13: Pass | N13: X | O13: Fail | P13: Y | Q13: Pass
B14: CASCADE | C14: WESTWOOD | D14: =C13&"-"&C14 -> SETO-WESTWOOD | E14: E | F14: 9766 | G14: 0.9 | H14: 0.02 | I14: Pass | J14: =G14/H14 -> 45 | K14: Pass | L14: Y | M14: Pass | N14: X | O14: Fail | P14: Y | Q14: Pass
B15: CASCADE | C15: MACAULAY | D15: =C14&"-"&C15 -> WESTWOOD-MACAULAY | E15: E | F15: 9688 | G15: 0.2 | H15: 0.02 | I15: Pass | J15: =G15/H15 -> 10 | K15: Pass | L15: Y | M15: Pass | N15: X | O15: Fail | P15: Y | Q15: Pass
B16: CASCADE | C16: COQUITLAM | D16: =C15&"-"&C16 -> MACAULAY-COQUITLAM | E16: E | F16: 9684 | G16: 0.7 | H16: 0.02 | I16: Pass | J16: =G16/H16 -> 35 | K16: Pass | L16: X | M16: Fail | N16: Y | O16: Pass | P16: Y | Q16: Pass
C18: FOUND ONLY IN SADB
C19: FOUND ONLY IN AWS

Sheet Jira
A1: Team | B1: Assignee | C1: Issue-key | D1: Status | E1: ETA | F1: Summary | G1: Description | W1: Summary | X1: Issue key | Y1: Issue id | Z1: Parent id | AA1: Issue Type | AB1: Status | AC1: Project key | AD1: Project name | AE1: Project type | AF1: Project lead | AG1: Project description | AH1: Project url | AI1: Priority | AJ1: Resolution | AK1: Assignee | AL1: Reporter | AM1: Creator | AN1: Created | AO1: Updated | AP1: Last Viewed | AQ1: Resolved | AR1: Affects Version/s | AS1: Fix Version/s | AT1: Component/s | AU1: Due Date | AV1: Votes | AW1: Labels | AX1: Description | AY1: Watchers | AZ1: Watchers | BA1: Watchers | BB1: Watchers | BC1: Watchers | BD1: Log Work | BE1: Original Estimate | BF1: Remaining Estimate | BG1: Time Spent | BH1: Work Ratio | BI1: Σ Original Estimate | BJ1: Σ Remaining Estimate | BK1: Σ Time Spent | BL1: Inward issue link (Blocks) | BM1: Outward issue link (Relates) | BN1: Attachment | BO1: Attachment | BP1: Custom field (Acceptance Criteria) | BQ1: Custom field (Build Number) | BR1: Custom field (Business Value) | BS1: Custom field (Defect Type) | BT1: Custom field (DeployToTest) | BU1: Custom field (Epic Link) | BV1: Custom field (Epic/Theme) | BW1: Custom field (External Story Number) | BX1: Custom field (External issue ID) | BY1: Custom field (Flagged) | BZ1: Custom field (Original story points) | CA1: Custom field (Parent Link) | CB1: Custom field (Rank) | CC1: Custom field (Requested by) | CD1: Sprint | CE1: Custom field (Story Points) | CF1: Custom field (Target end) | CG1: Custom field (Target start) | CH1: Custom field (Team) | CI1: Custom field (qTest Defect Code) | CJ1: Comment | CK1: Comment | CL1: Comment | CM1: Comment | CN1: Comment | CO1: Comment | CP1: Comment | CQ1: Comment | CR1: Comment | CS1: Comment | CT1: Comment
A2: =VLOOKUP(AK2,members!$A:$C,3,FALSE) -> MDM | B2: =VLOOKUP(AK2,members!$A:$C,2,FALSE) -> Nikhil | C2: =X2 -> RPD-82 | D2: =AB2 -> To Do | E2: =AU2 -> 46002 | F2: =W2 -> DIM equipment mapping document provision to QE team (VishnuB) | G2: =AX2 -> [~seh0018] to provide mapping documents to [~bor0475] [~sid0070] and [~sel0052] | W2: DIM equipment mapping document provision to QE team (VishnuB) | X2: RPD-82 | Y2: 190493 | Z2: 186078 | AA2: Sub-task | AB2: To Do | AC2: RPD | AD2: Rail360 Product Development | AE2: software | AF2: las0044 | AI2: 3-High | AK2: seh0018 | AL2: woo0234 | AM2: woo0234 | AN2: 46001.48 | AO2: 46001.48 | AP2: 46002.459 | AU2: 46002 | AV2: 0 | AW2: Rail360 | AX2: [~seh0018] to provide mapping documents to [~bor0475] [~sid0070] and [~sel0052] | AY2: woo0234 | CB2: 1|i0i838:
A3: =VLOOKUP(AK3,members!$A:$C,3,FALSE) -> ETL | B3: =VLOOKUP(AK3,members!$A:$C,2,FALSE) -> Naveen | C3: =X3 -> RPD-79 | D3: =AB3 -> In Progress | E3: =AU3 -> 46000 | F3: =W3 -> Data Ingestion based on Squadron's analysis | G3: =AX3 -> [~knxn12] to complete by working with Squadron for data ingestion. | W3: Data Ingestion based on Squadron's analysis | X3: RPD-79 | Y3: 190165 | AA3: Task | AB3: In Progress | AC3: RPD | AD3: Rail360 Product Development | AE3: software | AF3: las0044 | AI3: 3-High | AK3: knxn12 | AL3: woo0234 | AM3: woo0234 | AN3: 45999.478 | AO3: 46001.476 | AP3: 46001.475 | AU3: 46000 | AV3: 0 | AW3: Rail360 | AX3: [~knxn12] to complete by working with Squadron for data ingestion. | AY3: woo0234 | CB3: 1|i0i63g: | CJ3: 10/Dec/25 11:24 AM;woo0234;[~knxn12] to discuss with [~ngu0018] for injection options regarding historical data refreshing strategies. regarding Oracle/ IICS / CDC;;; | CK3: 10/Dec/25 11:25 AM;woo0234;[~mor0460] supports work sametime for tables that has less sensitivity [~tha0073] [~pat0606] to work together.;;;
A4: =VLOOKUP(AK4,members!$A:$C,3,FALSE) -> BDA | B4: =VLOOKUP(AK4,members!$A:$C,2,FALSE) -> VPS | C4: =X4 -> RPD-69 | D4: =AB4 -> In Progress | E4: =AU4 -> 45996 | F4: =W4 -> ER Diagram for Gold Layer fields | G4: =AX4 -> Data model needed | W4: ER Diagram for Gold Layer fields | X4: RPD-69 | Y4: 189315 | AA4: Task | AB4: In Progress | AC4: RPD | AD4: Rail360 Product Development | AE4: software | AF4: las0044 | AI4: 3-High | AK4: cvps10 | AL4: cvps10 | AM4: cvps10 | AN4: 45993.477 | AO4: 46002.438 | AP4: 46001.469 | AU4: 45996 | AV4: 0 | AX4: Data model needed | AY4: cvps10 | AZ4: woo0234 | CB4: 1|i0i1z8: | CJ4: 09/Dec/25 11:10 AM;woo0234;[~cvps10] provided ER diagram to [~pat0606] on 12/8 for review_x000D_ _x000D_ ;;; | CK4: 11/Dec/25 10:31 AM;cvps10;Will create data model for the entire gold layer fields. That's why putting it in progress. Awaiting access to Erwin;;;
A5: =VLOOKUP(AK5,members!$A:$C,3,FALSE) -> ETL | B5: =VLOOKUP(AK5,members!$A:$C,2,FALSE) -> Naveen | C5: =X5 -> RPD-73 | D5: =AB5 -> In Progress | E5: =AU5 -> 46003 | F5: =W5 -> MDM set up - Snowflake account and its representative needed | G5: =AX5 -> [~seh0018] requires an answer from Squadron to identify whom in Squadron covered / worked out to set up connection (this is about dimension table such as dim equipment, dim location, dim commodity, and dim customers)_x000D_ _x000D_ _x000D_ _x000D_ [~knxn12] / [~seh0018] / [~tha0073] / [~dan0243] to discuss 12/5 | W5: MDM set up - Snowflake account and its representative needed | X5: RPD-73 | Y5: 190021 | Z5: 186070 | AA5: Sub-task | AB5: In Progress | AC5: RPD | AD5: Rail360 Product Development | AE5: software | AF5: las0044 | AI5: 3-High | AK5: knxn12 | AL5: woo0234 | AM5: woo0234 | AN5: 45996.463 | AO5: 46001.467 | AP5: 46001.467 | AU5: 46003 | AV5: 0 | AW5: Rail360 | AX5: [~seh0018] requires an answer from Squadron to identify whom in Squadron covered / worked out to set up connection (this is about dimension table such as dim equipment, dim location, dim commodity, and dim customers)_x000D_ _x000D_ _x000D_ _x000D_ [~knxn12] / [~seh0018] / [~tha0073] / [~dan0243] to discuss 12/5 | AY5: dan0243 | AZ5: woo0234 | CB5: 1|i0i57w: | CJ5: 10/Dec/25 10:32 AM;dan0243;[~knxn12] - Can you please help here to create a service account and provide the details to Nikhil. Kindly let us know in case you need any help in creation of SA.;;; | CK5: 10/Dec/25 11:13 AM;woo0234;Naveen to own provision of account to MDM team for both public and private keys for Squadron members.;;;
A6: =VLOOKUP(AK6,members!$A:$C,3,FALSE) -> Squadron | B6: =VLOOKUP(AK6,members!$A:$C,2,FALSE) -> Harshil Patel | C6: =X6 -> RPD-65 | D6: =AB6 -> In Progress | E6: =AU6 -> 46002 | F6: =W6 -> SnowFlake ETL Plan - Bronze to Silver solution to provide - document / email needed | G6: =AX6 -> Document that_x000D_ _x000D_ includes methodologies out of below example options._x000D_ _x000D_ include data models for Silver Layers_x000D_ _x000D_ _x000D_ _x000D_ 1) DBT_x000D_ _x000D_ 2) Store Procedures_x000D_ _x000D_ 3) Snow Park | W6: SnowFlake ETL Plan - Bronze to Silver solution to provide - document / email needed | X6: RPD-65 | Y6: 189013 | AA6: Task | AB6: In Progress | AC6: RPD | AD6: Rail360 Product Development | AE6: software | AF6: las0044 | AI6: 3-High | AK6: pat0606 | AL6: woo0234 | AM6: woo0234 | AN6: 45988.469 | AO6: 46001.465 | AP6: 46001.465 | AU6: 46002 | AV6: 0 | AW6: Rail360 | AX6: Document that_x000D_ _x000D_ includes methodologies out of below example options._x000D_ _x000D_ include data models for Silver Layers_x000D_ _x000D_ _x000D_ _x000D_ 1) DBT_x000D_ _x000D_ 2) Store Procedures_x000D_ _x000D_ 3) Snow Park | AY6: cvps10 | AZ6: dan0243 | BA6: woo0234 | BN6: 10/Dec/25 10:11 AM;dan0243;Snowflake Native Capabilities_v2.docx;https://jira.cpr.ca/secure/attachment/166180/Snowflake+Native+Capabilities_v2.docx | CB6: 1|i0i064: | CJ6: 03/Dec/25 11:07 AM;cvps10;Awaiting transformation plan and ETL tool;;; | CK6: 09/Dec/25 10:09 AM;dan0243;9/12 - This is dependent on the data modeling documents which we are closing working on.;;; | CL6: 09/Dec/25 11:23 AM;woo0234;[~pat0606] will share document today 12/9;;; | CM6: 10/Dec/25 10:09 AM;dan0243;10/12 - The detailed documents on the transformation part have been sent across once we finalized the approach based on data model readiness._x000D_ _x000D_ _x000D_ _x000D_ I am attaching the sheet here as well for reference.[^Snowflake Native Capabilities_v2.docx];;; | CN6: 10/Dec/25 11:09 AM;woo0234;follow up a call 12/11 among [~ngu0018] [~moh0106] including both architect and Squadron/Celebal members;;;
A7: =VLOOKUP(AK7,members!$A:$C,3,FALSE) -> ETL | B7: =VLOOKUP(AK7,members!$A:$C,2,FALSE) -> Naveen | C7: =X7 -> RPD-81 | D7: =AB7 -> To Do | E7: =AU7 -> 46001 | F7: =W7 -> Data injection job to start from source to bronze | G7: =AX7 -> 0 | W7: Data injection job to start from source to bronze | X7: RPD-81 | Y7: 190352 | AA7: Task | AB7: To Do | AC7: RPD | AD7: Rail360 Product Development | AE7: software | AF7: las0044 | AI7: 3-High | AK7: knxn12 | AL7: woo0234 | AM7: woo0234 | AN7: 46000.477 | AO7: 46000.477 | AP7: 46001.459 | AU7: 46001 | AV7: 0 | AW7: Rail360 | AY7: woo0234 | CB7: 1|i0i78c:
A8: =VLOOKUP(AK8,members!$A:$C,3,FALSE) -> ETL | B8: =VLOOKUP(AK8,members!$A:$C,2,FALSE) -> Jatinder | C8: =X8 -> RPD-29 | D8: =AB8 -> In Progress | E8: =AU8 -> 46052 | F8: =W8 -> Identifying solutions to bring track/mileage info for Regulatory Tonnage Proj. | G8: =AX8 -> in the past, during the development of reg tonnage with FTI, csv file was created in order to provide detailed mapping of mileages and types of track information in CPKC network._x000D_ _x000D_ [~sin0404] to interview key stakeholders (Karthik / Jincy) to obtain source file._x000D_ _x000D_ _x000D_ _x000D_ Track level reporting is mainly sourcing legacy BMR data as per [~sau0093] so track information from business team are not fully incorporated in CPKC's data set. | W8: Identifying solutions to bring track/mileage info for Regulatory Tonnage Proj. | X8: RPD-29 | Y8: 186287 | AA8: Task | AB8: In Progress | AC8: RPD | AD8: Rail360 Product Development | AE8: software | AF8: las0044 | AI8: 3-High | AK8: sin0404 | AL8: woo0234 | AM8: woo0234 | AN8: 45954.482 | AO8: 46001.042 | AP8: 46001.458 | AU8: 46052 | AV8: 0 | AW8: Rail360 | AX8: in the past, during the development of reg tonnage with FTI, csv file was created in order to provide detailed mapping of mileages and types of track information in CPKC network._x000D_ _x000D_ [~sin0404] to interview key stakeholders (Karthik / Jincy) to obtain source file._x000D_ _x000D_ _x000D_ _x000D_ Track level reporting is mainly sourcing legacy BMR data as per [~sau0093] so track information from business team are not fully incorporated in CPKC's data set. | AY8: cvps10 | AZ8: woo0234 | CB8: 1|i0hkbg: | CJ8: 03/Dec/25 11:24 AM;cvps10;Phase 1 only 2 canadian subs, so difficult to test proximity with regulatory tonnage. Will look at it after first draft of tonnage is ready. We can compare two canadian subdivision data mid Jan (after Rail360 is ready for UAT);;;
A9: =VLOOKUP(AK9,members!$A:$C,3,FALSE) -> BDA | B9: =VLOOKUP(AK9,members!$A:$C,2,FALSE) -> Sangtae | C9: =X9 -> RPD-50 | D9: =AB9 -> In Progress | E9: =AU9 -> 46010 | F9: =W9 -> Product Design review from Squadron | G9: =AX9 -> 0 | W9: Product Design review from Squadron | X9: RPD-50 | Y9: 188011 | AA9: Task | AB9: In Progress | AC9: RPD | AD9: Rail360 Product Development | AE9: software | AF9: las0044 | AI9: 3-High | AK9: woo0234 | AL9: ana0017 | AM9: ana0017 | AN9: 45974.465 | AO9: 46001.041 | AP9: 46001.041 | AU9: 46010 | AV9: 0 | AY9: ana0017 | AZ9: cvps10 | CB9: 1|i0hub8: | CJ9: 02/Dec/25 11:34 AM;cvps10;In progress - regulatory reporting info to be fulfilled;;;
A10: =VLOOKUP(AK10,members!$A:$C,3,FALSE) -> Architect | B10: =VLOOKUP(AK10,members!$A:$C,2,FALSE) -> Karthik | C10: =X10 -> RPD-67 | D10: =AB10 -> To Do | E10: =AU10 -> 45992 | F10: =W10 -> CSN review for direction (regarding issues) | G10: =AX10 -> plan to navigate our options regarding_x000D_ _x000D_ duplicates_x000D_ _x000D_ changes in CSN during single trip | W10: CSN review for direction (regarding issues) | X10: RPD-67 | Y10: 189059 | AA10: Task | AB10: To Do | AC10: RPD | AD10: Rail360 Product Development | AE10: software | AF10: las0044 | AI10: 3-High | AK10: rav0018 | AL10: woo0234 | AM10: woo0234 | AN10: 45989.473 | AO10: 45989.473 | AP10: 46001.022 | AU10: 45992 | AV10: 0 | AW10: Rail360 | AX10: plan to navigate our options regarding_x000D_ _x000D_ duplicates_x000D_ _x000D_ changes in CSN during single trip | AY10: woo0234 | CB10: 1|i0i0fo:
A11: =VLOOKUP(AK11,members!$A:$C,3,FALSE) -> QE | B11: =VLOOKUP(AK11,members!$A:$C,2,FALSE) -> Manooj | C11: =X11 -> RPD-42 | D11: =AB11 -> In Progress | E11: =AU11 -> 45971 | F11: =W11 -> UAT related ideas gathering / high level scenarios | G11: =AX11 -> [~sel0052] [~sid0070] will contact/introduce QA team to start getting involved. (test strategy sharing may be starting point)_x000D_ _x000D_ [~woo0234] will set up 40-45 mins call with [~ste0370] 's team and QA team by 2nd week of November. | W11: UAT related ideas gathering / high level scenarios | X11: RPD-42 | Y11: 187294 | Z11: 186087 | AA11: Sub-task | AB11: In Progress | AC11: RPD | AD11: Rail360 Product Development | AE11: software | AF11: las0044 | AI11: 3-High | AK11: sel0052 | AL11: woo0234 | AM11: woo0234 | AN11: 45966.485 | AO11: 45993.481 | AP11: 46001.022 | AU11: 45971 | AV11: 0 | AW11: Rail360 | AX11: [~sel0052] [~sid0070] will contact/introduce QA team to start getting involved. (test strategy sharing may be starting point)_x000D_ _x000D_ [~woo0234] will set up 40-45 mins call with [~ste0370] 's team and QA team by 2nd week of November. | AY11: ana0017 | AZ11: cvps10 | BA11: woo0234 | CB11: 1|i0hpxw: | CJ11: 13/Nov/25 11:06 AM;ana0017;Team is Meeting with Business at 1030 MST 13/11 to discuss._x000D_ _x000D_ ;;; | CK11: 19/Nov/25 11:22 AM;cvps10;Awaiting feedback on data quality from Paul's team_x000D_ And UAT discussion yet to be done;;; | CL11: 02/Dec/25 11:32 AM;cvps10;Metrics threshold discussion with Paul and team - Sangtae;;;
A12: =VLOOKUP(AK12,members!$A:$C,3,FALSE) -> ETL | B12: =VLOOKUP(AK12,members!$A:$C,2,FALSE) -> Naveen | C12: =X12 -> RPD-55 | D12: =AB12 -> In Progress | E12: =AU12 -> 45981 | F12: =W12 -> Service Account SET UP request | G12: =AX12 -> ACC/DEV/PROD_x000D_ * MDW ( A8087)_x000D_ * EDW (ORAA414)_x000D_ * SADB (ORAA430)_x000D_ * Snowflake_x000D_ * Azure_x000D_ * AWS_x000D_ _x000D_ | W12: Service Account SET UP request | X12: RPD-55 | Y12: 188639 | Z12: 188628 | AA12: Sub-task | AB12: In Progress | AC12: RPD | AD12: Rail360 Product Development | AE12: software | AF12: las0044 | AI12: 3-High | AK12: knxn12 | AL12: woo0234 | AM12: woo0234 | AN12: 45981.482 | AO12: 45986.471 | AP12: 46001.022 | AU12: 45981 | AV12: 0 | AW12: Rail360 | AX12: ACC/DEV/PROD_x000D_ * MDW ( A8087)_x000D_ * EDW (ORAA414)_x000D_ * SADB (ORAA430)_x000D_ * Snowflake_x000D_ * Azure_x000D_ * AWS_x000D_ _x000D_ | AY12: woo0234 | CB12: 1|i0hy1g: | CJ12: 20/Nov/25 1:29 PM;woo0234;requested as RAILSDC name to be approved by [~gho0014] / followed by [~las0044] ;;; | CK12: 21/Nov/25 11:11 AM;woo0234;[~knxn12] to re-create request based on service team's format.;;; | CL12: 24/Nov/25 11:23 AM;woo0234;SADB/EDW DEV created_x000D_ _x000D_ MDW to be created;;; | CM12: 25/Nov/25 11:18 AM;woo0234;Oracle: use same account_x000D_ _x000D_ In discussion with Service Fulfillment Team.;;;
A13: =VLOOKUP(AK13,members!$A:$C,3,FALSE) -> Cloud | B13: =VLOOKUP(AK13,members!$A:$C,2,FALSE) -> Ruben | C13: =X13 -> RPD-8 | D13: =AB13 -> Done | E13: =AU13 -> 45954 | F13: =W13 -> AWS access grant for Rail 360 | G13: =AX13 -> Obtain Access to AWS for 3 core data sources, Wi-Tronics, Sentinel, and Geo-fence for all participants (need an access to table) | W13: AWS access grant for Rail 360 | X13: RPD-8 | Y13: 186081 | AA13: Task | AB13: Done | AC13: RPD | AD13: Rail360 Product Development | AE13: software | AF13: las0044 | AI13: 3-High | AJ13: Done | AK13: gue0154 | AL13: woo0234 | AM13: woo0234 | AN13: 45951.583 | AO13: 45982.474 | AP13: 46001.02 | AQ13: 45982.474 | AU13: 45954 | AV13: 0 | AW13: Rail360 | AX13: Obtain Access to AWS for 3 core data sources, Wi-Tronics, Sentinel, and Geo-fence for all participants (need an access to table) | AY13: cvps10 | AZ13: woo0234 | CB13: 1|i0hj38: | CJ13: 28/Oct/25 11:40 AM;woo0234;[~gue0154] and [~bry0059] will provide 2 table access that includes train and locomotive information. ;;; | CK13: 19/Nov/25 11:11 AM;cvps10;AWS access to be granted to Squadron folks.;;;
A14: =VLOOKUP(AK14,members!$A:$C,3,FALSE) -> QE | B14: =VLOOKUP(AK14,members!$A:$C,2,FALSE) -> Raheel | C14: =X14 -> RPD-68 | D14: =AB14 -> Done | E14: 46051 | F14: =W14 -> Raheel to discuss with Jatinder/Naveen for Source to Bronze pipeline builiding | G14: =AX14 -> there should be threshold and monitoring of performance related to data transfer from sources to bronze layer monitored/governed by CPKC's system/employees._x000D_ _x000D_ need input / plan and employees in charge prior to developing. | W14: Raheel to discuss with Jatinder/Naveen for Source to Bronze pipeline builiding | X14: RPD-68 | Y14: 189060 | AA14: Task | AB14: Done | AC14: RPD | AD14: Rail360 Product Development | AE14: software | AF14: las0044 | AI14: 3-High | AJ14: Done | AK14: sid0070 | AL14: woo0234 | AM14: woo0234 | AN14: 45989.479 | AO14: 45993.486 | AP14: 46001.019 | AQ14: 45993.486 | AU14: 45992 | AV14: 0 | AW14: Rail360 | AX14: there should be threshold and monitoring of performance related to data transfer from sources to bronze layer monitored/governed by CPKC's system/employees._x000D_ _x000D_ need input / plan and employees in charge prior to developing. | AY14: woo0234 | CB14: 1|i0i0fw: | CJ14: 01/Dec/25 11:06 AM;woo0234;meeting to be held for available testing options prior to all data pipeline is built mainly bronze side data but not limited to led by [~sid0070] with [~knxn12] ;;;
A15: =VLOOKUP(AK15,members!$A:$C,3,FALSE) -> Architect | B15: =VLOOKUP(AK15,members!$A:$C,2,FALSE) -> David | C15: =X15 -> RPD-76 | D15: =AB15 -> In Progress | E15: =AU15 -> 46007 | F15: =W15 -> Data Modeling Session among Architect, Celebal, and Squadron | G15: =AX15 -> [~ngu0018] to work with celebal and squadron to understand their approaches regarding transition from bronze to gold.... | W15: Data Modeling Session among Architect, Celebal, and Squadron | X15: RPD-76 | Y15: 190158 | AA15: Task | AB15: In Progress | AC15: RPD | AD15: Rail360 Product Development | AE15: software | AF15: las0044 | AI15: 3-High | AK15: ngu0018 | AL15: woo0234 | AM15: woo0234 | AN15: 45999.461 | AO15: 46001.434 | AP15: 46001.018 | AU15: 46007 | AV15: 0 | AW15: Rail360 | AX15: [~ngu0018] to work with celebal and squadron to understand their approaches regarding transition from bronze to gold.... | AY15: ngu0018 | AZ15: woo0234 | CB15: 1|i0i62c: | CJ15: 10/Dec/25 10:18 AM;ngu0018;Had to reschedule meeting to Dec 16th due to conflicts on the original schedule on Dec 6th. Reason to push all the way to next week is Karthik is on AV from Dec 10 -12 and we need his participation and input. ;;;
A16: =VLOOKUP(AK16,members!$A:$C,3,FALSE) -> BDA | B16: =VLOOKUP(AK16,members!$A:$C,2,FALSE) -> VPS | C16: =X16 -> RPD-62 | D16: =AB16 -> Done | E16: =AU16 -> 45985 | F16: =W16 -> Logic review with Manzoor | G16: =AX16 -> [~sau0093] and [~cvps10] to reach out to [~bab0040] to review set/lift logic_x000D_ _x000D_ Use workorder information_x000D_ _x000D_ consider using OPTRN TABLE and TRAIN.TRAIN_ACTUAL_WORK_x000D_ _x000D_ YARD_RPRTNG_IND = 'Y' for b-flag station in TRAIN_PLAN_EVENT table | W16: Logic review with Manzoor | X16: RPD-62 | Y16: 188704 | Z16: 188014 | AA16: Sub-task | AB16: Done | AC16: RPD | AD16: Rail360 Product Development | AE16: software | AF16: las0044 | AI16: 3-High | AJ16: Done | AK16: cvps10 | AL16: woo0234 | AM16: woo0234 | AN16: 45982.472 | AO16: 45992.471 | AP16: 46001.018 | AQ16: 45992.471 | AU16: 45985 | AV16: 0 | AX16: [~sau0093] and [~cvps10] to reach out to [~bab0040] to review set/lift logic_x000D_ _x000D_ Use workorder information_x000D_ _x000D_ consider using OPTRN TABLE and TRAIN.TRAIN_ACTUAL_WORK_x000D_ _x000D_ YARD_RPRTNG_IND = 'Y' for b-flag station in TRAIN_PLAN_EVENT table | AY16: bab0040 | AZ16: woo0234 | CB16: 1|i0hyf8: | CJ16: 21/Nov/25 3:59 PM;bab0040;this is the query used in train semantic for lift setoff in p8087:_x000D_ _x000D_ _x000D_ _x000D_ select LIFT_SET_IND,taw.TYES_TRAIN_ID, tll.TRAIN_CNST_ID, FSAC_CD, SCAC_CD, ROUTE_POINT_SQNC_NBR, _x000D_ coalesce(INTRMD_ROUTE_POINT_SQNC_NBR,0) as INTRMD_ROUTE_POINT_SQNC_NBR , count(*) as CNT_x000D_ from atm_train.TRAIN_ACTUAL_WORK taw with (nolock) --P89_x000D_ join (select * from DM_TRAIN.TRAIN_LAST_LCTN with (nolock) where EDW_UPDATE_TMS>= getdate()-1_x000D_ ) tll _x000D_ on taw.TYES_TRAIN_ID=tll.TYES_TRAIN_ID_x000D_ where taw.cnvyng_mark_cd is null_x000D_ group by LIFT_SET_IND, taw.TYES_TRAIN_ID, FSAC_CD,SCAC_CD, tll.TRAIN_CNST_ID,INTRMD_ROUTE_POINT_SQNC_NBR, ROUTE_POINT_SQNC_NBR;;;
A17: =VLOOKUP(AK17,members!$A:$C,3,FALSE) -> Squadron | B17: =VLOOKUP(AK17,members!$A:$C,2,FALSE) -> Hisham | C17: =X17 -> RPD-70 | D17: =AB17 -> Backlog | E17: =AU17 -> 46001 | F17: =W17 -> Identifying SAP tables for Rail360 | G17: =AX17 -> [~dan0243] to check with [~che0157] | W17: Identifying SAP tables for Rail360 | X17: RPD-70 | Y17: 189941 | AA17: Story | AB17: Backlog | AC17: RPD | AD17: Rail360 Product Development | AE17: software | AF17: las0044 | AI17: 3-High | AK17: dan0243 | AL17: dan0243 | AM17: dan0243 | AN17: 45994.62 | AO17: 45999.463 | AP17: 46001.016 | AU17: 46001 | AV17: 0 | AX17: [~dan0243] to check with [~che0157] | AY17: dan0243 | AZ17: woo0234 | CB17: 1|i0i4qs: | CJ17: 08/Dec/25 11:07 AM;woo0234;SAP BW is part of it;;;
A18: =VLOOKUP(AK18,members!$A:$C,3,FALSE) -> Squadron | B18: =VLOOKUP(AK18,members!$A:$C,2,FALSE) -> Babu | C18: =X18 -> RPD-78 | D18: =AB18 -> To Do | E18: =AU18 -> 46007 | F18: =W18 -> Snowflake Data Model Creation - Bronze to Silver | G18: =AX18 -> [~tha0073] to update data model within snowflake_x000D_ _x000D_ | W18: Snowflake Data Model Creation - Bronze to Silver | X18: RPD-78 | Y18: 190161 | Z18: 189315 | AA18: Sub-task | AB18: To Do | AC18: RPD | AD18: Rail360 Product Development | AE18: software | AF18: las0044 | AI18: 3-High | AK18: tha0073 | AL18: woo0234 | AM18: woo0234 | AN18: 45999.472 | AO18: 45999.473 | AP18: 46001.015 | AU18: 46007 | AV18: 0 | AW18: Rail360 | AX18: [~tha0073] to update data model within snowflake_x000D_ _x000D_ | AY18: woo0234 | CB18: 1|i0i630:
A19: =VLOOKUP(AK19,members!$A:$C,3,FALSE) -> Celebal | B19: =VLOOKUP(AK19,members!$A:$C,2,FALSE) -> Jatin | C19: =X19 -> RPD-75 | D19: =AB19 -> Done | E19: =AU19 -> 45996 | F19: =W19 -> AI - Foundation building check list to be completed | G19: =AX19 -> [~aro0027] to complete AI foundation checklist for Rail 360's (all layers) | W19: AI - Foundation building check list to be completed | X19: RPD-75 | Y19: 190030 | Z19: 190029 | AA19: Sub-task | AB19: Done | AC19: RPD | AD19: Rail360 Product Development | AE19: software | AF19: las0044 | AI19: 3-High | AJ19: Done | AK19: aro0027 | AL19: woo0234 | AM19: woo0234 | AN19: 45996.493 | AO19: 46001.226 | AP19: 46001.015 | AQ19: 46001.226 | AU19: 45996 | AV19: 0 | AW19: Rail360 | AX19: [~aro0027] to complete AI foundation checklist for Rail 360's (all layers) | AY19: aro0027 | AZ19: woo0234 | CB19: 1|i0i59w: | CJ19: 08/Dec/25 8:22 AM;aro0027;I have created the AI Foundation Checklist for Rail 360's_x000D_ _x000D_ 1.Created a detailed document explaining the process that how we will govern the status of data readiness for AI use cases.[AI Foundation Building Check List.docx|https://cpkcrail.sharepoint.com/:w:/t/3_22025InformationServices/EZ5m8UgIkmVAv4gofW3JW7sBMaDKiz8JMPDrO_CssrQgQQ?e=vtELVH]_x000D_ _x000D_ 2.Created a checklist divided into 6 major sections and 35 subpoints to validate the alignment of the data platform for AI use cases.[AI Foundation Building Check List.ods|https://cpkcrail.sharepoint.com/:x:/t/3_22025InformationServices/ESTh5YZeE0BOsjyPg2PXbkUBbSY0Bay0nLIfFyCp6f-PKw?e=wswYGk]_x000D_ _x000D_ ;;; | CK19: 09/Dec/25 11:07 AM;woo0234;feedback required for [~aro0027] ;;;
A20: =VLOOKUP(AK20,members!$A:$C,3,FALSE) -> Celebal | B20: =VLOOKUP(AK20,members!$A:$C,2,FALSE) -> Jatin | C20: =X20 -> RPD-74 | D20: =AB20 -> In Progress | E20: =AU20 -> 46052 | F20: =W20 -> AI - Foundation building | G20: =AX20 -> building and monitoring foundation of AI platform for Rail 360 led by [~aro0027] | W20: AI - Foundation building | X20: RPD-74 | Y20: 190029 | AA20: Task | AB20: In Progress | AC20: RPD | AD20: Rail360 Product Development | AE20: software | AF20: las0044 | AI20: 3-High | AK20: aro0027 | AL20: woo0234 | AM20: woo0234 | AN20: 45996.492 | AO20: 46000.463 | AP20: 46001.015 | AU20: 46052 | AV20: 0 | AW20: Rail360 | AX20: building and monitoring foundation of AI platform for Rail 360 led by [~aro0027] | AY20: aro0027 | AZ20: woo0234 | CB20: 1|i0i59o: | CJ20: 09/Dec/25 9:14 AM;aro0027;I have created the AI Foundation Checklist for Rail 360's_x000D_ _x000D_ 1.Created a detailed document explaining the process that how we will govern the status of data readiness for AI use cases.[AI Foundation Building Check List.docx|https://cpkcrail.sharepoint.com/:w:/t/3_22025InformationServices/EZ5m8UgIkmVAv4gofW3JW7sBMaDKiz8JMPDrO_CssrQgQQ?e=vtELVH]_x000D_ _x000D_ 2.Created a checklist divided into 6 major sections and 35 subpoints to validate the alignment of the data platform for AI use cases.[AI Foundation Building Check List.ods|https://cpkcrail.sharepoint.com/:x:/t/3_22025InformationServices/ESTh5YZeE0BOsjyPg2PXbkUBbSY0Bay0nLIfFyCp6f-PKw?e=wswYGk];;;
A21: =VLOOKUP(AK21,members!$A:$C,3,FALSE) -> Squadron | B21: =VLOOKUP(AK21,members!$A:$C,2,FALSE) -> Harshil Patel | C21: =X21 -> RPD-77 | D21: =AB21 -> In Progress | E21: =AU21 -> 45999 | F21: =W21 -> ER diagram review | G21: =AX21 -> [~pat0606] [~tha0073] to complete review of ER diagram files | W21: ER diagram review | X21: RPD-77 | Y21: 190160 | Z21: 189315 | AA21: Sub-task | AB21: In Progress | AC21: RPD | AD21: Rail360 Product Development | AE21: software | AF21: las0044 | AI21: 3-High | AK21: pat0606 | AL21: woo0234 | AM21: woo0234 | AN21: 45999.469 | AO21: 46001.47 | AP21: 45999.482 | AU21: 45999 | AV21: 0 | AW21: Rail360 | AX21: [~pat0606] [~tha0073] to complete review of ER diagram files | AY21: dan0243 | AZ21: woo0234 | CB21: 1|i0i62s: | CJ21: 09/Dec/25 10:21 AM;dan0243;9/12 - we started deep dive into the doc shared by Vishu Priya we are doing Initial analysis of the existing system based on this we have identify two approaches 1. Dynamic table 2. Stored Proc. ;;; | CK21: 10/Dec/25 10:23 AM;dan0243;we would like to get the 4 queries in text form.[~cvps10] ;;; | CL21: 10/Dec/25 11:15 AM;woo0234;is being reviewed by Squadron team and architect;;; | CM21: 10/Dec/25 11:17 AM;woo0234;[~moh0106] has documents that depicts individual query for each table associated with the data flow for [~pat0606] and squadron team.;;;
A22: =VLOOKUP(AK22,members!$A:$C,3,FALSE) -> QE | B22: =VLOOKUP(AK22,members!$A:$C,2,FALSE) -> VishnuB | C22: =X22 -> RPD-80 | D22: =AB22 -> To Do | E22: =AU22 -> 46002 | F22: =W22 -> MDM entity testing - DIM commodity DIM customer DIM equipment tables. | G22: =AX22 -> [~bor0475] and [~sid0070] to initiate and take on... checking and automating tables related to DIM commodity DIM customer DIM equipment tables._x000D_ _x000D_ ensure [~seh0018] and [~ric0230] are involved and aligned | W22: MDM entity testing - DIM commodity DIM customer DIM equipment tables. | X22: RPD-80 | Y22: 190167 | AA22: Task | AB22: To Do | AC22: RPD | AD22: Rail360 Product Development | AE22: software | AF22: las0044 | AI22: 3-High | AK22: bor0475 | AL22: woo0234 | AM22: woo0234 | AN22: 45999.481 | AO22: 46002.452 | AP22: 45999.481 | AU22: 46002 | AV22: 0 | AW22: Rail360 | AX22: [~bor0475] and [~sid0070] to initiate and take on... checking and automating tables related to DIM commodity DIM customer DIM equipment tables._x000D_ _x000D_ ensure [~seh0018] and [~ric0230] are involved and aligned | AY22: bor0475 | AZ22: woo0234 | BM22: RPD-83 | BN22: 10/Dec/25 10:45 AM;bor0475;DIM_CUSTOMER -QA Findings.docx;https://jira.cpr.ca/secure/attachment/166191/DIM_CUSTOMER+-QA+Findings.docx | CB22: 1|i0i63w: | CJ22: 09/Dec/25 10:45 AM;bor0475;Testing/Automation started with DIM_CUSTOMER, will be targeting by 12/10/2025. ;;; | CK22: 10/Dec/25 10:46 AM;bor0475;Performed testing on the DIM_COMMODITY and communicated the findings to [~seh0018] _x000D_ _x000D_ [^DIM_CUSTOMER -QA Findings.docx];;; | CL22: 11/Dec/25 10:51 AM;bor0475;Started testing with DIM_COMMODITY.;;;
A23: =VLOOKUP(AK23,members!$A:$C,3,FALSE) -> QE | B23: =VLOOKUP(AK23,members!$A:$C,2,FALSE) -> VishnuB | C23: =X23 -> RPD-5 | D23: =AB23 -> In Progress | E23: =AU23 -> 46002 | F23: =W23 -> Test Planning Phase 2 (P415) - Conversion of requirement into Task Cases from P140 | G23: =AX23 -> Test Planning Phase 2 - Conversion of requirement into Task Cases from P140 requirement document_x000D_ (e.g. SADB transformation into Snowflake loading -> what transformation we do -> multiple subtask and testing cases to be followed)_x000D_ complete test plan with access to AWS and Cloud platforms | W23: Test Planning Phase 2 (P415) - Conversion of requirement into Task Cases from P140 | X23: RPD-5 | Y23: 186078 | AA23: Task | AB23: In Progress | AC23: RPD | AD23: Rail360 Product Development | AE23: software | AF23: las0044 | AI23: 3-High | AK23: bor0475 | AL23: woo0234 | AM23: woo0234 | AN23: 45951.578 | AO23: 46002.453 | AP23: 45999.479 | AU23: 46002 | AV23: 0 | AW23: Rail360 | AX23: Test Planning Phase 2 - Conversion of requirement into Task Cases from P140 requirement document_x000D_ (e.g. SADB transformation into Snowflake loading -> what transformation we do -> multiple subtask and testing cases to be followed)_x000D_ complete test plan with access to AWS and Cloud platforms | AY23: bor0475 | AZ23: cvps10 | BA23: sau0093 | BB23: sid0070 | BC23: woo0234 | CB23: 1|i0hj2k: | CJ23: 27/Oct/25 11:41 AM;woo0234;require a high-level solution from source to bronze (partially defined) and bronze to siliver (not started) and silver to gold (gold is defined but not the data pipeline)_x000D_ _x000D_ this requires update from [~kvxg11], [~cvps10] supported by [~sin0404] and [~sau0093] _x000D_ _x000D_ ;;; | CK23: 19/Nov/25 11:20 AM;cvps10;Dependent on P220 and P219;;; | CL23: 26/Nov/25 11:23 AM;sau0093;Waiting for P220.;;; | CM23: 02/Dec/25 11:10 AM;sid0070;Development can be started on current data in P220;;; | CN23: 03/Dec/25 11:03 AM;cvps10;Initial draft started;;; | CO23: 04/Dec/25 11:15 AM;bor0475;I started drafting P415 and targeting by Dec 8th , after I'll send to Automation/Performance teams for updates. Thanks!;;; | CP23: 10/Dec/25 10:41 AM;bor0475;I have updated Initial test plan and Automation updates are in progress.;;; | CQ23: 10/Dec/25 11:29 AM;woo0234;MDM - dim equipment table mapping document is missing to progress as per [~bor0475] . discussion needed with MDM team.;;; | CR23: 11/Dec/25 10:53 AM;bor0475;Automation updates have been incorporated with the test plan. I will share them for review today.;;;
A24: =VLOOKUP(AK24,members!$A:$C,3,FALSE) -> Architect | B24: =VLOOKUP(AK24,members!$A:$C,2,FALSE) -> David | C24: =X24 -> RPD-30 | D24: =AB24 -> Done | E24: =AU24 -> 45995 | F24: =W24 -> P310 LogicGate System Security Documentation (solution architect) | G24: =AX24 -> [~ngu0018] could you review and update proper ETA? this is part of required docu for stage gate purposes. | W24: P310 LogicGate System Security Documentation (solution architect) | X24: RPD-30 | Y24: 186290 | AA24: Task | AB24: Done | AC24: RPD | AD24: Rail360 Product Development | AE24: software | AF24: las0044 | AI24: 3-High | AJ24: Done | AK24: ngu0018 | AL24: woo0234 | AM24: woo0234 | AN24: 45954.503 | AO24: 46001.435 | AP24: 45999.46 | AQ24: 46001.435 | AU24: 45995 | AV24: 0 | AW24: Rail360 | AX24: [~ngu0018] could you review and update proper ETA? this is part of required docu for stage gate purposes. | AY24: ana0017 | AZ24: cvps10 | BA24: ngu0018 | BB24: sid0070 | BC24: woo0234 | BN24: 04/Dec/25 11:04 PM;ngu0018;LogicGate P310 - Rail 360 SG2.pdf;https://jira.cpr.ca/secure/attachment/165818/LogicGate+P310+-+Rail+360+SG2.pdf | BO24: 10/Dec/25 10:23 AM;ngu0018;LogicGate P310 - Rail 360 SG2-1.pdf;https://jira.cpr.ca/secure/attachment/166183/LogicGate+P310+-+Rail+360+SG2-1.pdf | CB24: 1|i0hkc4: | CJ24: 27/Oct/25 11:14 AM;woo0234;[~ngu0018] can you share estimated timeline/ effort for this document for us?_x000D_ _x000D_ ;;; | CK24: 04/Nov/25 9:42 AM;ngu0018;P310 is data recorded into LogicGate application for Enterprise Security to review the proposed solution for potential risk areas. This is done when the P219 has been reviewed and approved by EA, as the same data from P219 is transferred into LogicGate for ES. My target date to have the P219 completed, reviewed and approved by Nov 14th, provided that any/all outstanding questions regarding Snowflake and integration details have been answered. ;;; | CL24: 12/Nov/25 10:38 AM;ana0017;Will have it Complete. Next week after P219 Completion.;;; | CM24: 02/Dec/25 11:11 AM;sid0070;P219 is updated. can be used for this task;;; | CN24: 03/Dec/25 11:04 AM;cvps10;[~ngu0018] any progress on this?;;; | CO24: 03/Dec/25 11:27 AM;ngu0018;I will have the LogicGate record submitted today since we have decided to use IDMC and no longer waiting for a decision on Openflow for this phase of the project. ;;; | CP24: 04/Dec/25 7:18 PM;ngu0018;LogicGate P310 submitted for ES review and assessment. Assignee from ES is Bayo Oladele. Will provide update once ES assessment is complete.;;; | CQ24: 04/Dec/25 11:06 PM;ngu0018;ES Assessment completed with no risks identified. can proceed with SG2. ;;; | CR24: 10/Dec/25 10:24 AM;ngu0018;LogicGate P310 has been assessed by Enterprise Security and no risks identified. The project can proceed with PMO SG2 when ready. ;;;
A25: =VLOOKUP(AK25,members!$A:$C,3,FALSE) -> ETL | B25: =VLOOKUP(AK25,members!$A:$C,2,FALSE) -> Naveen | C25: =X25 -> RPD-54 | D25: =AB25 -> Done | E25: =AU25 -> 45988 | F25: =W25 -> Base Table - Setting Secure Agent and Testing jobs | G25: =AX25 -> once rpd-53 decision is made by architect._x000D_ _x000D_ start setting secure agent and testing jobs._x000D_ _x000D_ _x000D_ _x000D_ start today 11/20 for EXISTING JOBS._x000D_ _x000D_ _x000D_ _x000D_ if we go with openflow, there are different jobs to be followed. | W25: Base Table - Setting Secure Agent and Testing jobs | X25: RPD-54 | Y25: 188632 | Z25: 188628 | AA25: Sub-task | AB25: Done | AC25: RPD | AD25: Rail360 Product Development | AE25: software | AF25: las0044 | AI25: 3-High | AJ25: Done | AK25: knxn12 | AL25: woo0234 | AM25: woo0234 | AN25: 45981.477 | AO25: 45992.47 | AP25: 45992.47 | AQ25: 45992.47 | AU25: 45988 | AV25: 0 | AW25: Rail360 | AX25: once rpd-53 decision is made by architect._x000D_ _x000D_ start setting secure agent and testing jobs._x000D_ _x000D_ _x000D_ _x000D_ start today 11/20 for EXISTING JOBS._x000D_ _x000D_ _x000D_ _x000D_ if we go with openflow, there are different jobs to be followed. | AY25: woo0234 | CB25: 1|i0hxzw:
A26: =VLOOKUP(AK26,members!$A:$C,3,FALSE) -> ETL | B26: =VLOOKUP(AK26,members!$A:$C,2,FALSE) -> Naveen | C26: =X26 -> RPD-58 | D26: =AB26 -> In Progress | E26: =AU26 -> 45989 | F26: =W26 -> Create Informatica Secure Agent account for Squadron | G26: =AX26 -> meantime, start working via existing secure agent DEV | W26: Create Informatica Secure Agent account for Squadron | X26: RPD-58 | Y26: 188654 | AA26: Task | AB26: In Progress | AC26: RPD | AD26: Rail360 Product Development | AE26: software | AF26: las0044 | AI26: 3-High | AK26: knxn12 | AL26: woo0234 | AM26: woo0234 | AN26: 45981.558 | AO26: 45993.486 | AP26: 45992.469 | AU26: 45989 | AV26: 0 | AX26: meantime, start working via existing secure agent DEV | AY26: cvps10 | AZ26: woo0234 | CB26: 1|i0hxz4: | CJ26: 02/Dec/25 11:39 AM;cvps10;For now, existing secure agent is used. Naveen working on creating new secure agent. Dependent on multiple teams - might take 2 weeks;;;
A27: =VLOOKUP(AK27,members!$A:$C,3,FALSE) -> ETL | B27: =VLOOKUP(AK27,members!$A:$C,2,FALSE) -> Naveen | C27: =X27 -> RPD-59 | D27: =AB27 -> Done | E27: =AU27 -> 45981 | F27: =W27 -> Schema Testing (SADB) using existing module | G27: =AX27 -> [~ngu0018] asked ETL team to test connection for SADB by creating jobs. [~sin0404] [~knxn12] to follow. | W27: Schema Testing (SADB) using existing module | X27: RPD-59 | Y27: 188656 | Z27: 188628 | AA27: Sub-task | AB27: Done | AC27: RPD | AD27: Rail360 Product Development | AE27: software | AF27: las0044 | AI27: 3-High | AJ27: Done | AK27: knxn12 | AL27: woo0234 | AM27: woo0234 | AN27: 45981.564 | AO27: 45988.47 | AP27: 45988.47 | AQ27: 45988.47 | AU27: 45981 | AV27: 0 | AW27: Rail360 | AX27: [~ngu0018] asked ETL team to test connection for SADB by creating jobs. [~sin0404] [~knxn12] to follow. | AY27: sau0093 | AZ27: woo0234 | CB27: 1|i0hy50: | CJ27: 26/Nov/25 11:12 AM;sau0093;Openflow steup is still pending. ;;;
A28: =VLOOKUP(AK28,members!$A:$C,3,FALSE) -> Squadron | B28: =VLOOKUP(AK28,members!$A:$C,2,FALSE) -> Babu | C28: =X28 -> RPD-66 | D28: =AB28 -> To Do | E28: 46010 | F28: =W28 -> SnowFlake ETL Plan - Silver to Gold solution to provide - document / email needed | G28: =AX28 -> Document that_x000D_ _x000D_ includes methodologies out of below example options._x000D_ _x000D_ include data models for Silver Layers_x000D_ _x000D_ _x000D_ _x000D_ 1) DBT_x000D_ _x000D_ 2) Store Procedures_x000D_ _x000D_ 3) Snow Park | W28: SnowFlake ETL Plan - Silver to Gold solution to provide - document / email needed | X28: RPD-66 | Y28: 189014 | AA28: Task | AB28: To Do | AC28: RPD | AD28: Rail360 Product Development | AE28: software | AF28: las0044 | AI28: 3-High | AK28: tha0073 | AL28: woo0234 | AM28: woo0234 | AN28: 45988.47 | AO28: 46001.431 | AP28: 45988.47 | AU28: 45994 | AV28: 0 | AW28: Rail360 | AX28: Document that_x000D_ _x000D_ includes methodologies out of below example options._x000D_ _x000D_ include data models for Silver Layers_x000D_ _x000D_ _x000D_ _x000D_ 1) DBT_x000D_ _x000D_ 2) Store Procedures_x000D_ _x000D_ 3) Snow Park | AY28: dan0243 | AZ28: woo0234 | BN28: 10/Dec/25 10:17 AM;dan0243;Snowflake Native Capabilities_v2.docx;https://jira.cpr.ca/secure/attachment/166182/Snowflake+Native+Capabilities_v2.docx | CB28: 1|i0i06c: | CJ28: 09/Dec/25 10:10 AM;dan0243;9/12 - Since it a dependent on data modeling document;;; | CK28: 10/Dec/25 10:21 AM;dan0243;Once we decide the silver layer approach and bring up the data from all sources. we will then finalize the silver to gold. but for the better understanding i have attached the document ;;;
A29: =VLOOKUP(AK29,members!$A:$C,3,FALSE) -> BDA | B29: =VLOOKUP(AK29,members!$A:$C,2,FALSE) -> VPS | C29: =X29 -> RPD-64 | D29: =AB29 -> Done | E29: =AU29 -> 45993 | F29: =W29 -> allocate to celebal team with KT by 12/2 Tuesday | G29: =AX29 -> [~cvps10] to KT to Celebal team [~moh0106] and [~bab0060] / [~aro0027] | W29: allocate to celebal team with KT by 12/2 Tuesday | X29: RPD-64 | Y29: 188862 | Z29: 188014 | AA29: Sub-task | AB29: Done | AC29: RPD | AD29: Rail360 Product Development | AE29: software | AF29: las0044 | AI29: 3-High | AJ29: Done | AK29: cvps10 | AL29: woo0234 | AM29: woo0234 | AN29: 45986.469 | AO29: 45993.484 | AP29: 45986.469 | AQ29: 45993.484 | AU29: 45993 | AV29: 0 | AW29: Rail360 | AX29: [~cvps10] to KT to Celebal team [~moh0106] and [~bab0060] / [~aro0027] | AY29: cvps10 | AZ29: woo0234 | CB29: 1|i0hzck: | CJ29: 02/Dec/25 11:37 AM;cvps10;KT completed with the help of documents and recordings by Sangtae and team for Rail 360;;;
A30: =VLOOKUP(AK30,members!$A:$C,3,FALSE) -> ETL | B30: =VLOOKUP(AK30,members!$A:$C,2,FALSE) -> Naveen | C30: =X30 -> RPD-52 | D30: =AB30 -> Done | E30: =AU30 -> 45988 | F30: =W30 -> Base Table DEV environment setting (Bronze data) | G30: =AX30 -> [~knxn12] / [~sin0404] to work with [~tha0073] to confirm base table environment (bronze data) is set (access is granted but job needs to be set up) such as dedicated server for CDC work._x000D_ _x000D_ | W30: Base Table DEV environment setting (Bronze data) | X30: RPD-52 | Y30: 188628 | AA30: Task | AB30: Done | AC30: RPD | AD30: Rail360 Product Development | AE30: software | AF30: las0044 | AI30: 3-High | AJ30: Done | AK30: knxn12 | AL30: woo0234 | AM30: woo0234 | AN30: 45981.47 | AO30: 45994.476 | AP30: 45985.476 | AQ30: 45994.476 | AU30: 45988 | AV30: 0 | AW30: Rail360 | AX30: [~knxn12] / [~sin0404] to work with [~tha0073] to confirm base table environment (bronze data) is set (access is granted but job needs to be set up) such as dedicated server for CDC work._x000D_ _x000D_ | AY30: cvps10 | AZ30: woo0234 | CB30: 1|i0hube: | CJ30: 03/Dec/25 11:26 AM;cvps10;Dev load tested from SADB to Bronze using IICS;;;
A31: =VLOOKUP(AK31,members!$A:$C,3,FALSE) -> BDA | B31: =VLOOKUP(AK31,members!$A:$C,2,FALSE) -> VPS | C31: =X31 -> RPD-51 | D31: =AB31 -> In Progress | E31: =AU31 -> 0 | F31: =W31 -> Set up/Lift Logic Review | G31: =AX31 -> [~cvps10] to schedule a meeting to Review Logic with Karthik and Kishore. | W31: Set up/Lift Logic Review | X31: RPD-51 | Y31: 188014 | AA31: Task | AB31: In Progress | AC31: RPD | AD31: Rail360 Product Development | AE31: software | AF31: las0044 | AI31: 3-High | AK31: cvps10 | AL31: ana0017 | AM31: ana0017 | AN31: 45974.467 | AO31: 46002.438 | AP31: 45982.469 | AV31: 0 | AX31: [~cvps10] to schedule a meeting to Review Logic with Karthik and Kishore. | AY31: ana0017 | AZ31: cvps10 | BA31: woo0234 | CB31: 1|i0hubc: | CJ31: 08/Dec/25 11:10 AM;woo0234;follow up with saurabh and celable by 12/9;;; | CK31: 11/Dec/25 10:30 AM;cvps10;email sent to Kishore and Karthik to review the set off/lift logic. Will await their response;;;
A32: =VLOOKUP(AK32,members!$A:$C,3,FALSE) -> ETL | B32: =VLOOKUP(AK32,members!$A:$C,2,FALSE) -> Naveen | C32: =X32 -> RPD-53 | D32: =AB32 -> Done | E32: =AU32 -> 45981 | F32: =W32 -> Base table - injection tool options decision (e.g. IDMC / Openflow) | G32: =AX32 -> [~sin0404] / [~knxn12] / [~tha0073] to reach out architect to make a decision on tool options between idmc vs. openflow_x000D_ _x000D_ [~ngu0018] / [~tig0002] to make a decision which tool will be used for MDM, SADB/ORACLE, AZURE, AWS. AND SAP BW, GIS, to be added/documented once decision is made_x000D_ _x000D_ [~cvps10] to reflect data setting changes into technical document._x000D_ _x000D_ _x000D_ _x000D_ | W32: Base table - injection tool options decision (e.g. IDMC / Openflow) | X32: RPD-53 | Y32: 188630 | Z32: 188628 | AA32: Sub-task | AB32: Done | AC32: RPD | AD32: Rail360 Product Development | AE32: software | AF32: las0044 | AI32: 3-High | AJ32: Done | AK32: knxn12 | AL32: woo0234 | AM32: woo0234 | AN32: 45981.476 | AO32: 45982.467 | AP32: 45982.467 | AQ32: 45982.467 | AU32: 45981 | AV32: 0 | AW32: Rail360 | AX32: [~sin0404] / [~knxn12] / [~tha0073] to reach out architect to make a decision on tool options between idmc vs. openflow_x000D_ _x000D_ [~ngu0018] / [~tig0002] to make a decision which tool will be used for MDM, SADB/ORACLE, AZURE, AWS. AND SAP BW, GIS, to be added/documented once decision is made_x000D_ _x000D_ [~cvps10] to reflect data setting changes into technical document._x000D_ _x000D_ _x000D_ _x000D_ | AY32: woo0234 | CB32: 1|i0hxzg: | CJ32: 20/Nov/25 1:05 PM;woo0234;Open flow is not an option due to timing as per [~ngu0018] 11/20;;; | CK32: 20/Nov/25 1:06 PM;woo0234;Use Informatica to get into SnowFlake for phase 1 and build Open flow for future base data ENV setting.;;; | CL32: 21/Nov/25 11:12 AM;woo0234;phase 1 will be via informatica process while phase 2 has high chance to go with open flow type of methods.;;; | CM32: 21/Nov/25 11:13 AM;woo0234;as per [~bha0056] and [~ngu0018], use Informatica IDMC method for phase 1 level.;;;
A33: =VLOOKUP(AK33,members!$A:$C,3,FALSE) -> ETL | B33: =VLOOKUP(AK33,members!$A:$C,2,FALSE) -> Naveen | C33: =X33 -> RPD-61 | D33: =AB33 -> Done | E33: =AU33 -> 45989 | F33: =W33 -> Create PROD secure agent (second) | G33: =AX33 -> 0 | W33: Create PROD secure agent (second) | X33: RPD-61 | Y33: 188700 | Z33: 188654 | AA33: Sub-task | AB33: Done | AC33: RPD | AD33: Rail360 Product Development | AE33: software | AF33: las0044 | AI33: 3-High | AJ33: Done | AK33: knxn12 | AL33: woo0234 | AM33: woo0234 | AN33: 45982.465 | AO33: 45987.468 | AP33: 45982.465 | AQ33: 45987.468 | AU33: 45989 | AV33: 0 | AW33: Rail360 | AY33: woo0234 | CB33: 1|i0hyec:
A34: =VLOOKUP(AK34,members!$A:$C,3,FALSE) -> ETL | B34: =VLOOKUP(AK34,members!$A:$C,2,FALSE) -> Naveen | C34: =X34 -> RPD-60 | D34: =AB34 -> In Progress | E34: =AU34 -> 45986 | F34: =W34 -> Create DEV secure agent (first) | G34: =AX34 -> 0 | W34: Create DEV secure agent (first) | X34: RPD-60 | Y34: 188699 | Z34: 188654 | AA34: Sub-task | AB34: In Progress | AC34: RPD | AD34: Rail360 Product Development | AE34: software | AF34: las0044 | AI34: 3-High | AK34: knxn12 | AL34: woo0234 | AM34: woo0234 | AN34: 45982.465 | AO34: 45987.467 | AP34: 45982.465 | AU34: 45986 | AV34: 0 | AW34: Rail360 | AY34: woo0234 | CB34: 1|i0hye4:
A35: =VLOOKUP(AK35,members!$A:$C,3,FALSE) -> BDA | B35: =VLOOKUP(AK35,members!$A:$C,2,FALSE) -> Sangtae | C35: =X35 -> RPD-39 | D35: =AB35 -> Done | E35: =AU35 -> 0 | F35: =W35 -> Buisness Glossary | G35: =AX35 -> Need to Create Business Glossary for for Phase 1 with details. | W35: Buisness Glossary | X35: RPD-39 | Y35: 187245 | AA35: Task | AB35: Done | AC35: RPD | AD35: Rail360 Product Development | AE35: software | AF35: las0044 | AI35: 4-Medium | AJ35: Done | AK35: woo0234 | AL35: ana0017 | AM35: ana0017 | AN35: 45965.472 | AO35: 45982.463 | AP35: 45982.463 | AQ35: 45982.463 | AV35: 0 | AX35: Need to Create Business Glossary for for Phase 1 with details. | AY35: ana0017 | AZ35: woo0234 | CB35: 1|i0hpnw: | CJ35: 07/Nov/25 11:13 AM;woo0234;[~mok0002] will help [~woo0234] to expedite by November 13th.;;;
A36: =VLOOKUP(AK36,members!$A:$C,3,FALSE) -> BDA | B36: =VLOOKUP(AK36,members!$A:$C,2,FALSE) -> Ron | C36: =X36 -> RPD-48 | D36: =AB36 -> Done | E36: =AU36 -> 45975 | F36: =W36 -> Share the work and complete with Ron and Pankaj for Business Glossary | G36: =AX36 -> [~woo0234] work with [~mok0002] and [~ana0017] till 11/14._x000D_ _x000D_ _x000D_ _x000D_ [Product_PoC_V1.xlsx|https://cpkcrail.sharepoint.com/:x:/r/teams/3_22025InformationServices/_layouts/15/Doc.aspx?sourcedoc=%7BCC2A6CF5-D39D-42E6-91B0-00C454B1916A%7D&file=Product_PoC_V1.xlsx&action=default&mobileredirect=true]_x000D_ _x000D_ in tab data dictionary. | W36: Share the work and complete with Ron and Pankaj for Business Glossary | X36: RPD-48 | Y36: 187803 | Z36: 187245 | AA36: Sub-task | AB36: Done | AC36: RPD | AD36: Rail360 Product Development | AE36: software | AF36: las0044 | AI36: 3-High | AJ36: Done | AK36: mok0002 | AL36: woo0234 | AM36: woo0234 | AN36: 45971.483 | AO36: 45982.463 | AP36: 45982.463 | AQ36: 45982.463 | AU36: 45975 | AV36: 0 | AX36: [~woo0234] work with [~mok0002] and [~ana0017] till 11/14._x000D_ _x000D_ _x000D_ _x000D_ [Product_PoC_V1.xlsx|https://cpkcrail.sharepoint.com/:x:/r/teams/3_22025InformationServices/_layouts/15/Doc.aspx?sourcedoc=%7BCC2A6CF5-D39D-42E6-91B0-00C454B1916A%7D&file=Product_PoC_V1.xlsx&action=default&mobileredirect=true]_x000D_ _x000D_ in tab data dictionary. | AY36: ana0017 | AZ36: cvps10 | BA36: woo0234 | CB36: 1|i0ht10: | CJ36: 12/Nov/25 10:20 AM;ana0017;Team is working on Document will have it complete by Nov 14.;;; | CK36: 17/Nov/25 11:08 AM;ana0017;[~woo0234] if we can share with Business this week to Review it.;;; | CL36: 19/Nov/25 11:23 AM;cvps10;Updated by Sangtae and Ron;;;
A37: =VLOOKUP(AK37,members!$A:$C,3,FALSE) -> BDA | B37: =VLOOKUP(AK37,members!$A:$C,2,FALSE) -> VPS | C37: =X37 -> RPD-57 | D37: =AB37 -> Done | E37: =AU37 -> 45981 | F37: =W37 -> P220 System to Bronze detail to fill up | G37: =AX37 -> while awaiting for bronze to gold, complete system to bronze P220 | W37: P220 System to Bronze detail to fill up | X37: RPD-57 | Y37: 188645 | Z37: 186079 | AA37: Sub-task | AB37: Done | AC37: RPD | AD37: Rail360 Product Development | AE37: software | AF37: las0044 | AI37: 3-High | AJ37: Done | AK37: cvps10 | AL37: woo0234 | AM37: woo0234 | AN37: 45981.492 | AO37: 45987.476 | AP37: 45982.463 | AQ37: 45987.476 | AU37: 45981 | AV37: 0 | AW37: Rail360 | AX37: while awaiting for bronze to gold, complete system to bronze P220 | AY37: woo0234 | CB37: 1|i0hy2s: | CJ37: 21/Nov/25 11:06 AM;woo0234;[~cvps10] will complete by end of today 11/21st Friday;;; | CK37: 25/Nov/25 11:08 AM;woo0234;determining fields required transformation vs. not will be completed._x000D_ _x000D_ however exact transformation logic will be in early December week completion.;;;
A38: =VLOOKUP(AK38,members!$A:$C,3,FALSE) -> ETL | B38: =VLOOKUP(AK38,members!$A:$C,2,FALSE) -> Naveen | C38: =X38 -> RPD-6 | D38: =AB38 -> Done | E38: =AU38 -> 45965 | F38: =W38 -> P220 Prep Work - Initial data process review | G38: =AX38 -> P220 Prep Work - Initial data process review (include a complete diagram and target tables) - more technical / naming convention / architects_x000D_ adding more to reflect the platform changes, MDM composition, and preliminary requirement for regulatory tonnage data_x000D_ _x000D_ Co work to be done by both ETL and Analysts | W38: P220 Prep Work - Initial data process review | X38: RPD-6 | Y38: 186079 | AA38: Task | AB38: Done | AC38: RPD | AD38: Rail360 Product Development | AE38: software | AF38: las0044 | AI38: 3-High | AJ38: Done | AK38: kvxg11 | AL38: woo0234 | AM38: woo0234 | AN38: 45951.58 | AO38: 45987.475 | AP38: 45981.49 | AQ38: 45987.475 | AU38: 45965 | AV38: 0 | AW38: Rail360 | AX38: P220 Prep Work - Initial data process review (include a complete diagram and target tables) - more technical / naming convention / architects_x000D_ adding more to reflect the platform changes, MDM composition, and preliminary requirement for regulatory tonnage data_x000D_ _x000D_ Co work to be done by both ETL and Analysts | AY38: ana0017 | AZ38: woo0234 | BE38: 144000 | BF38: 144000 | BH38: 0 | BI38: 144000 | BJ38: 144000 | CB38: 1|i0hj2s: | CJ38: 23/Oct/25 11:24 AM;ana0017;[~cvps10] will be working from BDA team with assigned ETL folks.;;; | CK38: 05/Nov/25 11:26 AM;woo0234;other than diagram part, majority of sections are ready.;;;
A39: =VLOOKUP(AK39,members!$A:$C,3,FALSE) -> PM | B39: =VLOOKUP(AK39,members!$A:$C,2,FALSE) -> Robert | C39: =X39 -> RPD-44 | D39: =AB39 -> Done | E39: =AU39 -> 45971 | F39: =W39 -> Data quality strategy draft v1 | G39: =AX39 -> [~sel0052] to strategize data quality structure (backbone)_x000D_ _x000D_ discussed about layer based approach_x000D_ _x000D_ work with [~sid0070] as well._x000D_ _x000D_ eventuall will work with business to weigh in after our review on 10th of Nov. | W39: Data quality strategy draft v1 | X39: RPD-44 | Y39: 187445 | Z39: 186087 | AA39: Sub-task | AB39: Done | AC39: RPD | AD39: Rail360 Product Development | AE39: software | AF39: las0044 | AI39: 3-High | AJ39: Done | AK39: las0044 | AL39: woo0234 | AM39: woo0234 | AN39: 45967.475 | AO39: 45987.485 | AP39: 45971.478 | AQ39: 45987.485 | AU39: 45971 | AV39: 0 | AW39: Rail360 | AX39: [~sel0052] to strategize data quality structure (backbone)_x000D_ _x000D_ discussed about layer based approach_x000D_ _x000D_ work with [~sid0070] as well._x000D_ _x000D_ eventuall will work with business to weigh in after our review on 10th of Nov. | AY39: woo0234 | CB39: 1|i0hqtw:
A40: =VLOOKUP(AK40,members!$A:$C,3,FALSE) -> Cloud | B40: =VLOOKUP(AK40,members!$A:$C,2,FALSE) -> Ruben | C40: =X40 -> RPD-47 | D40: =AB40 -> Done | E40: =AU40 -> 45973 | F40: =W40 -> Access to build Foundation of Bronze Layer for Squadron | G40: =AX40 -> Establishment of all data systems into Bronze Layer _x000D_ _x000D_ e.g. temp admin access for informatica set up. Need Admin Access for Squadron team._x000D_ _x000D_ _x000D_ _x000D_ [~las0044] will follow up with [~gue0154] for Squadron team ([~dan0243] / [~hel0063] / [~tha0073] ..) | W40: Access to build Foundation of Bronze Layer for Squadron | X40: RPD-47 | Y40: 187790 | AA40: Task | AB40: Done | AC40: RPD | AD40: Rail360 Product Development | AE40: software | AF40: las0044 | AI40: 2-Very High | AJ40: Done | AK40: gue0154 | AL40: woo0234 | AM40: woo0234 | AN40: 45971.476 | AO40: 45987.485 | AP40: 45971.477 | AQ40: 45987.485 | AU40: 45973 | AV40: 0 | AW40: Rail360 | AX40: Establishment of all data systems into Bronze Layer _x000D_ _x000D_ e.g. temp admin access for informatica set up. Need Admin Access for Squadron team._x000D_ _x000D_ _x000D_ _x000D_ [~las0044] will follow up with [~gue0154] for Squadron team ([~dan0243] / [~hel0063] / [~tha0073] ..) | AY40: ana0017 | AZ40: woo0234 | CB40: 1|i0hsy4: | CJ40: 12/Nov/25 10:43 AM;ana0017;Squadran team has a meeting with Rueben and Team today.will Discuss the Access requirements during the Meeting.;;; | CK40: 13/Nov/25 11:05 AM;ana0017;Squadron Team is working with Rueben to do the setup.;;; | CL40: 21/Nov/25 11:22 AM;woo0234;tested with existing bridge;;;
A41: =VLOOKUP(AK41,members!$A:$C,3,FALSE) -> ETL | B41: =VLOOKUP(AK41,members!$A:$C,2,FALSE) -> Vicky | C41: =X41 -> RPD-10 | D41: =AB41 -> In Progress | E41: =AU41 -> 45957 | F41: =W41 -> SADB / MDW / EDW / Azure / Snowflake | G41: =AX41 -> [~mor0460] to initiate / grant access details in _x000D_ _x000D_ [Rail360 Categorized_Timeline_with_Transcript_Tasks_V1.xlsx|https://cpkcrail.sharepoint.com/:x:/r/teams/3_22025InformationServices/_layouts/15/Doc.aspx?sourcedoc=%7BB98E5961-DAB0-4579-82A0-99B223DB130E%7D&file=Rail360%20Categorized_Timeline_with_Transcript_Tasks_V1.xlsx&action=default&mobileredirect=true] tab Access | W41: SADB / MDW / EDW / Azure / Snowflake | X41: RPD-10 | Y41: 186086 | AA41: Task | AB41: In Progress | AC41: RPD | AD41: Rail360 Product Development | AE41: software | AF41: las0044 | AI41: 3-High | AK41: pat0582 | AL41: woo0234 | AM41: woo0234 | AN41: 45951.61 | AO41: 45995.472 | AP41: 45971.47 | AU41: 45957 | AV41: 0 | AW41: Rail360 | AX41: [~mor0460] to initiate / grant access details in _x000D_ _x000D_ [Rail360 Categorized_Timeline_with_Transcript_Tasks_V1.xlsx|https://cpkcrail.sharepoint.com/:x:/r/teams/3_22025InformationServices/_layouts/15/Doc.aspx?sourcedoc=%7BB98E5961-DAB0-4579-82A0-99B223DB130E%7D&file=Rail360%20Categorized_Timeline_with_Transcript_Tasks_V1.xlsx&action=default&mobileredirect=true] tab Access | AY41: ana0017 | AZ41: sau0093 | BA41: woo0234 | CB41: 1|i0hj4c: | CJ41: 23/Oct/25 11:23 AM;ana0017;Need Access for [~cvps10] for all the mentioned DB.;;; | CK41: 10/Nov/25 11:18 AM;woo0234;QA team have not been granted access to Snowflake for [~sel0052] and [~sid0070] yet. raised this to [~dow0059] ;;; | CL41: 26/Nov/25 11:31 AM;sau0093;Naveen : SADB Acc and Prod access is still pending and working with service fulfillment team ;;; | CM41: 04/Dec/25 11:19 AM;sau0093;Its still in progress, expected to complete by Dec08.;;;
A42: =VLOOKUP(AK42,members!$A:$C,3,FALSE) -> Business | B42: =VLOOKUP(AK42,members!$A:$C,2,FALSE) -> Paul | C42: =X42 -> RPD-11 | D42: =AB42 -> In Progress | E42: =AU42 -> 45975 | F42: =W42 -> Data Quality Rules to complete | G42: =AX42 -> this will be joint efforts among QA ([~sel0052] / [~sid0070] ) and Business team ([~ste0370] / [~ten0025] ) and analysts will engage during the process._x000D_ _x000D_ tentative time attached. | W42: Data Quality Rules to complete | X42: RPD-11 | Y42: 186087 | AA42: Task | AB42: In Progress | AC42: RPD | AD42: Rail360 Product Development | AE42: software | AF42: las0044 | AI42: 3-High | AK42: ste0370 | AL42: woo0234 | AM42: woo0234 | AN42: 45951.61 | AO42: 45993.48 | AP42: 45968.468 | AU42: 45975 | AV42: 0 | AW42: Rail360 | AX42: this will be joint efforts among QA ([~sel0052] / [~sid0070] ) and Business team ([~ste0370] / [~ten0025] ) and analysts will engage during the process._x000D_ _x000D_ tentative time attached. | AY42: cvps10 | AZ42: sau0093 | BA42: woo0234 | CB42: 1|i0hj4k: | CJ42: 26/Nov/25 11:32 AM;sau0093;Session with Paul and team is required to have their comments. ;;; | CK42: 02/Dec/25 11:31 AM;cvps10;Recevied feedback on broken CSNs from Paul and team. Need to strategize solution;;;
A43: =VLOOKUP(AK43,members!$A:$C,3,FALSE) -> QE | B43: =VLOOKUP(AK43,members!$A:$C,2,FALSE) -> Raheel | C43: =X43 -> RPD-34 | D43: =AB43 -> Done | E43: =AU43 -> 45961 | F43: =W43 -> recap and summary of test case phase 1 draft document | G43: =AX43 -> for harleen and key stakeholders. | W43: recap and summary of test case phase 1 draft document | X43: RPD-34 | Y43: 186587 | AA43: Task | AB43: Done | AC43: RPD | AD43: Rail360 Product Development | AE43: software | AF43: las0044 | AI43: 3-High | AJ43: Done | AK43: sid0070 | AL43: woo0234 | AM43: woo0234 | AN43: 45958.466 | AO43: 45967.476 | AP43: 45967.476 | AQ43: 45967.476 | AU43: 45961 | AV43: 0 | AW43: Rail360 | AX43: for harleen and key stakeholders. | AY43: ana0017 | AZ43: woo0234 | CB43: 1|i0hkbk: | CJ43: 29/Oct/25 11:08 AM;ana0017;[~sid0070] to schedule a meeting to present the test case draft to Harleen.;;;
A44: =VLOOKUP(AK44,members!$A:$C,3,FALSE) -> Squadron | B44: =VLOOKUP(AK44,members!$A:$C,2,FALSE) -> Babu | C44: =X44 -> RPD-43 | D44: =AB44 -> Done | E44: =AU44 -> 45967 | F44: =W44 -> P220 - subtask to identify data points with Squadron team | G44: =AX44 -> requires design overview update for table level detail between CPKC DA's/ETL's and Squadron_x000D_ _x000D_ allocation of data points by layers _x000D_ _x000D_ [~tha0073] / [~cvps10] / [~kvxg11] / [~dan0243] to follow up | W44: P220 - subtask to identify data points with Squadron team | X44: RPD-43 | Y44: 187426 | Z44: 186079 | AA44: Sub-task | AB44: Done | AC44: RPD | AD44: Rail360 Product Development | AE44: software | AF44: las0044 | AI44: 3-High | AJ44: Done | AK44: tha0073 | AL44: woo0234 | AM44: woo0234 | AN44: 45967.463 | AO44: 45993.476 | AP44: 45967.466 | AQ44: 45993.476 | AU44: 45967 | AV44: 0 | AW44: Rail360 | AX44: requires design overview update for table level detail between CPKC DA's/ETL's and Squadron_x000D_ _x000D_ allocation of data points by layers _x000D_ _x000D_ [~tha0073] / [~cvps10] / [~kvxg11] / [~dan0243] to follow up | AY44: ana0017 | AZ44: cvps10 | BA44: sau0093 | BB44: woo0234 | CB44: 1|i0hqq4: | CJ44: 12/Nov/25 10:45 AM;ana0017;[~cvps10] arrange a call with ETL and Squadron team to Discuss data Points.;;; | CK44: 24/Nov/25 11:08 AM;woo0234;P220 bronze to silver transformation logic is needed.;;; | CL44: 26/Nov/25 11:26 AM;sau0093;Meeting today with CPKC team on Nov 26 to discuss this one ;;; | CM44: 27/Nov/25 11:05 AM;woo0234;11/27 make further progression column mapping and tables bronze and bronze to silver portion by [~sau0093] ;;; | CN44: 02/Dec/25 11:25 AM;cvps10;Data model pending as asked by Squadron team;;;
A45: =VLOOKUP(AK45,members!$A:$C,3,FALSE) -> ETL | B45: =VLOOKUP(AK45,members!$A:$C,2,FALSE) -> Vicky | C45: =X45 -> RPD-7 | D45: =AB45 -> Done | E45: =AU45 -> 45953 | F45: =W45 -> Set Out / Lift update (Vicky) | G45: =AX45 -> *Understanding lift / set out data along with work order for equipment on train or in yard. (TYES)*_x000D_ - architecture review with Kishore_x000D_ - review with TYES team (Ronald)_x000D_ - review with SADB to confirm data unavailability (that we don't have it) | W45: Set Out / Lift update (Vicky) | X45: RPD-7 | Y45: 186080 | AA45: Task | AB45: Done | AC45: RPD | AD45: Rail360 Product Development | AE45: software | AF45: las0044 | AI45: 3-High | AJ45: Done | AK45: pat0582 | AL45: woo0234 | AM45: woo0234 | AN45: 45951.583 | AO45: 45967.463 | AP45: 45967.463 | AQ45: 45967.463 | AU45: 45953 | AV45: 0 | AW45: Rail360 | AX45: *Understanding lift / set out data along with work order for equipment on train or in yard. (TYES)*_x000D_ - architecture review with Kishore_x000D_ - review with TYES team (Ronald)_x000D_ - review with SADB to confirm data unavailability (that we don't have it) | AY45: woo0234 | CB45: 1|i0hj30: | CJ45: 24/Oct/25 11:20 AM;woo0234;now it is going with non B Flag locations too and this is under review.;;; | CK45: 05/Nov/25 11:27 AM;woo0234;set out / lift data was found in TYES/RPM level (upper stream of data we use);;;
A46: =VLOOKUP(AK46,members!$A:$C,3,FALSE) -> ETL | B46: =VLOOKUP(AK46,members!$A:$C,2,FALSE) -> Vicky | C46: =X46 -> RPD-28 | D46: =AB46 -> Done | E46: =AU46 -> 45957 | F46: =W46 -> Set Out / Lift update (identify datapoint within SADB in house first) | G46: =AX46 -> if it requires further investigation, [~ana0017] and [~woo0234] will validate_x000D_ _x000D_ and [~ana0017] will weigh in with Neeraj_x000D_ _x000D_ _x000D_ _x000D_ | W46: Set Out / Lift update (identify datapoint within SADB in house first) | X46: RPD-28 | Y46: 186286 | Z46: 186080 | AA46: Sub-task | AB46: Done | AC46: RPD | AD46: Rail360 Product Development | AE46: software | AF46: las0044 | AI46: 3-High | AJ46: Done | AK46: pat0582 | AL46: woo0234 | AM46: woo0234 | AN46: 45954.475 | AO46: 45967.463 | AP46: 45967.463 | AQ46: 45967.463 | AU46: 45957 | AV46: 0 | AW46: Rail360 | AX46: if it requires further investigation, [~ana0017] and [~woo0234] will validate_x000D_ _x000D_ and [~ana0017] will weigh in with Neeraj_x000D_ _x000D_ _x000D_ _x000D_ | AY46: ana0017 | AZ46: pat0582 | BA46: woo0234 | CB46: 1|i0hkb8: | CJ46: 27/Oct/25 11:16 AM;woo0234;trying to visualize within PBI for review with [~woo0234] [~ana0017] [~sid0070] by [~pat0582] ;;; | CK46: 28/Oct/25 10:57 AM;pat0582;The logic has been built and internally reviewed. Refinements are pending based on the gaps if any that we identify verifying the data with parallel systems such as TYES. _x000D_ _x000D_ _x000D_ _x000D_ Once the logic validation is done, the plan is to develop following datapoints from available data - in a phased manner -_x000D_ _x000D_ _x000D_ _x000D_ The target location where these fields are to be stored is TBD based on review with Kishore and David and SADB if required. _x000D_ _x000D_ phase 1 - _x000D_ _x000D_ _x000D_ • LIFT_EVENT_TMS_x000D_ • LIFT_SCAC_CD_x000D_ • LIFT_FSAC_CD_x000D_ • LIFT_TRSTN_VRSN_NBR_x000D_ _x000D_ _x000D_ • SET_EVENT_TMS_x000D_ • SET_SCAC_CD_x000D_ • SET_FSAC_CD_x000D_ • SET_TRSTN_VRSN_NBR_x000D_ _x000D_ _x000D_ _x000D_ phase-2_x000D_ _x000D_ • CARE_OF_PARTY_CPRS_CSTMR_ID_x000D_ • LIFT_RPRTNG_TM_ZN_CD_x000D_ • LIFT_RPRTNG_TM_ZN_YR_NBR_x000D_ • SET_RPRTNG_TM_ZN_CD_x000D_ • SET_RPRTNG_TM_ZN_YR_NBR_x000D_ _x000D_ • LIFT_MVMNT_EVENT_ID_x000D_ _x000D_ • SET_MVMNT_EVENT_ID_x000D_ _x000D_ ;;; | CL46: 30/Oct/25 10:52 AM;ana0017;[~pat0582] please update the Jira with all the details;;; | CM46: 30/Oct/25 10:57 AM;pat0582;Set-Life is logic is being firmed up to iron out gaps I/we found while testing the logic with multiple trains internally. _x000D_ _x000D_ By next week, we can have it finalized for review with Kishore/David/SADB for the approval of logic to go ahead with next steps of where to target this data - in a new table or in any other way. ;;;
A47: =VLOOKUP(AK47,members!$A:$C,3,FALSE) -> BDA | B47: =VLOOKUP(AK47,members!$A:$C,2,FALSE) -> Pankaj | C47: =X47 -> RPD-3 | D47: =AB47 -> Done | E47: =AU47 -> 45951 | F47: =W47 -> P140 creation | G47: =AX47 -> Obtaining approval for P140_x000D_ - revising / updating P140 to reflect the platform changes, MDM composition, and preliminary requirement for regulatory tonnage data | W47: P140 creation | X47: RPD-3 | Y47: 186074 | AA47: Task | AB47: Done | AC47: RPD | AD47: Rail360 Product Development | AE47: software | AF47: las0044 | AI47: 3-High | AJ47: Done | AK47: ana0017 | AL47: woo0234 | AM47: woo0234 | AN47: 45951.574 | AO47: 45967.46 | AP47: 45967.46 | AQ47: 45967.46 | AU47: 45951 | AV47: 0 | AW47: Rail360 | AX47: Obtaining approval for P140_x000D_ - revising / updating P140 to reflect the platform changes, MDM composition, and preliminary requirement for regulatory tonnage data | AY47: woo0234 | BE47: 28800 | BF47: 28800 | BH47: 0 | BI47: 28800 | BJ47: 28800 | CB47: 1|i0hj1o: | CJ47: 24/Oct/25 11:28 AM;woo0234;updating based on decisions made with Paul's team regarding the use of MDM sources.;;;
A48: =VLOOKUP(AK48,members!$A:$C,3,FALSE) -> PM | B48: =VLOOKUP(AK48,members!$A:$C,2,FALSE) -> Robert | C48: =X48 -> RPD-40 | D48: =AB48 -> Done | E48: =AU48 -> 45967 | F48: =W48 -> P140 draft review with Sangtae | G48: =AX48 -> draft is crafted by [~pat0582] and [~ana0017] | W48: P140 draft review with Sangtae | X48: RPD-40 | Y48: 187290 | Z48: 186074 | AA48: Sub-task | AB48: Done | AC48: RPD | AD48: Rail360 Product Development | AE48: software | AF48: las0044 | AI48: 3-High | AJ48: Done | AK48: las0044 | AL48: woo0234 | AM48: woo0234 | AN48: 45966.469 | AO48: 45967.46 | AP48: 45967.46 | AQ48: 45967.46 | AU48: 45967 | AV48: 0 | AX48: draft is crafted by [~pat0582] and [~ana0017] | AY48: woo0234 | CB48: 1|i0hpx0:
A49: =VLOOKUP(AK49,members!$A:$C,3,FALSE) -> Architect | B49: =VLOOKUP(AK49,members!$A:$C,2,FALSE) -> David | C49: =X49 -> RPD-27 | D49: =AB49 -> In Progress | E49: =AU49 -> 46010 | F49: =W49 -> P219- update and details | G49: =AX49 -> Just a follow up task for P219 document in daily scrum meeting. | W49: P219- update and details | X49: RPD-27 | Y49: 186240 | AA49: Task | AB49: In Progress | AC49: RPD | AD49: Rail360 Product Development | AE49: software | AF49: las0044 | AI49: 3-High | AK49: ngu0018 | AL49: ana0017 | AM49: ana0017 | AN49: 45953.473 | AO49: 46001.431 | AP49: 45966.485 | AU49: 46010 | AV49: 0 | AX49: Just a follow up task for P219 document in daily scrum meeting. | AY49: ana0017 | AZ49: cvps10 | BA49: ngu0018 | BB49: woo0234 | CB49: 1|i0hk1o: | CJ49: 28/Oct/25 11:20 AM;woo0234;[~ngu0018] mentioned that this task also requires Squadron's assistance for part of this work;;; | CK49: 28/Oct/25 11:26 AM;ngu0018;SG2 P219 documentation started and planned for first draft for initial review by end of day November 7th. Will need the latest P140. Squadron team's involvement in the architecture is required. David will reach out to Squadron for support on P219 details wrt Snowflake architecture and Train product solution design. ;;; | CL49: 29/Oct/25 10:39 AM;ana0017;[~ngu0018] Sent the updated P140 yesterday after the meeting please review the document and if any questions please let me know._x000D_ _x000D_ _x000D_ _x000D_ Thank you!_x000D_ _x000D_ ;;; | CM49: 04/Nov/25 9:36 AM;ngu0018;Still in progress. Consulting with Squadron and Snowflake for proper foundational set up in Snowflake for development. Aiming to still get first draft for review with EA end of week, Nov 7th.;;; | CN49: 10/Nov/25 11:04 AM;woo0234;no ETA changes end 14th of November.;;; | CO49: 17/Nov/25 10:42 AM;ngu0018;Initial draft created, with some outstanding details to be documented in the coming days. _x000D_ _x000D_ Bigger item to be sorted. Due to technical blocker preventing the setup of Snowflake Openflow due to the platform not supporting AWS PrivateLin, which is CPKC's standard for private network communication, it will be necessary to discuss alternative deployment options for Openflow (such as the BOYC version) or other available solutions. A decision record must be created and reviewed by Enterprise Architecture (EA) and security teams, with their approval required before moving forward. All relevant details will be documented in the P219, and updates will be provided once a final decision is made and necessary approvals are obtained.;;; | CP49: 17/Nov/25 10:54 AM;ana0017;[~ngu0018] would you be able to share the P219 draft with team. please do share over the email or Teams Rail 360 scrum group._x000D_ _x000D_ _x000D_ _x000D_ Thank you!_x000D_ _x000D_ _x000D_ _x000D_ ;;; | CQ49: 02/Dec/25 11:32 AM;cvps10;P219 first draft is ready for review;;; | CR49: 04/Dec/25 7:16 PM;ngu0018;Latest P219s version submitted to EA for review;;; | CS49: 08/Dec/25 11:02 AM;woo0234;[~tig0002] for update;;; | CT49: 10/Dec/25 10:17 AM;ngu0018;Sent Kishore a follow up for his review of the latest draft. Once he's finalized his input, will update and circulate to Harleen for review. ;;;
A50: =VLOOKUP(AK50,members!$A:$C,3,FALSE) -> BDA | B50: =VLOOKUP(AK50,members!$A:$C,2,FALSE) -> Sangtae | C50: =X50 -> RPD-15 | D50: =AB50 -> Done | E50: =AU50 -> 45954 | F50: =W50 -> Interview with Stakeholders for Product Design | G50: =AX50 -> Product design, user interfaces, and self service analytics requirement gathering from key stakeholders with departments leaders including operating analytics, mechanical, engineering, finance, and regulatory teams (key user groups) | W50: Interview with Stakeholders for Product Design | X50: RPD-15 | Y50: 186091 | AA50: Task | AB50: Done | AC50: RPD | AD50: Rail360 Product Development | AE50: software | AF50: las0044 | AI50: 3-High | AJ50: Done | AK50: woo0234 | AL50: woo0234 | AM50: woo0234 | AN50: 45951.618 | AO50: 45958.725 | AP50: 45958.725 | AQ50: 45958.725 | AU50: 45954 | AV50: 0 | AW50: Rail360 | AX50: Product design, user interfaces, and self service analytics requirement gathering from key stakeholders with departments leaders including operating analytics, mechanical, engineering, finance, and regulatory teams (key user groups) | AY50: woo0234 | BI50: 720 | BJ50: 720 | BL50: RPD-16 | CB50: 1|i0hj5g:
A51: =VLOOKUP(AK51,members!$A:$C,3,FALSE) -> BDA | B51: =VLOOKUP(AK51,members!$A:$C,2,FALSE) -> Sangtae | C51: =X51 -> RPD-19 | D51: =AB51 -> Done | E51: =AU51 -> 45958 | F51: =W51 -> Interview - Finance | G51: =AX51 -> Interview - Finance | W51: Interview - Finance | X51: RPD-19 | Y51: 186095 | Z51: 186091 | AA51: Sub-task | AB51: Done | AC51: RPD | AD51: Rail360 Product Development | AE51: software | AF51: las0044 | AI51: 3-High | AJ51: Done | AK51: woo0234 | AL51: woo0234 | AM51: woo0234 | AN51: 45951.621 | AO51: 45958.725 | AP51: 45958.725 | AQ51: 45958.725 | AU51: 45958 | AV51: 0 | AW51: Rail360 | AX51: Interview - Finance | AY51: woo0234 | BE51: 180 | BF51: 180 | BH51: 0 | BI51: 180 | BJ51: 180 | CB51: 1|i0hj6c: | CJ51: 27/Oct/25 7:02 PM;woo0234;interview set up on October 28th;;;
A52: =VLOOKUP(AK52,members!$A:$C,3,FALSE) -> PM | B52: =VLOOKUP(AK52,members!$A:$C,2,FALSE) -> Robert | C52: =X52 -> RPD-38 | D52: =AB52 -> Done | E52: =AU52 -> 45961 | F52: =W52 -> R4J document to be done by PM | G52: =AX52 -> [~ana0017] already have approved P140 document and details can be entered back into system by [~las0044] | W52: R4J document to be done by PM | X52: RPD-38 | Y52: 186600 | AA52: Task | AB52: Done | AC52: RPD | AD52: Rail360 Product Development | AE52: software | AF52: las0044 | AI52: 3-High | AJ52: Done | AK52: las0044 | AL52: woo0234 | AM52: woo0234 | AN52: 45958.509 | AO52: 45964.463 | AP52: 45958.509 | AQ52: 45964.463 | AU52: 45961 | AV52: 0 | AW52: Rail360 | AX52: [~ana0017] already have approved P140 document and details can be entered back into system by [~las0044] | AY52: woo0234 | CB52: 1|i0hlr0:
A53: =VLOOKUP(AK53,members!$A:$C,3,FALSE) -> BDA | B53: =VLOOKUP(AK53,members!$A:$C,2,FALSE) -> Pankaj | C53: =X53 -> RPD-37 | D53: =AB53 -> Done | E53: =AU53 -> 45961 | F53: =W53 -> business transformation document (revised for issue type change) | G53: =AX53 -> Updated:4 days ago 10:27 AM_x000D_ h3. Description_x000D_ Document Business rules - get the code from ETL and Qlik and convert them into plain English for Squadron team._x000D_ explain in plain English for business rule_x000D_ _x000D_ Try to put plain English in OUR (CPKC Employee's) understanding then fabricate with A.I._x000D_ do not start with A.I. | W53: business transformation document (revised for issue type change) | X53: RPD-37 | Y53: 186599 | AA53: Task | AB53: Done | AC53: RPD | AD53: Rail360 Product Development | AE53: software | AF53: las0044 | AI53: 3-High | AJ53: Done | AK53: ana0017 | AL53: woo0234 | AM53: woo0234 | AN53: 45958.508 | AO53: 45964.429 | AP53: 45958.508 | AQ53: 45964.429 | AU53: 45961 | AV53: 0 | AW53: Rail360 | AX53: Updated:4 days ago 10:27 AM_x000D_ h3. Description_x000D_ Document Business rules - get the code from ETL and Qlik and convert them into plain English for Squadron team._x000D_ explain in plain English for business rule_x000D_ _x000D_ Try to put plain English in OUR (CPKC Employee's) understanding then fabricate with A.I._x000D_ do not start with A.I. | AY53: ana0017 | AZ53: woo0234 | CB53: 1|i0hlqs: | CJ53: 29/Oct/25 10:35 AM;ana0017;Sent to [~pat0582] and [~woo0234] to Review.;;; | CK53: 30/Oct/25 10:51 AM;ana0017;Reviewed with Vicky will close it by 31st with minor changes.;;;

Sheet members
A1: Assignee | B1: Name | C1: Team
A2: knxn12 | B2: Naveen | C2: ETL
A3: pat0606 | B3: Harshil Patel | C3: Squadron
A4: aro0027 | B4: Jatin | C4: Celebal
A5: bor0475 | B5: VishnuB | C5: QE
A6: tha0073 | B6: Babu | C6: Squadron
A7: cvps10 | B7: VPS | C7: BDA
A8: dan0243 | B8: Hisham | C8: Squadron
A9: ngu0018 | B9: David | C9: Architect
A10: sin0404 | B10: Jatinder | C10: ETL
A11: sid0070 | B11: Raheel | C11: QE
A12: rav0018 | B12: Karthik | C12: Architect
... A22: seh0018 | B22: Nikhil | C22: MDM

Sheet Data_Dictionary
A1: Dimension | B1: Field_Name | C1: Data Dictionary | D1: Businsess Glossary | E1: How it works | F1: Example or Methodology | G1: Data Type | H1: Source System | I1: Validation Rules
A2: Time | B2: Train Year | C2: Calendar year of the actual departure from origin for this train instance. | D2: The calendar year when the train started its journey from the origin station. Derived from the train's departure timestamp and used to group train operations by year. | E2: If Train 180-01 departed on February 1st, 2025 at 15:20 CT, the Train Year would be 2025. | F2: 2025 | G2: String | H2: SADB/TYES | I2: String, max length 50 | K2: Optional
A3: Time | B3: Train Quarter | C3: Quarter that a train departed from its origin | D3: The quarter (Q1 to Q4) in which the train departed from its origin station. Helps in analyzing train operations on a quarterly basis. | E3: If a train departed in February 2025, the Train Quarter would be Q1. | F3: 1 | G3: String | H3: SADB/TYES | I3: String, max length 50 | K3: mandate
A4: Time | B4: Train Month | C4: Month that a train departed from its origin | D4: The month (e.g., January, February) when the train departed from its origin station. Useful for monthly trend analysis. | E4: If a train departed on February 1st, 2025, the Train Month would be February. | F4: 2 | G4: String | H4: SADB/TYES | I4: String, max length 50
A5: Time | B5: Train Day | C5: Day that a train departed from its origin | D5: The specific calendar day when the train departed from its origin station. Enables daily tracking of train movements. | E5: If a train departed on February 1st, 2025, the Train Day would be 1. | F5: 25 | G5: String | H5: SADB/TYES | I5: String, max length 50
A6: Time Stamp | B6: SADB_RECEIVING_DT | C6: Reporting time stamp for most recent events at the time train was reported | D6: The timestamp indicating when the latest event data for the train was received into the system. Used for tracking and reporting purposes. | F6: 8/2/25 0:00 | G6: DateTime | H6: SADB/TYES | I6: Format: YYYY-MM-DD HH:MM:SS
A7: System | B7: SRC_SYS | C7: Source systems such as KCS = MCS or CP = TYES | D7: Identifies the originating system that provided the train data. Helps in understanding data lineage and system-specific attributes. | F7: KCS | G7: String | H7: System Metadata | I7: String, max length 50
A8: Train | B8: TRAIN_SERIES | C8: Train series identifier | D8: A numeric identifier that groups trains into a series based on operational or scheduling similarities. Useful for tracking performance trends across similar train types. | E8: Train series 100 may represent a group of freight trains operating on a specific corridor. | F8: 100 | G8: Integer | H8: SADB/TYES | I8: Numeric, >=0
A9: Train | B9: TRAIN_SYMBOL | C9: Train symbol code | D9: A short code used to uniquely identify a train's operational schedule or route. Often used in dispatching and tracking systems. | E9: Symbol 181 may refer to a train running from Laredo to Kansas City. | F9: 181 | G9: String | H9: SADB/TYES | I9: String, max length 50
A10: Train | B10: TRAIN_NAME | C10: Train name | D10: A descriptive name combining the train symbol and additional identifiers to distinguish specific train instances. | E10: Train name 181-01 indicates the first instance of train symbol 181. | F10: 181-01 | G10: String | H10: SADB/TYES | I10: String, max length 50
A11: Train | B11: TRAIN_TYPE_CD | C11: Train type code | D11: A code representing the general category of the train, such as freight (FRT), passenger, or work train. | E11: FRT indicates a freight train. | F11: FRT | G11: String | H11: SADB/TYES | I11: String, max length 50
A12: Train | B12: TRAIN_KIND_CD | C12: Train kind code | D12: Indicates whether the train is a primary or secondary service type. Helps in prioritizing train movements. | E12: PRIM indicates a primary train service. | F12: PRIM | G12: Boolean | H12: SADB/TYES | I12: {Y,N}
A13: Train | B13: TYPE | C13: Train operational type | D13: Defines the operational nature of the train, such as 'OP' for operational or 'TEST' for test runs. | E13: OP indicates a regular operational train. | F13: OP | G13: String | H13: SADB/TYES | I13: String, max length 50
A14: Location | B14: DEPART_FSAC | C14: Departure FSAC code | D14: FSAC is a unique 5-digit station location reference number derived from the station name. The departure FSAC code identifies the station where the train began its journey or segment. | E14: The departure FSAC code is assigned based on the station from which the train departed. It is used for tracking, reporting, and linking train events to specific locations. | F14: 5770 | G14: String | H14: DIM_LOCATION | I14: String, max length 50
A15: Location | B15: ARRIVE_FSAC | C15: Arrival FSAC code | D15: FSAC is a unique 5-digit station location reference number derived from the station name. The arrival FSAC code identifies the station where the train ended its journey or segment. | E15: The arrival FSAC code is assigned based on the station where the train arrived. It is used for tracking, reporting, and linking train events to specific locations. | F15: 5772 | G15: String | H15: DIM_LOCATION | I15: String, max length 50
A16: Time Stamp | B16: ARRIVE_TMS | C16: Arrival timestamp | D16: Date/Time when a shipment/Equipment Arrives at a particular location | E16: Report Time associated with AAR_STNDRD_EVENT_CD of ARRI (Arrived at Destination), ARIL (Arrival intermediate location) | F16: 8/1/25 23:43 | G16: DateTime | H16: SADB/TYES | I16: Format: YYYY-MM-DD HH:MM:SS
A17: Time Stamp | B17: DEPART_TMS | C17: Departure timestamp | D17: Date/Time when a shipment/Equipment Departs from a particular location | E17: Report Time associated with AAR_STNDRD_EVENT_CD of DFLC (Depart from Location, Depart Passing Outbound, Departure) | F17: 8/1/25 21:37 | G17: DateTime | H17: SADB/TYES | I17: Format: YYYY-MM-DD HH:MM:SS
A18: Train | B18: TITAN_NBR | C18: Titan number for train | D18: A unique identifier assigned to each train instance for tracking and reporting purposes. | E18: Titan number 942442 uniquely identifies a specific train but often found it has been reused after 2-3 months | F18: 942442 | G18: Integer | H18: SADB/TYES | I18: Numeric, >=0
A19: Miles | B19: TRAIN_MILES | C19: Total train miles | D19: The movement of a train times the distance in miles traveled, based on the actual distance run between terminals and/or stations computed from official timetables or distance tables. | E19: Sum of all train miles travelled by lead locomotive. | F19: 7.986 | G19: Decimal | H19: SADB/TYES | I19: Numeric, precision up to 3 decimals | J19: if Train miles > 0, Gross ton miles >0
A20: Miles | B20: CONTENT_TON_MILES | C20: Content ton miles | D20: measures the total tonnage of cargo (content) transported by a train, multiplied by the distance (in miles) that the cargo travels. This metric is used to assess the volume of freight moved over a given distance, supporting operational analysis, billing, and regulatory reporting. It reflects the productivity of train operations by quantifying how much cargo is moved and how far it is transported. | E20: Example: If a train carries 1,000 tons of cargo for 100 miles, the Content Ton Miles is 100,000. Calculation: Content Ton Miles=∑(Net Weight of Cargo (tons)×Miles Traveled)Content Ton Miles=∑(Net Weight of Cargo (tons)×Miles Traveled) | F20: 16043.874 | G20: Decimal | H20: SADB/TYES | I20: Numeric, precision up to 3 decimals
A21: Equipment | B21: TARE_WEIGHT_TONS_QTY | C21: Tare weight in tons | D21: Tare weight of the equipment in tons (empty weight). | E21: TARE_WEIGHT_TONS_QTY 30 for a 30-ton empty car. | F21: 66 | G21: Decimal | H21: AEI/Umler | I21: Numeric, precision up to 3 decimals
A22: Equipment | B22: NET_WEIGHT_TONS_QTY | C22: Net weight in tons | D22: Net weight of the commodity in the equipment, in tons. | E22: NET_WEIGHT_TONS_QTY 100 for a loaded grain car. | F22: 104 | G22: Decimal | H22: AEI/Umler | I22: Numeric, precision up to 3 decimals
A23: Weight | B23: LOCO_FULL_WEIGHT | C23: Locomotive full weight | D23: The total weight of a locomotive, including its frame, engine, and all permanently attached components. Used for train performance calculations and regulatory compliance. | E23: The locomotive full weight is recorded for each locomotive and used to calculate total train weight, braking requirements, and compliance with track and bridge limits. | F23: 424 | G23: Decimal | H23: SADB/TYES | I23: Numeric, precision up to 3 decimals
A24: Weight | B24: TARE_TONS | C24: Total tare tons | D24: The combined tare weight (empty weight) of all railcars or equipment in a train, excluding any cargo or lading. Used to determine net and gross weights for operational and billing purposes. | E24: Tare tons are summed for all empty cars in a train to calculate the total empty weight, which is then added to the net cargo weight to determine the gross train weight. | F24: 1598.45 | G24: Decimal | H24: SADB/TYES | I24: Numeric, precision up to 3 decimals
A25: Time | B25: TRAIN_HRS | C25: Train hours | D25: Total hours a train is in operation from departure to arrival. | E25: Calculated as elapsed time in hours between departure and arrival timestamps. | F25: 2 | G25: String | H25: SADB/TYES | I25: String, max length 50
A26: Time | B26: TRAIN_MINS | C26: Train minutes | D26: Total minutes a train is in operation from departure to arrival. | E26: Calculated as elapsed time in minutes between departure and arrival timestamps. | F26: 6.02 | G26: String | H26: SADB/TYES | I26: String, max length 50
A27: Miles | B27: EQPMT_MILES | C27: Equipment miles | D27: Total miles traveled by all equipment in a train. | E27: Sum of miles traveled by each piece of equipment during the journey. | F27: 167.706 | G27: Decimal | H27: SADB/TYES | I27: Numeric, precision up to 3 decimals
A28: TonneMiles | B28: TARE_TON_MILES | C28: Tare ton miles | D28: Tare tones multiplied by tonnage of the equipment associated with the tare tones | E28: Logic to be confirmed based on source system and data lineage. | F28: 9379.158 | G28: Decimal | H28: SADB/TYES | I28: Numeric, precision up to 3 decimals
A29: TonneMiles | B29: GROSS_TON_MILES | C29: Gross ton miles | D29: Sum of tare plus content, multiplied by the actual car miles incurred. Includes tare and content tons of cars and deadhead locomotives, and company resource equipment (vans, business cars, robot locomotives, passenger cars or work cars reported on the freight journal). | F29: 25423.032 | G29: Decimal | H29: SADB/TYES | I29: Numeric, precision up to 3 decimals
A30: TonneMiles | B30: DH_TARE_TON_MILES | C30: Deadhead tare ton miles | D30: Tare ton miles represent empty weight multiplied by miles traveled. | E30: Multiply tare weight (tons) by miles traveled for each equipment and sum. | F30: 0 | G30: Decimal | H30: SADB/TYES | I30: Numeric, precision up to 3 decimals
A31: TonneMiles | B31: LOCO_TARE_TON_MILES | C31: Locomotive tare ton miles | D31: Tare ton miles represent empty weight multiplied by miles traveled. | E31: Multiply tare weight (tons) by miles traveled for each equipment and sum. | F31: 3386.064 | G31: Decimal | H31: SADB/TYES | I31: Numeric, precision up to 3 decimals
A32: Miles | B32: REV_CAR_MILES_LOADED | C32: Revenue car miles loaded | D32: Miles traveled by loaded revenue cars. | E32: Sum miles traveled by each loaded revenue car. | F32: 167.706 | G32: Decimal | H32: SADB/TYES | I32: Numeric, precision up to 3 decimals
A33: Miles | B33: REV_CAR_MILES_EMPTY | C33: Revenue car miles empty | D33: Miles traveled by empty revenue cars. | E33: Sum miles traveled by each empty revenue car. | F33: 0 | G33: Decimal | H33: SADB/TYES | I33: Numeric, precision up to 3 decimals
A34: Miles | B34: LIVE_LOCO_MILES | C34: Live locomotive miles | D34: Miles traveled by locomotives (live or deadhead). | E34: Sum miles traveled by each locomotive based on its status. | F34: 15.972 | G34: Decimal | H34: SADB/TYES | I34: Numeric, precision up to 3 decimals
A35: Miles | B35: DH_LOCO_MILES | C35: Deadhead locomotive miles | D35: Miles traveled by locomotives (live or deadhead). | E35: Sum miles traveled by each locomotive based on its status. | F35: 0 | G35: Decimal | H35: SADB/TYES | I35: Numeric, precision up to 3 decimals
A36: Miles | B36: PASS_BUS_MILES | C36: Passenger business miles | D36: Total miles traveled by passenger business cars (e.g., business, inspection, or special event cars). | E36: Sum the miles traveled by each passenger business car during the reporting period. | F36: 0 | G36: Decimal | H36: SADB/TYES | I36: Numeric, precision up to 3 decimals
A37: Miles | B37: WORK_CAR_MILES | C37: Work car miles | D37: Total miles traveled by work cars (maintenance-of-way or service cars), used for tracking support operations. | E37: Sum the miles traveled by each work car during the reporting period. | F37: 0 | G37: Decimal | H37: SADB/TYES | I37: Numeric, precision up to 3 decimals
A38: Miles | B38: CABOOSE_MILES | C38: Caboose miles | D38: Total miles traveled by cabooses, used for historical reporting or special operations. | E38: Sum the miles traveled by each caboose during the reporting period. | F38: 0 | G38: Decimal | H38: SADB/TYES | I38: Numeric, precision up to 3 decimals
A39: Miles | B39: LIVE_LOCO_HP_MILES | C39: Live locomotive horsepower miles | D39: Miles traveled by locomotives (live or deadhead). | E39: Sum miles traveled by each locomotive based on its status. | F39: 69478.2 | G39: Decimal | H39: SADB/TYES | I39: Numeric, precision up to 3 decimals
A40: Miles | B40: DH_LOCO_HP_MILES | C40: Deadhead locomotive horsepower miles | D40: Miles traveled by locomotives (live or deadhead). | E40: Sum miles traveled by each locomotive based on its status. | F40: 0 | G40: Decimal | H40: SADB/TYES | I40: Numeric, precision up to 3 decimals
A41: Length | B41: LIVE_LOCO_FOOT_MILES | C41: Live locomotive foot miles | D41: Miles traveled by locomotives (live or deadhead). | E41: Sum miles traveled by each locomotive based on its status. | F41: 1224.52 | G41: Decimal | H41: SADB/TYES | I41: Numeric, precision up to 3 decimals
... A48: Equipment | B48: EQPUN_NBR | C48: Equipment number | D48: The identifying number on the piece of equipment (car or locomotive). | E48: EQPUN_NBR 123456 for car CP123456. | F48: 55688 | G48: Integer | H48: AEI/Umler | I48: Numeric, >=0
A49: Equipment | B49: Load_Empty_Ind | C49: Load or empty indicator of equipment on a train | D49: Indicator showing whether equipment on a train is loaded or empty. | E49: Y = Loaded, N = Empty. | G49: String | H49: AEI/Umler | I49: String, max length 50
A50: Waybill | B50: Cycle_Serial_Nbr | C50: Shipment cycle serial number | D50: Unique identifier used to manage cycles of railway equipment | E50: A new CSN is created when equipment is waybilled or Load/Empty indicator changes (602242530) | F50: 667123456 | G50: String | H50: SAP/TMS | I50: String, max length 50
A51: Waybill | B51: WYBL_NBR | C51: Waybill number | D51: Waybill number assigned to the shipment or equipment for tracking. | E51: WYBL_NBR 987654 for shipment from Toronto to Vancouver. | G51: Integer | H51: SAP/TMS | I51: Numeric, >=0
A52: Waybill | B52: Wybl_ID | C52: Waybill internal ID | D52: Internal identifier for a waybill, used for tracking and referencing shipments. | E52: Assigned by the system when a waybill is created; used to link shipment records. | G52: Integer | H52: SAP/TMS | I52: Numeric, >=0
A53: Waybill | B53: ORIGIN_SCAC_CD | C53: Origin SCAC code | D53: SCAC code of the origin carrier handling the equipment. | E53: ORIGIN_SCAC_CD 'CPRS' for Canadian Pacific. | F53: KCSM | G53: String | H53: SAP/TMS | I53: String, max length 50
A54: Waybill | B54: DSTNTN_SCAC_CD | C54: Destination SCAC code | D54: SCAC code of the destination carrier handling the equipment. | E54: DSTNTN_SCAC_CD 'NS' for Norfolk Southern. | F54: CPRS | G54: String | H54: SAP/TMS | I54: String, max length 50
A55: Waybill | B55: ORIGIN_FSAC_CD | C55: Origin FSAC code | D55: Freight Station Accounting Code (FSAC) of the origin station. | E55: ORIGIN_FSAC_CD 5770 for Laredo Bridge. | F55: 426 | G55: String | H55: SAP/TMS | I55: String, max length 50
A56: Waybill | B56: DSTNTN_FSAC_CD | C56: Destination FSAC code | D56: FSAC code of the destination station. | E56: DSTNTN_FSAC_CD 4541 for Chicago. (Bensenville IMS) | F56: 4541 | G56: String | H56: SAP/TMS | I56: String, max length 50
A57: Waybill | B57: ORIGIN_STN_NM | C57: Origin station name of equipment | D57: Station Name for where the waybilled equipment Originated | E57: Laredo Bridge if SCAC equals 'CPRS' and FSAC equals '05770' | G57: String | H57: SAP/TMS | I57: String, max length 50
A58: Waybill | B58: DSTNTN_STN_NM | C58: Destination station name of equipment | D58: Station Name for where the waybilled equipment is destined | E58: Winnipeg if SCAC equals 'CPRS' and FSAC equals '05200" | G58: String | H58: SAP/TMS | I58: String, max length 50
A59: Time | B59: Train Year | C59: Calendar year of the actual departure from origin for this train instance. | D59: The calendar year when the train started its journey from the origin station. Derived from the train's departure timestamp and used to group train operations by year. | E59: If Train 180-01 departed on February 1st, 2025 at 15:20 CT, the Train Year would be 2025. | F59: Based on DFLC TMS | G59: DateTime | H59: SADB/TYES | I59: Must be valid timestamp format (YYYY-MM-DD HH:MM:SS)
A60: Time | B60: Train Quarter | C60: Quarter that a train departed from its origin | D60: The quarter (Q1 to Q4) in which the train departed from its origin station. Helps in analyzing train operations on a quarterly basis. | E60: If a train departed in February 2025, the Train Quarter would be Q1. | F60: Based on DFLC TMS | G60: DateTime | H60: SADB/TYES | I60: Must be valid timestamp format (YYYY-MM-DD HH:MM:SS)
A61: Time | B61: Train Month | C61: Month that a train departed from its origin | D61: The month (e.g., January, February) when the train departed from its origin station. Useful for monthly trend analysis. | E61: If a train departed on February 1st, 2025, the Train Month would be February. | F61: Based on DFLC TMS | G61: DateTime | H61: SADB/TYES | I61: Must be valid timestamp format (YYYY-MM-DD HH:MM:SS)
A62: Time | B62: Train Day | C62: Day that a train departed from its origin | D62: The specific calendar day when the train departed from its origin station. Enables daily tracking of train movements. | E62: If a train departed on February 1st, 2025, the Train Day would be 1. | F62: Based on DFLC TMS | G62: DateTime | H62: SADB/TYES | I62: Must be valid timestamp format (YYYY-MM-DD HH:MM:SS)
A63: Waybill | B63: ORIGIN_TRSTN_VRSN_NBR | C63: Origin transition version number | D63: Transition version number for the origin station in a shipment’s route. | E63: Indicates the version or update sequence for the origin transition; used for auditing and tracking changes. | F63: 3 | G63: String | H63: SAP/TMS | I63: General text, max length 100
A64: Waybill | B64: DSTNTN_TRSTN_VRSN_NBR | C64: Destination transition version number | D64: Transition version number for the destination station in a shipment’s route. | E64: Indicates the version or update sequence for the destination transition; used for auditing and tracking changes. | F64: 10 | G64: String | H64: SAP/TMS | I64: General text, max length 100
A65: Waybill | B65: SHPPR_CPRS_CSTMR_ID | C65: Shipper customer ID | D65: Chopcode (up to 8 Chars) of the Shipper for the equipment being moved | E65: TOYMOTSA for TOYOTA MOTOR SALES USA INC | F65: CPINTSER | G65: String | H65: SAP/TMS | I65: General text, max length 100
A66: Waybill | B66: CNSGN_CPRS_CSTMR_ID | C66: Consignee customer ID | D66: Chopcode (up to 8 Chars) of the Consignee for the equipment being moved | E66: TOYOTA for TOYOTA CANADA INC | F66: CPINTSER | G66: String | H66: SAP/TMS | I66: General text, max length 100
A67: Waybill | B67: CARE_OF_PARTY_CPRS_CSTMR_ID | C67: Care of party customer ID | D67: Chopcode (up to 8 Chars) of the Care of Party for the equipment being moved | E67: HANFORWA for L HANSENS FORWARDING LTD | G67: String | H67: SAP/TMS | I67: General text, max length 100
A68: Waybill | B68: CLRNC_PLATE_CD | C68: Clearance plate code | D68: The AAR publishes the “plates”, which are cross-section clearance profiles (like Plate B, C, H, etc.) showing the envelope a railcar must fit within. | E68: "C" 95% route coverage, "G-H" Intermodal double-stacks, tall tank/flat cars | F68: H | G68: String | H68: SAP/TMS | I68: General text, max length 100
A69: Waybill | B69: STCC_CD | C69: Standard Transportation Commodity Code | D69: seven-digit numeric classification system used to identify and categorize commodities on shipping documents/waybills. | E69: 3711215 for Trucks, 3711120 for Autos | F69: 9980205 | G69: String | H69: SAP/TMS | I69: General text, max length 100
A70: Waybill | B70: SUB-LOB | C70: Detailed line of business | D70: Detailed line of business classification for a shipment or train. | E70: Categorizes shipments for reporting and analysis; typically derived from commodity or customer data. | F70: PULP | G70: String | H70: SAP/TMS | I70: General text, max length 100
A71: Waybill | B71: LOB | C71: Line of business | D71: Line of business classification for a shipment or train. | E71: Used for high-level business segmentation and reporting; assigned based on commodity, customer, or service type. | F71: FOREST_PRODUCTS | G71: String | H71: SAP/TMS | I71: General text, max length 100
A72: Waybill | B72: HZCMD_MTRL_RSPNS_CD | C72: Hazardous material response code | D72: Hazardous material response code for a shipment or equipment. | E72: Indicates the required response or handling for hazardous materials; derived from waybill or regulatory data. | G72: String | H72: SAP/TMS | I72: General text, max length 100
A73: Waybill | B73: FSTWY_WYBL_NBR | C73: First waybill number | D73: First waybill number associated with a shipment or equipment. | E73: Used to track the initial waybill in a shipment’s lifecycle; supports auditing and traceability. | G73: String | H73: SAP/TMS | I73: General text, max length 100
A74: Waybill | B74: *Revenue in CAD? (active version) | C74: Revenue in Canadian funds | D74: Indicates if revenue for the shipment or train is recorded in Canadian dollars. | E74: Flag or value set based on billing system; used for financial reporting and currency conversion. | F74: Do we need to know how much revenue each train generates? | G74: String | H74: SAP/TMS | I74: General text, max length 100
A75: Waybill | B75: DG/HZD Indicator? | C75: Dangerous or Hazardous content indicator | D75: Dangerous or hazardous content indicator for a shipment or equipment. | E75: Flag set to “Y” or “N” based on commodity codes or regulatory requirements. | F75: NON HZD | G75: Boolean | H75: SAP/TMS | I75: Allowed values = {Y, N}
A76: Waybill | B76: REV_CAR_MILES_LOADED_IND | C76: Indicator for revenue car miles loaded | D76: Used to determine compliance, registration, or operational status. | E76: Derived from system flags or registry checks (e.g., Railinc, Umler). | G76: Boolean | H76: SAP/TMS | I76: Allowed values = {Y, N}
A77: Waybill | B77: REV_CAR_MILES_EMPTY_IND | C77: Indicator for revenue car miles empty | D77: Used to determine compliance, registration, or operational status. | E77: Derived from system flags or registry checks (e.g., Railinc, Umler). | G77: Boolean | H77: SAP/TMS | I77: Allowed values = {Y, N}
A78: Waybill | B78: EQPMT_ASGNMN_ID | C78: Equipment assignment ID | D78: Unique identifier for equipment assignment in a shipment or train consist. | E78: Assigned by the system when equipment is allocated; used for tracking and auditing. | F78: 5933239369 | G78: String | H78: SAP/TMS | I78: General text, max length 100
A79: Waybill | B79: SHPMT_ID | C79: Shipment ID | D79: Unique identifier for a shipment. | E79: Assigned by the system; used to link all records and events related to a shipment. | F79: 5933239360 | G79: String | H79: SAP/TMS | I79: General text, max length 100
A80: Location | B80: CNST_CHNG_MVMNT_EVENT_ID | C80: Consist change movement event ID | D80: Identifier for a consist change movement event. | E80: Assigned when a consist (train makeup) is changed; used for event tracking and auditing. | G80: String | H80: SADB/TYES/AEI | I80: General text, max length 100
A81: Location | B81: CNST_CHNG_SCAC_CD | C81: Consist change SCAC code | D81: The Standard Carrier Alpha Code, a unique two- to four-letter code assigned to transportation companies for what Railroad the change occured on | E81: CPRS would identify change happend on CPKC railroad | F81: CPRS | G81: String | H81: SADB/TYES/AEI | I81: Length <= 10, uppercase letters
A82: Location | B82: CNST_CHNG_FSAC_CD | C82: Consist change FSAC code | D82: The Freight Station Accounting Code, a five-digit numeric code used in the railroad industry to identify specific freight stations. | E82: 03409 would Identify change happened at Vaughan IMS location | F82: 5770 | G82: String | H82: SADB/TYES/AEI | I82: Length <= 10, uppercase letters
A83: Location | B83: CNST_CHNG_TRSTN_VRSN_NBR | C83: Consist change transition version number | D83: Transition version number for a consist change event. | E83: Indicates the version or update sequence for a consist change; supports auditing. | F83: 1 | G83: String | H83: SADB/TYES/AEI | I83: General text, max length 100
A84: Location | B84: CNST_LCM_OPRSTS_ID | C84: Consist LCM operations ID | D84: Identifier for consist LCM (Locomotive Consist Management) operations. | E84: Assigned by the system for tracking LCM events and changes. | G84: String | H84: SADB/TYES/AEI | I84: General text, max length 100
A85: Location | B85: SUBDIVISION | C85: Subdivision name | D85: Name of the railway subdivision associated with a location or movement. | E85: Derived from FSAC or station mapping; used for geographic and operational analysis. | F85: LAREDO | G85: String | H85: SADB/TYES/AEI | I85: General text, max length 100
A86: Location | B86: District | C86: District name | D86: Name of the railway district associated with a location or movement. | E86: Derived from FSAC or station mapping; used for higher-level geographic reporting. | F86: Southwest | G86: String | H86: SADB/TYES/AEI | I86: General text, max length 100
A87: Location | B87: ZONE | C87: Zone name | D87: Name of the Zone associated with the CPKC station as defined by the Business | E87: If CPKC Station Name is LAREDO YARD then ZONE equals SOUTHWEST | F87: SOUTHWEST | G87: String | H87: SADB/TYES/AEI | I87: General text, max length 100
A88: Location | B88: DIVISION | C88: Division name | D88: Name of the Division associated with the CPKC station as defined by the Business | E88: If CPKC Station Name is LAREDO YARD then Division equals South West | F88: South West | G88: String | H88: SADB/TYES/AEI | I88: General text, max length 100
A89: Location | B89: REGION | C89: Region name | D89: Name of the railway region associated with a location or movement. | E89: Derived from FSAC or station mapping; used for broad geographic reporting and analysis. | F89: Mexico | G89: String | H89: SADB/TYES/AEI | I89: General text, max length 100
A90: Location | B90: Country | C90: Country name | D90: Country associated with a location or movement. | E90: Derived from FSAC or station mapping; used for international reporting and compliance. | F90: US | G90: String | H90: SADB/TYES/AEI | I90: General text, max length 100
A91: Location | B91: Company | C91: Company name | D91: Name of the company associated with a train, equipment, or shipment. | E91: Derived from ownership or operating data; used for reporting and asset management. | F91: KCSR | G91: String | H91: SADB/TYES/AEI | I91: General text, max length 100
A92: Location | B92: RAIL_LINE | C92: Rail line name | D92: Name of the rail line associated with a location or movement. | E92: Derived from station or route data; used for routing and operational reporting. | F92: KCSR | G92: String | H92: SADB/TYES/AEI | I92: General text, max length 100
A93: Location | B93: ON_JNCTN_SCAC_CD | C93: On junction SCAC code | D93: SCAC code of the carrier from which equipment is received at a junction. | E93: ON_JNCTN_SCAC_CD 'CN' for Canadian National. | F93: CPRS | G93: String | H93: SADB/TYES/AEI | I93: Length <= 10, uppercase letters
A94: Location | B94: OFF_JNCTN_SCAC_CD | C94: Off junction SCAC code | D94: SCAC code of the carrier to which equipment is delivered at a junction. | E94: OFF_JNCTN_SCAC_CD 'BNSF' for BNSF Railway. | F94: CPRS | G94: String | H94: SADB/TYES/AEI | I94: Length <= 10, uppercase letters
A95: Location | B95: ON_JNCTN_FSAC_CD | C95: On junction FSAC code | D95: The Freight Station Accounting Code used to identify freight station where equipment is received at a junction | E95: ON_JNCTN_FSAC_CD "05770" would represent Laredo Bridge if SCAC equals 'CPRS' | F95: 5770 | G95: String | H95: SADB/TYES/AEI | I95: Length <= 10, uppercase letters
A96: Location | B96: OFF_JNCTN_FSAC_CD | C96: Off junction FSAC code | D96: The Freight Station Accounting Code used to identify freight station where equipment is delivered to at a junction | E96: OFF_JNCTN_FSAC_CD "04540" would represent Bensenville if SCAC equals 'CPRS' | F96: 4540 | G96: String | H96: SADB/TYES/AEI | I96: Length <= 10, uppercase letters
A97: Location | B97: ON_JNCTN_TRSTN_VRSN_NBR | C97: On junction transition version number | D97: Transition version number for the on-junction event. | E97: Indicates the version or update sequence for the on-junction transition; supports auditing. | F97: 1 | G97: String | H97: SADB/TYES/AEI | I97: General text, max length 100
A98: Location | B98: OFF_JNCTN_TRSTN_VRSN_NBR | C98: Off junction transition version number | D98: Transition version number for the off-junction event. | E98: Indicates the version or update sequence for the off-junction transition; supports auditing. | F98: 10 | G98: String | H98: SADB/TYES/AEI | I98: General text, max length 100
A99: Location | B99: RCVD_FROM_SCAC_CD | C99: Received from SCAC code | D99: SCAC code of the rail carrier that that CPRS recieved the rail equipment from | E99: RCVD_FROM_SCAC_CD 'UP' for Union Pacfic | F99: KCSM | G99: String | H99: SADB/TYES/AEI | I99: Length <= 10, uppercase letters
A100: Location | B100: DLVR_TO_SCAC_CD | C100: Deliver to SCAC code | D100: SCAC code of the carrier responsible for final delivery of the equipment. | E100: DLVR_TO_SCAC_CD 'UP' for Union Pacific. | F100: CPRS | G100: String | H100: SADB/TYES/AEI | I100: Length <= 10, uppercase letters
A101: Location | B101: ORNTN_CD | C101: Orientation code | D101: Orientation code for equipment or movement. | E101: Indicates the orientation or facing direction; used for operational and safety purposes. | G101: String | H101: SADB/TYES/AEI | I101: General text, max length 100
A102: Location | B102: Depart Station | C102: Departure station name | D102: Name of the station where the Depature event occured | E102: Laredo Bridge if the SCAC is 'CPRS, FSAC is '05770' and AAR_STNDRD_EVENT_CD = 'DFLC' | F102: LAREDO BRIDGE | G102: String | H102: SADB/TYES/AEI | I102: General text, max length 100
A103: Location | B103: Arrival Station | C103: Arrival station name | D103: Name of the station where the Arrival event occured | E103: Laredo Yard if the SCAC is 'CPRS, FSAC is '05772' and AAR_STNDRD_EVENT_CD in (ARIL or ARRI) | F103: LAREDO YARD | G103: String | H103: SADB/TYES/AEI | I103: General text, max length 100
A104: Equipment | B104: AAR_CAR_TYPE_CD | C104: AAR car type code | D104: AAR car type code identifying the type and specifications of a railcar (e.g., length, door height). | E104: AAR_CAR_TYPE_CD 'C636' for a covered hopper. | F104: S635 | G104: String | H104: SADB/TYES/AEI | I104: Length <= 10, uppercase letters
A105: Equipment | B105: OTSD_LENGTH_FEET_QTY | C105: Outside length in feet | D105: Maximum coupled length of the consist or equipment, in feet. | E105: OTSD_LENGTH_FEET_QTY 89 for a standard flatcar. | F105: 204 | G105: String | H105: SADB/TYES/AEI | I105: General text, max length 100
A106: Equipment | B106: OTSD_LENGTH_INCHES_QTY | C106: Outside length in inches | D106: Outside length of equipment in inches. | E106: Measured or recorded for each piece of equipment; used for clearance and planning. | F106: 2 | G106: String | H106: SADB/TYES/AEI | I106: General text, max length 100
...

Sheet AWS_TrainEvent
A1: event_id | B1: event | C1: event_timestamp_utc | D1: train_plan_leg_id | E1: source_system | F1: direction | G1: train_name | H1: fsac | I1: latitude | J1: longitude | K1: mile_km_number | L1: subdivision_name | M1: station_name | N1: scac | O1: division | P1: region | Q1: district | R1: state_province | S1: country | T1: subdivision_id | U1: record_update_timestamp_utc | V1: updated_from_loco_id | W1: lead_locomotive | X1: geog | AF1: events.train_mvmnt_event | AG1: event_id | AH1: 1
A2: 1 | B2: Arrival | C2: 45702.661 | D2: 14713929294 | E2: SENTINEL | F2: W | G2: 113-11 | H2: 5313 | I2: 50.05031 | J2: -97.67517 | K2: 26.18 | L2: CARBERRY | M2: MARQUETTE | N2: CPRS | O2: CANADA CENTRAL | P2: WEST | Q2: WINNIPEG | R2: MB | S2: CA | T2: 6318 | U2: 45702.666 | V2: CP8785 | W2: CP8785 | X2: 0101000020E6100000614F3BFC356B58C0B554DE8E70064940 | AF2: events.train_mvmnt_event | AG2: event | AH2: Arrival
A3: 2 | B3: Arrival | C3: 45702.663 | D3: 14758548479 | E3: SENTINEL | F3: E | G3: 730-003 | H3: 4824 | I3: 43.896156 | J3: -91.34317 | K3: 289.03 | L3: RIVER | M3: RIVER JCT WEST | N3: CPRS | O3: US EAST | P3: EAST | Q3: WISCONSIN | R3: MN | S3: US | T3: 25 | U3: 45702.666 | V3: CP9732 | W3: CP9732 | X3: 0101000020E6100000F9BD4D7FF6D556C09D0E643DB5F24540 | AF3: events.train_mvmnt_event | AG3: event_timestamp_utc | AH3: 45702.661
A4: 3 | B4: Departure | C4: 45702.662 | D4: 14713929294 | E4: SENTINEL | F4: W | G4: 113-11 | H4: 5313 | I4: 50.05537 | J4: -97.69462 | K4: 27.14 | L4: CARBERRY | M4: MARQUETTE | N4: CPRS | O4: CANADA CENTRAL | P4: WEST | Q4: WINNIPEG | R4: MB | S4: CA | T4: 6318 | U4: 45702.666 | V4: CP8785 | W4: CP8785 | X4: 0101000020E610000071C971A7746C58C0FB96395D16074940 | AF4: events.train_mvmnt_event | AG4: train_plan_leg_id | AH4: 14713929294
A5: 4 | B5: Arrival | C5: 45702.66 | D5: 14758548479 | E5: SENTINEL | F5: E | G5: 730-003 | H5: 4820 | I5: 43.93419 | J5: -91.37092 | K5: 292.05 | L5: RIVER | M5: DONE HOWER | N5: CPRS | O5: US EAST | P5: EAST | Q5: WISCONSIN | R5: MN | S5: US | T5: 25 | U5: 45702.666 | V5: CP9732 | W5: CP9732 | X5: 0101000020E6100000AB5B3D27BDD756C00820B58993F74540 | AF5: events.train_mvmnt_event | AG5: source_system | AH5: SENTINEL
A6: 5 | B6: Departure | C6: 45702.662 | D6: 14718021618 | E6: SENTINEL | F6: N | G6: 149-12 | H6: 6092 | I6: 49.810787 | J6: -104.16321 | K6: 67.11 | L6: WEYBURN | M6: YELLOW GRASS | N6: CPRS | O6: PRAIRIE SOUTH | P6: WEST | Q6: SASKATCHEWAN SOUTH | R6: SK | S6: CA | T6: 6375 | U6: 45702.666 | V6: KCSM4724 | W6: KCSM4724 | X6: 0101000020E610000055185B08720A5AC0CF8250DEC7E74840 | AF6: events.train_mvmnt_event | AG6: direction | AH6: W
A7: 6 | B7: Departure | C7: 45702.647 | D7: 14758548479 | E7: SENTINEL | F7: E | G7: 730-003 | H7: 4821 | I7: 44.02316 | J7: -91.559746 | K7: 303.9 | L7: RIVER | M7: HOMER | N7: CPRS | O7: US EAST | P7: EAST | Q7: WISCONSIN | R7: MN | S7: US | T7: 25 | U7: 45702.666 | V7: CP9732 | W7: NULL | X7: 0101000020E61000004704E3E0D2E356C0A54929E8F6024640 | AF7: events.train_mvmnt_event | AG7: train_name | AH7: 113-11
A8: 7 | B8: Arrival | C8: 45702.661 | D8: 14718021618 | E8: SENTINEL | F8: N | G8: 149-12 | H8: 6092 | I8: 49.80844 | J8: -104.15865 | K8: 67.4 | L8: WEYBURN | M8: YELLOW GRASS | N8: CPRS | O8: PRAIRIE SOUTH | P8: WEST | Q8: SASKATCHEWAN SOUTH | R8: SK | S8: CA | T8: 6375 | U8: 45702.666 | V8: KCSM4724 | W8: KCSM4724 | X8: 0101000020E61000000A698D41270A5AC09D6340F67AE74840 | AF8: events.train_mvmnt_event | AG8: fsac | AH8: 5313
A9: 8 | B9: Departure | C9: 45702.663 | D9: 14764894316 | E9: SENTINEL | F9: E | G9: 391-838 | H9: 5777 | I9: 27.30464 | J9: -98.64141 | K9: 64.16 | L9: LAREDO | M9: HEBBRONVILLE | N9: CPRS | O9: SOUTH WEST | P9: MEXICO | Q9: SOUTHWEST | R9: TX | S9: US | T9: 6727 | U9: 45702.666 | V9: CP8822 | W9: CP8822 | X9: 0101000020E6100000F35487DC0CA958C0AE0D15E3FC4D3B40 | AF9: events.train_mvmnt_event | AG9: latitude | AH9: 50.05031
A10: 9 | B10: Departure | C10: 45702.66 | D10: 14758548479 | E10: SENTINEL | F10: E | G10: 730-003 | H10: 4820 | I10: 43.93419 | J10: -91.37092 | K10: 292.05 | L10: RIVER | M10: DONE HOWER | N10: CPRS | O10: US EAST | P10: EAST | Q10: WISCONSIN | R10: MN | S10: US | T10: 25 | U10: 45702.666 | V10: CP9732 | W10: CP9732 | X10: 0101000020E6100000AB5B3D27BDD756C00820B58993F74540 | AF10: events.train_mvmnt_event | AG10: longitude | AH10: -97.67517
A11: 10 | B11: Arrival | C11: 45702.662 | D11: 14709821184 | E11: SENTINEL | F11: E | G11: 118-10 | H11: 4396 | I11: 48.761147 | J11: -86.55038 | K11: 75.62 | L11: HERON BAY | M11: COLDWELL | N11: CPRS | O11: CANADA CENTRAL | P11: WEST | Q11: THUNDER BAY | R11: ON | S11: CA | T11: 6415 | U11: 45702.666 | V11: CP8830 | W11: CP8830 | X11: 0101000020E6100000D717096D39A355C06939D0436D614840 | AF11: events.train_mvmnt_event | AG11: mile_km_number | AH11: 26.18
A12: 11 | B12: Arrival | C12: 45702.66 | D12: 14752611853 | E12: SENTINEL | F12: N | G12: 581-012 | H12: 5538 | I12: 28.969683 | J12: -96.66074 | K12: 959.53 | L12: ROSENBERG | M12: EDNA | N12: CPRS | O12: SOUTH WEST | P12: MEXICO | Q12: SOUTHWEST | R12: TX | S12: US | T12: 6726 | U12: 45702.666 | V12: CP8786 | W12: CP8786 | X12: 0101000020E61000002ECA6C90492A58C0B77C24253DF83C40 | AF12: events.train_mvmnt_event | AG12: subdivision_name | AH12: CARBERRY
A13: 12 | B13: Departure | C13: 45702.662 | D13: 14718009362 | E13: SENTINEL | F13: N | G13: 113-12 | H13: 4405 | I13: 48.788002 | J13: -87.11636 | K13: 110.83 | L13: HERON BAY | M13: TERRACE BAY | N13: CPRS | O13: CANADA CENTRAL | P13: WEST | Q13: THUNDER BAY | R13: ON | S13: CA | T13: 6415 | U13: 45702.666 | V13: CP8709 | W13: CP8709 | X13: 0101000020E610000001A4367172C755C05F97E13FDD644840 | AF13: events.train_mvmnt_event | AG13: station_name | AH13: MARQUETTE
A14: 13 | B14: Departure | C14: 45702.662 | D14: 14752611853 | E14: SENTINEL | F14: N | G14: 581-012 | H14: 5538 | I14: 28.983458 | J14: -96.63404 | K14: 957.66 | L14: ROSENBERG | M14: EDNA | N14: CPRS | O14: SOUTH WEST | P14: MEXICO | Q14: SOUTHWEST | R14: TX | S14: US | T14: 6726 | U14: 45702.666 | V14: CP8786 | W14: CP8786 | X14: 0101000020E6100000C616821C942858C054FD4AE7C3FB3C40 | AF14: events.train_mvmnt_event | AG14: scac | AH14: CPRS
A15: 14 | B15: Departure | C15: 45702.662 | D15: 14736977502 | E15: SENTINEL | F15: W | G15: 645-669 | H15: 4958 | I15: 46.834667 | J15: -97.87316 | K15: 276.85 | L15: CARRINGTON | M15: CUBA | N15: CPRS | O15: US WEST | P15: EAST | Q15: NORTH DAKOTA | R15: ND | S15: US | T15: 2 | U15: 45702.666 | V15: CP8756 | W15: CP8756 | X15: 0101000020E6100000390B7BDAE17758C07506465ED66A4740 | AF15: events.train_mvmnt_event | AG15: division | AH15: CANADA CENTRAL
A16: 15 | B16: Arrival | C16: 45702.662 | D16: 14722133327 | E16: WITRONIX | F16: N | G16: 293-13 | H16: 1127 | I16: 24.516162 | J16: -100.87032 | K16: 492.22 | L16: VANEGAS | M16: SAN SALVADOR | N16: CPRS | O16: MEXICO SOUTH | P16: MEXICO | Q16: VANEGAS | R16: ZA | S16: MX | T16: 6802 | U16: 45702.666 | V16: KCS4696 | W16: KCS4696 | X16: 0101000020E61000007214C550B33759C0DCAEE13323843840 | AF16: events.train_mvmnt_event | AG16: region | AH16: WEST
A17: 16 | B17: Departure | C17: 45702.66 | D17: 14764723440 | E17: WITRONIX | F17: S | G17: LEN-139 | H17: 2619 | I17: 22.048855 | J17: -99.683735 | K17: 252 | L17: TAMASOPO | M17: LA CINTA | N17: CPRS | O17: MEXICO SOUTH | P17: MEXICO | Q17: TAMASOPO | R17: SL | S17: MX | T17: 6815 | U17: 45702.666 | V17: KCSM4896 | W17: KCSM4897 | X17: 0101000020E6100000521F504FC2EB58C0DB7092C5810C3640 | AF17: events.train_mvmnt_event | AG17: district | AH17: WINNIPEG
A18: 17 | B18: Arrival | C18: 45702.656 | D18: 14764723440 | E18: WITRONIX | F18: S | G18: LEN-139 | H18: 2619 | I18: 22.105571 | J18: -99.714903 | K18: 247.61 | L18: TAMASOPO | M18: LA CINTA | N18: CPRS | O18: MEXICO SOUTH | P18: MEXICO | Q18: TAMASOPO | R18: SL | S18: MX | T18: 6815 | U18: 45702.666 | V18: KCSM4897 | W18: KCSM4897 | X18: 0101000020E6100000E8297AF9C0ED58C0A3F0B0BB061B3640 | AF18: events.train_mvmnt_event | AG18: state_province | AH18: MB
A19: 18 | B19: Departure | C19: 45702.653 | D19: 14764723440 | E19: WITRONIX | F19: S | G19: LEN-139 | H19: 2617 | I19: 22.149366 | J19: -99.740071 | K19: 244.18 | L19: TAMASOPO | M19: LAS TABLAS | N19: CPRS | O19: MEXICO SOUTH | P19: MEXICO | Q19: TAMASOPO | R19: SL | S19: MX | T19: 6815 | U19: 45702.666 | V19: KCSM4896 | W19: KCSM4897 | X19: 0101000020E6100000A1DA01535DEF58C03A792EDF3C263640 | AF19: events.train_mvmnt_event | AG19: country | AH19: CA
A20: 19 | B20: Arrival | C20: 45702.635 | D20: 14764723440 | E20: WITRONIX | F20: S | G20: LEN-139 | H20: 2617 | I20: 22.257204 | J20: -99.861795 | K20: 233.43 | L20: TAMASOPO | M20: LAS TABLAS | N20: CPRS | O20: MEXICO SOUTH | P20: MEXICO | Q20: TAMASOPO | R20: SL | S20: MX | T20: 6815 | U20: 45702.666 | V20: KCSM4896 | W20: KCSM4897 | X20: 0101000020E61000003C1AC1A527F758C08641361CD8413640 | AF20: events.train_mvmnt_event | AG20: subdivision_id | AH20: 6318
A21: 20 | B21: Arrival | C21: 45702.625 | D21: 14722133327 | E21: WITRONIX | F21: N | G21: 293-13 | H21: 1125 | I21: 24.302984 | J21: -100.85945 | K21: 477.3 | L21: VANEGAS | M21: EL SALADO | N21: CPRS | O21: MEXICO SOUTH | P21: MEXICO | Q21: VANEGAS | R21: SL | S21: MX | T21: 6802 | U21: 45702.666 | V21: KCS4696 | W21: KCS4696 | X21: 0101000020E61000000BD24A29013759C0AACB1064904D3840 | AF21: events.train_mvmnt_event | AG21: record_update_timestamp_utc | AH21: 45702.666
A22: 21 | B22: Departure | C22: 45702.632 | D22: 14764723440 | E22: WITRONIX | F22: S | G22: LEN-139 | H22: 2616 | I22: 22.277285 | J22: -99.899911 | K22: 230.44 | L22: TAMASOPO | M22: VIEJO | N22: CPRS | O22: MEXICO SOUTH | P22: MEXICO | Q22: TAMASOPO | R22: SL | S22: MX | T22: 6815 | U22: 45702.666 | V22: KCSM4896 | W22: KCSM4897 | X22: 0101000020E61000000B13FC2598F958C0B502E02BFC463640 | AF22: events.train_mvmnt_event | AG22: updated_from_loco_id | AH22: CP8785
A23: 22 | B23: Departure | C23: 45702.663 | D23: 14757298912 | E23: WITRONIX | F23: E | G23: 3410-13 | H23: 5639 | I23: 50.374106 | J23: -102.51058 | K23: 127.88 | L23: BROADVIEW | M23: BROADVIEW EAST | N23: CPRS | O23: CANADA CENTRAL | P23: WEST | Q23: BRANDON/MINNEDOSA | R23: SK | S23: CA | T23: 6319 | U23: 45702.666 | V23: KCS4590 | W23: KCSM4881 | X23: 0101000020E6100000AAD08248ADA059C08CB2A7B2E22F4940 | AF23: events.train_mvmnt_event | AG23: lead_locomotive | AH23: CP8785
A24: 23 | B24: Arrival | C24: 45702.659 | D24: 14748923106 | E24: WITRONIX | F24: E | G24: 318-533 | H24: 9016 | I24: 49.39196 | J24: -115.01544 | K24: 44.52 | L24: CRANBROOK | M24: MORRISSEY | N24: CPRS | O24: PACIFIC | P24: WEST | Q24: KOOTENAY | R24: BC | S24: CA | T24: 6111 | U24: 45702.666 | V24: KCS4849 | W24: KCS4849 | X24: 0101000020E61000009FB468E8FCC05CC055A09ABB2BB24840 | AF24: events.train_mvmnt_event | AG24: geog | AH24: 0101000020E6100000614F3BFC356B58C0B554DE8E70064940
A25: 24 | B25: Arrival | C25: 45702.66 | D25: 14722144847 | E25: WITRONIX | F25: W | G25: 421-13 | H25: 4303 | I25: 46.806424 | J25: -81.689043 | K25: 11.36 | L25: NEMEGOS | M25: STRALAK | N25: CPRS | O25: CANADA CENTRAL | P25: WEST | Q25: THUNDER BAY | R25: ON | S25: CA | T25: 6412 | U25: 45702.666 | V25: KCSM4665 | W25: CP7012 | X25: 0101000020E61000000B838D46196C54C0909955E938674740 | AF25: events.locomotive_mvmnt_event | AG25: event_id | AH25: 1
A26: 25 | B26: Departure | C26: 45702.66 | D26: 14722137766 | E26: WITRONIX | F26: W | G26: 401-13 | H26: 9520 | I26: 51.351485 | J26: -117.44434 | K26: 78.45 | L26: MOUNTAIN | M26: STONEY CREEK | N26: CPRS | O26: PACIFIC | P26: WEST | Q26: MOUNTAIN | R26: BC | S26: CA | T26: 6103 | U26: 45702.666 | V26: KCS5022 | W26: CP8904 | X26: 0101000020E6100000BEF05203705C5DC05B9D3977FDAC4940 | AF26: events.locomotive_mvmnt_event | AG26: event | AH26: Departure
A27: 26 | B27: Departure | C27: 45702.649 | D27: 14722133327 | E27: WITRONIX | F27: N | G27: 293-13 | H27: 1125 | I27: 24.328428 | J27: -100.85403 | K27: 479.09 | L27: VANEGAS | M27: EL SALADO | N27: CPRS | O27: MEXICO SOUTH | P27: MEXICO | Q27: VANEGAS | R27: SL | S27: MX | T27: 6802 | U27: 45702.666 | V27: KCS4696 | W27: KCS4696 | X27: 0101000020E6100000E534975DA83659C008E774D513543840 | AF27: events.locomotive_mvmnt_event | AG27: event_timestamp_utc | AH27: 45702.661
A28: 27 | B28: Departure | C28: 45702.444 | D28: 14722133327 | E28: WITRONIX | F28: N | G28: 293-13 | H28: 1122 | I28: 24.041877 | J28: -100.91514 | K28: 459.02 | L28: VANEGAS | M28: LA TRUEBA | N28: CPRS | O28: MEXICO SOUTH | P28: MEXICO | Q28: VANEGAS | R28: SL | S28: MX | T28: 6802 | U28: 45702.666 | V28: KCS4696 | W28: KCS4696 | X28: 0101000020E6100000E846FD9A913A59C0485C7470B80A3840 | AF28: events.locomotive_mvmnt_event | AG28: source_system | AH28: SENTINEL
A29: 28 | B29: Departure | C29: 45702.618 | D29: 14722133327 | E29: WITRONIX | F29: N | G29: 293-13 | H29: 1124 | I29: 24.223732 | J29: -100.87644 | K29: 471.73 | L29: VANEGAS | M29: SAN VICENTE | N29: CPRS | O29: MEXICO SOUTH | P29: MEXICO | Q29: VANEGAS | R29: SL | S29: MX | T29: 6802 | U29: 45702.666 | V29: KCS4696 | W29: KCS4696 | X29: 0101000020E61000008F9CD885173859C02F824A8546393840 | AF29: events.locomotive_mvmnt_event | AG29: direction | AH29: S
A30: 29 | B30: Arrival | C30: 45702.615 | D30: 14722133327 | E30: WITRONIX | F30: N | G30: 293-13 | H30: 1124 | I30: 24.166739 | J30: -100.88858 | K30: 467.67 | L30: VANEGAS | M30: SAN VICENTE | N30: CPRS | O30: MEXICO SOUTH | P30: MEXICO | Q30: VANEGAS | R30: SL | S30: MX | T30: 6802 | U30: 45702.666 | V30: KCS4696 | W30: KCS4696 | X30: 0101000020E6100000EAE1708BDE3859C0A6DF3265AF2A3840 | AF30: events.locomotive_mvmnt_event | AG30: mark_cd | AH30: CP
A31: 30 | B31: Arrival | C31: 45702.437 | D31: 14722133327 | E31: WITRONIX | F31: N | G31: 293-13 | H31: 1122 | I31: 24.014569 | J31: -100.92103 | K31: 457.07 | L31: VANEGAS | M31: LA TRUEBA | N31: CPRS | O31: MEXICO SOUTH | P31: MEXICO | Q31: VANEGAS | R31: SL | S31: MX | T31: 6802 | U31: 45702.666 | V31: KCS4696 | W31: KCS4696 | X31: 0101000020E61000004CB1DD1CF23A59C0D0C7C6CDBA033840 | AF31: events.locomotive_mvmnt_event | AG31: eqpun_nbr | AH31: 8078
A32: 31 | B32: Departure | C32: 45702.42 | D32: 14722133327 | E32: WITRONIX | F32: N | G32: 293-13 | H32: 1121 | I32: 23.904402 | J32: -100.9446 | K32: 449.39 | L32: VANEGAS | M32: VANEGAS | N32: CPRS | O32: MEXICO SOUTH | P32: MEXICO | Q32: VANEGAS | R32: SL | S32: MX | T32: 6802 | U32: 45702.666 | V32: KCS4696 | W32: KCS4696 | X32: 0101000020E61000006E484849743C59C0A3895EE386E73740 | AF32: events.locomotive_mvmnt_event | AG32: fsac | AH32: 5112
A33: 32 | B33: Departure | C33: 45702.656 | D33: 14722086417 | E33: WITRONIX | F33: E | G33: 112-13 | H33: 9522 | I33: 51.300397 | J33: -117.46099 | K33: NULL | L33: NULL | M33: GLACIER | N33: CPRS | O33: NULL | P33: NULL | Q33: NULL | R33: NULL | S33: NULL | T33: NULL | U33: 45702.666 | V33: KCS5015 | W33: CP8740 | X33: 0101000020E6100000BE3BE8C8805D5DC0423C966773A64940 | AF33: events.locomotive_mvmnt_event | AG33: latitude | AH33: 35.56737
A34: 33 | B34: Arrival | C34: 45702.66 | D34: 14709811861 | E34: WITRONIX | F34: E | G34: 100-10 | H34: 4435 | I34: 48.909527 | J34: -87.752363 | K34: 32.26 | L34: NIPIGON | M34: GRAVEL | N34: CPRS | O34: CANADA CENTRAL | P34: WEST | Q34: THUNDER BAY | R34: ON | S34: CA | T34: 6410 | U34: 45702.666 | V34: KCS4686 | W34: KCS4686 | X34: 0101000020E6100000CBFDC4B726F055C0CF9C79626B744840 | AF34: events.locomotive_mvmnt_event | AG34: longitude | AH34: -94.83112
A35: 34 | B35: Departure | C35: 45702.663 | D35: 14634724304 | E35: WITRONIX | F35: N | G35: 865-903 | H35: 4735 | I35: 38.369595 | J35: -94.584262 | K35: 61.04 | L35: PITTSBURG | M35: AMSTERDAM | N35: CPRS | O35: MIDWEST | P35: SOUTH | Q35: PITTSBURG | R35: MO | S35: US | T35: 6706 | U35: 45702.666 | V35: KCSM4738 | W35: KCSM4738 | X35: 0101000020E6100000FF9C7A8B64A557C0196140E54E2F4340 | AF35: events.locomotive_mvmnt_event | AG35: mile_km_number | AH35: 282.08
A36: 35 | B36: Departure | C36: 45702.661 | D36: 14749261111 | E36: SENTINEL | F36: N | G36: 602-032 | H36: 9647 | I36: 50.234543 | J36: -121.5778 | K36: 94.88 | L36: THOMPSON | M36: LYTTON | N36: CPRS | O36: PACIFIC | P36: WEST | Q36: MOUNTAIN | R36: BC | S36: CA | T36: 6006 | U36: 45702.666 | V36: CP9805 | W36: CP9805 | X36: 0101000020E6100000C79DD2C1FA645EC0BC404981051E4940 | AF36: events.locomotive_mvmnt_event | AG36: subdivision_name | AH36: HEAVENER
A37: 36 | B37: Arrival | C37: 45702.662 | D37: 14744980370 | E37: SENTINEL | F37: E | G37: 804-512 | H37: 9027 | I37: 49.30072 | J37: -115.15957 | K37: 57.58 | L37: CRANBROOK | M37: WALDO | N37: CPRS | O37: PACIFIC | P37: WEST | Q37: KOOTENAY | R37: BC | S37: CA | T37: 6111 | U37: 45702.666 | V37: CP8803 | W37: CP8803 | X37: 0101000020E61000000EDB166536CA5CC066A032FE7DA64840 | AF37: events.locomotive_mvmnt_event | AG37: station_name | AH37: MARBLE CITY
A38: 37 | B38: Departure | C38: 45702.663 | D38: 14744980370 | E38: SENTINEL | F38: E | G38: 804-512 | H38: 9027 | I38: 49.297718 | J38: -115.15407 | K38: 57.18 | L38: CRANBROOK | M38: WALDO | N38: CPRS | O38: PACIFIC | P38: WEST | Q38: KOOTENAY | R38: BC | S38: CA | T38: 6111 | U38: 45702.666 | V38: CP8803 | W38: CP8803 | X38: 0101000020E6100000DDD26A48DCC95CC01CB7989F1BA64840 | AF38: events.locomotive_mvmnt_event | AG38: train_plan_leg_id | AH38: 14726049483
A39: 38 | B39: Arrival | C39: 45702.663 | D39: 14757118145 | E39: SENTINEL | F39: N | G39: 802-101 | H39: 9643 | I39: 50.33578 | J39: -121.39753 | K39: 79.51 | L39: THOMPSON | M39: DRYNOCH | N39: CPRS | O39: PACIFIC | P39: WEST | Q39: MOUNTAIN | R39: BC | S39: CA | T39: 6006 | U39: 45702.666 | V39: CP9371 | W39: CP9371 | X39: 0101000020E6100000734BAB2171595EC05053CBD6FA2A4940 | AF39: events.locomotive_mvmnt_event | AG39: train_name | AH39: 262-14
A40: 39 | B40: Arrival | C40: 45702.662 | D40: 14705729410 | E40: SENTINEL | F40: S | G40: 118-09 | H40: 3428 | I40: 44.225037 | J40: -79.838425 | K40: 50.46 | L40: MACTIER | M40: BAXTER | N40: CPRS | O40: CANADA ONTARIO | P40: EAST | Q40: TORONTO/NORTH | R40: ON | S40: CA | T40: 6501 | U40: 45702.666 | V40: CP8865 | W40: CP8865 | X40: 0101000020E610000086C954C1A8F553C0EAB12D03CE1C4640 | AF40: events.locomotive_mvmnt_event | AG40: scac | AH40: CPRS
A41: 40 | B41: Departure | C41: 45702.662 | D41: 14705729410 | E41: SENTINEL | F41: S | G41: 118-09 | H41: 3428 | I41: 44.225037 | J41: -79.838425 | K41: 50.46 | L41: MACTIER | M41: BAXTER | N41: CPRS | O41: CANADA ONTARIO | P41: EAST | Q41: TORONTO/NORTH | R41: ON | S41: CA | T41: 6501 | U41: 45702.666 | V41: CP8865 | W41: CP8865 | X41: 0101000020E610000086C954C1A8F553C0EAB12D03CE1C4640 | AF41: events.locomotive_mvmnt_event | AG41: division | AH41: MIDWEST
A42: 41 | B42: Arrival | C42: 45702.663 | D42: 14709813354 | E42: SENTINEL | F42: W | G42: 101-10 | H42: 8240 | I42: 51.32535 | J42: -116.03724 | K42: 106.31 | L42: LAGGAN | M42: ELDON | N42: CPRS | O42: PRAIRIE NORTH | P42: WEST | Q42: CALGARY | R42: AB | S42: CA | T42: 6201 | U42: 45702.666 | V42: CP8704 | W42: CP8704 | X42: 0101000020E61000009886E12362025DC076E09C11A5A94940 | AF42: events.locomotive_mvmnt_event | AG42: region | AH42: SOUTH
A43: 42 | B43: Departure | C43: 45702.659 | D43: 14705729410 | E43: SENTINEL | F43: S | G43: 118-09 | H43: 3412 | I43: 44.271885 | J43: -79.84303 | K43: 53.72 | L43: MACTIER | M43: YPRES | N43: CPRS | O43: CANADA ONTARIO | P43: EAST | Q43: TORONTO/NORTH | R43: ON | S43: CA | T43: 6501 | U43: 45702.666 | V43: CP8865 | W43: NULL | X43: 0101000020E610000000E31934F4F553C0F0A2AF20CD224640 | AF43: events.locomotive_mvmnt_event | AG43: district | AH43: PITTSBURG
A44: 43 | B44: Arrival | C44: 45702.663 | D44: 14749209494 | E44: SENTINEL | F44: E | G44: 3240-12 | H44: 4897 | I44: 46.324486 | J44: -95.4449 | K44: 170.42 | L44: DETROIT LAKES | M44: HENNING | N44: CPRS | O44: US WEST | P44: EAST | Q44: MINNESOTA | R44: MN | S44: US | T44: 5 | U44: 45702.666 | V44: CP8016 | W44: CP8016 | X44: 0101000020E6100000637FD93D79DC57C04301DBC188294740 | AF44: events.locomotive_mvmnt_event | AG44: state_province | AH44: OK
A45: 44 | B45: Departure | C45: 45702.66 | D45: 14722097045 | E45: SENTINEL | F45: E | G45: 134-13 | H45: 3498 | I45: 43.58908 | J45: -79.78996 | K45: 25.34 | L45: GALT | M45: HORNBY EAST | N45: CPRS | O45: CANADA ONTARIO | P45: EAST | Q45: TORONTO/NORTH | R45: ON | S45: CA | T45: 6534 | U45: 45702.666 | V45: CP9355 | W45: CP9355 | X45: 0101000020E61000007B4963B48EF253C0255D33F966CB4540 | AF45: events.locomotive_mvmnt_event | AG45: country | AH45: US
A46: 45 | B46: Arrival | C46: 45702.66 | D46: 14722097045 | E46: SENTINEL | F46: E | G46: 134-13 | H46: 3498 | I46: 43.58908 | J46: -79.78996 | K46: 25.34 | L46: GALT | M46: HORNBY EAST | N46: CPRS | O46: CANADA ONTARIO | P46: EAST | Q46: TORONTO/NORTH | R46: ON | S46: CA | T46: 6534 | U46: 45702.666 | V46: CP9355 | W46: CP9355 | X46: 0101000020E61000007B4963B48EF253C0255D33F966CB4540 | AF46: events.locomotive_mvmnt_event | AG46: subdivision_id | AH46: 6707
A47: 46 | B47: Arrival | C47: 45702.662 | D47: 14722097045 | E47: SENTINEL | F47: E | G47: 134-13 | H47: 3500 | I47: 43.598953 | J47: -79.769905 | K47: 24.07 | L47: GALT | M47: MEADOWVALE | N47: CPRS | O47: CANADA ONTARIO | P47: EAST | Q47: TORONTO/NORTH | R47: ON | S47: CA | T47: 6534 | U47: 45702.666 | V47: CP9355 | W47: CP9355 | X47: 0101000020E6100000B8019F1F46F153C0A96BED7DAACC4540 | AF47: events.locomotive_mvmnt_event | AG47: record_update_timestamp_utc | AH47: 45702.667
A48: 47 | B48: Departure | C48: 45702.663 | D48: 14718003665 | E48: SENTINEL | F48: W | G48: 105-12 | H48: 5005 | I48: 48.363083 | J48: -89.29385 | K48: 2.61 | L48: KAMINISTIQUIA | M48: WESTFORT | N48: CPRS | O48: CANADA CENTRAL | P48: WEST | Q48: THUNDER BAY | R48: ON | S48: CA | T48: 6314 | U48: 45702.666 | V48: CP8705 | W48: CP8705 | X48: 0101000020E61000007FFB3A70CE5256C0E65DF580792E4840 | AF48: events.locomotive_mvmnt_event | AG48: geog | AH48: 0101000020E61000004CC3F01131B557C0A25D85949FC84140
A49: 48 | B49: Departure | C49: 45702.658 | D49: 14722095830 | E49: SENTINEL | F49: N | G49: 132-13 | H49: 3254 | I49: 43.45762 | J49: -79.996506 | K49: 75.17 | L49: HAMILTON | M49: CAMPBELLVILLE | N49: CPRS | O49: CANADA ONTARIO | P49: EAST | Q49: SOUTH ONTARIO | R49: ON | S49: CA | T49: 6534 | U49: 45702.666 | V49: CP8810 | W49: NULL | X49: 0101000020E610000023111AC1C6FF53C06DFFCA4A93BA4540
A50: 49 | B50: Departure | C50: 45702.658 | D50: 14722097045 | E50: SENTINEL | F50: E | G50: 134-13 | H50: 3218 | I50: 43.553993 | J50: -79.82874 | K50: 28.39 | L50: GALT | M50: HORNBY | N50: CPRS | O50: CANADA ONTARIO | P50: EAST | Q50: SOUTH ONTARIO | R50: ON | S50: CA | T50: 6534 | U50: 45702.666 | V50: CP9355 | W50: NULL | X50: 0101000020E6100000C5387F130AF553C0419B1C3EE9C64540
A51: 50 | B51: Arrival | C51: 45702.661 | D51: 14722095830 | E51: SENTINEL | F51: N | G51: 132-13 | H51: 3247 | I51: 43.480785 | J51: -79.98638 | K51: 38.51 | L51: GALT | M51: FLANDERS | N51: CPRS | O51: CANADA ONTARIO | P51: EAST | Q51: SOUTH ONTARIO | R51: ON | S51: CA | T51: 6534 | U51: 45702.666 | V51: CP8810 | W51: CP8810 | X51: 0101000020E61000006C5B94D920FF53C024B4E55C8ABD4540
A52: 51 | B52: Arrival | C52: 45702.662 | D52: 14718003665 | E52: SENTINEL | F52: W | G52: 105-12 | H52: 5005 | I52: 48.36287 | J52: -89.290665 | K52: 2.42 | L52: KAMINISTIQUIA | M52: WESTFORT | N52: CPRS | O52: CANADA CENTRAL | P52: WEST | Q52: THUNDER BAY | R52: ON | S52: CA | T52: 6314 | U52: 45702.666 | V52: CP8705 | W52: CP8705 | X52: 0101000020E6100000E1455F419A5256C08A592F86722E4840
A53: 52 | B53: Departure | C53: 45702.661 | D53: 14722095830 | E53: SENTINEL | F53: N | G53: 132-13 | H53: 3247 | I53: 43.480785 | J53: -79.98638 | K53: 38.51 | L53: GALT | M53: FLANDERS | N53: CPRS | O53: CANADA ONTARIO | P53: EAST | Q53: SOUTH ONTARIO | R53: ON | S53: CA | T53: 6534 | U53: 45702.666 | V53: CP8810 | W53: CP8810 | X53: 0101000020E61000006C5B94D920FF53C024B4E55C8ABD4540
A54: 53 | B54: Departure | C54: 45702.66 | D54: 14705738285 | E54: SENTINEL | F54: W | G54: 149-09 | H54: 9638 | I54: 50.61063 | J54: -121.30993 | K54: 56.79 | L54: THOMPSON | M54: BASQUE | N54: CPRS | O54: PACIFIC | P54: WEST | Q54: MOUNTAIN | R54: BC | S54: CA | T54: 6006 | U54: 45702.666 | V54: CP8892 | W54: CP8892 | X54: 0101000020E61000002783A3E4D5535EC06EFAB31F294E4940
A55: 54 | B55: Departure | C55: 45702.663 | D55: 14751994284 | E55: SENTINEL | F55: S | G55: 866-050 | H55: 5118 | I55: 35.11685 | J55: -94.64973 | K55: 320.93 | L55: HEAVENER | M55: SHADY POINT | N55: CPRS | O55: MIDWEST | P55: SOUTH | Q55: PITTSBURG | R55: OK | S55: US | T55: 6707 | U55: 45702.666 | V55: CP8707 | W55: CP8707 | X55: 0101000020E6100000BA4E232D95A957C0D044D8F0F48E4140
A56: 55 | B56: Arrival | C56: 45702.661 | D56: 14722142336 | E56: SENTINEL | F56: N | G56: 418-13 | H56: 8279 | I56: 52.12261 | J56: -113.88064 | K56: 82.81 | L56: RED DEER | M56: PENHOLD | N56: CPRS | O56: PRAIRIE NORTH | P56: WEST | Q56: ALBERTA NORTH | R56: AB | S56: CA | T56: 6223 | U56: 45702.666 | V56: CP8823 | W56: CP8823 | X56: 0101000020E61000002AE3DF675C785CC0CF143AAFB10F4A40
A57: 56 | B57: Departure | C57: 45702.663 | D57: 14722142336 | E57: SENTINEL | F57: N | G57: 418-13 | H57: 8279 | I57: 52.136368 | J57: -113.87584 | K57: 83.74 | L57: RED DEER | M57: PENHOLD | N57: CPRS | O57: PRAIRIE NORTH | P57: WEST | Q57: ALBERTA NORTH | R57: AB | S57: CA | T57: 6223 | U57: 45702.666 | V57: CP8823 | W57: CP8823 | X57: 0101000020E6100000D52137C30D785CC0471CB28174114A40
A58: 57 | B58: Departure | C58: 45702.66 | D58: 14757086482 | E58: SENTINEL | F58: S | G58: 2413-13 | H58: 8562 | I58: 52.576706 | J58: -113.63861 | K58: 27.28 | L58: LEDUC | M58: MORNINGSIDE | N58: CPRS | O58: PRAIRIE NORTH | P58: WEST | Q58: ALBERTA NORTH | R58: AB | S58: CA | T58: 6224 | U58: 45702.666 | V58: CP8847 | W58: CP8847 | X58: 0101000020E610000082397AFCDE685CC018B49080D1494A40
A59: 58 | B59: Arrival | C59: 45702.66 | D59: 14722112239 | E59: SENTINEL | F59: W | G59: 231-13 | H59: 3248 | I59: 42.999 | J59: -81.204735 | K59: 112.17 | L59: GALT | M59: LONDON QUEBEC ST | N59: CPRS | O59: CANADA ONTARIO | P59: EAST | Q59: SOUTH ONTARIO | R59: ON | S59: CA | T59: 6507 | U59: 45702.666 | V59: CP8874 | W59: CP8874 | X59: 0101000020E61000002E56D4601A4D54C01D5A643BDF7F4540
A60: 59 | B60: Arrival | C60: 45702.662 | D60: 14701082359 | E60: SENTINEL | F60: S | G60: 112-08 | H60: 3047 | I60: 44.82932 | J60: -76.41616 | K60: 21.88 | L60: BELLEVILLE | M60: ELLIOTT | N60: CPRS | O60: CANADA QUEBEC | P60: EAST | Q60: QUEBEC | R60: ON | S60: CA | T60: 6517 | U60: 45702.666 | V60: CP8787 | W60: CP8787 | X60: 0101000020E6100000D1798D5DA21A53C099F56228276A4640
... A101: 100 | B101: Arrival | C101: 45702.658 | D101: 14765148385 | E101: PTC | F101: W | G101: 2274-14 | H101: 5419 | I101: 32.419293 | J101: -91.256086 | K101: 21.11 | L101: VICKSBURG | M101: TALLA BENA | N101: CPRS | O101: SOUTH EAST | P101: SOUTH | Q101: SPEEDWAY | R101: LA | S101: US | T101: 6718 | U101: 45702.664 | V101: KCS5013 | W101: KCS5013 | X101: 0101000020E61000002908BBB463D056C0BA927063AB354040

Sheet AWS_LocoEvent
A1: event_id | B1: event | C1: event_timestamp_utc | D1: source_system | E1: direction | F1: mark_cd | G1: eqpun_nbr | H1: fsac | I1: latitude | J1: longitude | K1: mile_km_number | L1: subdivision_name | M1: station_name | N1: train_plan_leg_id | O1: train_name | P1: scac | Q1: division | R1: region | S1: district | T1: state_province | U1: country | V1: subdivision_id | W1: record_update_timestamp_utc | X1: geog
A2: 1 | B2: Departure | C2: 45702.661 | D2: SENTINEL | E2: S | F2: CP | G2: 8078 | H2: 5112 | I2: 35.56737 | J2: -94.83112 | K2: 282.08 | L2: HEAVENER | M2: MARBLE CITY | N2: 14726049483 | O2: 262-14 | P2: CPRS | Q2: MIDWEST | R2: SOUTH | S2: PITTSBURG | T2: OK | U2: US | V2: 6707 | W2: 45702.667 | X2: 0101000020E61000004CC3F01131B557C0A25D85949FC84140
A3: 2 | B3: Departure | C3: 45702.662 | D3: SENTINEL | E3: N | F3: CP | G3: 7026 | H3: 1127 | I3: 24.531733 | J3: -100.87324 | K3: 493.31 | L3: VANEGAS | M3: SAN SALVADOR | N3: 14722133327 | O3: 293-13 | P3: CPRS | Q3: MEXICO SOUTH | R3: MEXICO | S3: VANEGAS | T3: ZA | U3: MX | V3: 6802 | W3: 45702.666 | X3: 0101000020E61000005019FF3EE33759C0373465A71F883840
A4: 3 | B4: Departure | C4: 45702.628 | D4: SENTINEL | E4: N | F4: CP | G4: 7026 | H4: 1125 | I4: 24.31068 | J4: -100.8578 | K4: 477.84 | L4: VANEGAS | M4: EL SALADO | N4: 14722133327 | O4: 293-13 | P4: CPRS | Q4: MEXICO SOUTH | R4: MEXICO | S4: VANEGAS | T4: SL | U4: MX | V4: 6802 | W4: 45702.666 | X4: 0101000020E610000090A0F831E63659C0738577B9884F3840
A5: 4 | B5: Arrival | C5: 45702.661 | D5: SENTINEL | E5: N | F5: CP | G5: 7026 | H5: 1127 | I5: 24.50547 | J5: -100.86833 | K5: 491.47 | L5: VANEGAS | M5: SAN SALVADOR | N5: 14722133327 | O5: 293-13 | P5: CPRS | Q5: MEXICO SOUTH | R5: MEXICO | S5: VANEGAS | T5: ZA | U5: MX | V5: 6802 | W5: 45702.666 | X5: 0101000020E6100000AF08FEB7923759C0EF1B5F7B66813840
A6: 5 | B6: Arrival | C6: 45702.66 | D6: SENTINEL | E6: E | F6: CP | G6: 9732 | H6: 4820 | I6: 43.93419 | J6: -91.37092 | K6: 292.05 | L6: RIVER | M6: DONE HOWER | N6: 14758548479 | O6: 730-003 | P6: CPRS | Q6: US EAST | R6: EAST | S6: WISCONSIN | T6: MN | U6: US | V6: 25 | W6: 45702.666 | X6: 0101000020E6100000AB5B3D27BDD756C00820B58993F74540
A7: 6 | B7: Departure | C7: 45702.66 | D7: SENTINEL | E7: E | F7: CP | G7: 9732 | H7: 4820 | I7: 43.93419 | J7: -91.37092 | K7: 292.05 | L7: RIVER | M7: DONE HOWER | N7: 14758548479 | O7: 730-003 | P7: CPRS | Q7: US EAST | R7: EAST | S7: WISCONSIN | T7: MN | U7: US | V7: 25 | W7: 45702.666 | X7: 0101000020E6100000AB5B3D27BDD756C00820B58993F74540
A8: 7 | B8: Arrival | C8: 45702.663 | D8: SENTINEL | E8: E | F8: CP | G8: 9732 | H8: 4824 | I8: 43.896156 | J8: -91.34317 | K8: 289.03 | L8: RIVER | M8: RIVER JCT WEST | N8: 14758548479 | O8: 730-003 | P8: CPRS | Q8: US EAST | R8: EAST | S8: WISCONSIN | T8: MN | U8: US | V8: 25 | W8: 45702.666 | X8: 0101000020E6100000F9BD4D7FF6D556C09D0E643DB5F24540
A9: 8 | B9: Departure | C9: 45702.658 | D9: SENTINEL | E9: E | F9: CP | G9: 8934 | H9: 3218 | I9: 43.553577 | J9: -79.82926 | K9: 28.43 | L9: GALT | M9: HORNBY | N9: 14722097045 | O9: 134-13 | P9: CPRS | Q9: CANADA ONTARIO | R9: EAST | S9: SOUTH ONTARIO | T9: ON | U9: CA | V9: 6534 | W9: 45702.666 | X9: 0101000020E610000062F8889812F553C0AD68739CDBC64540
A10: 9 | B10: Arrival | C10: 45702.66 | D10: SENTINEL | E10: E | F10: CP | G10: 8934 | H10: 3498 | I10: 43.58915 | J10: -79.78996 | K10: 25.34 | L10: GALT | M10: HORNBY EAST | N10: 14722097045 | O10: 134-13 | P10: CPRS | Q10: CANADA ONTARIO | R10: EAST | S10: TORONTO/NORTH | T10: ON | U10: CA | V10: 6534 | W10: 45702.666 | X10: 0101000020E61000007B4963B48EF253C01D38674469CB4540
A11: 10 | B11: Departure | C11: 45702.66 | D11: SENTINEL | E11: E | F11: CP | G11: 8934 | H11: 3498 | I11: 43.58915 | J11: -79.78996 | K11: 25.34 | L11: GALT | M11: HORNBY EAST | N11: 14722097045 | O11: 134-13 | P11: CPRS | Q11: CANADA ONTARIO | R11: EAST | S11: TORONTO/NORTH | T11: ON | U11: CA | V11: 6534 | W11: 45702.666 | X11: 0101000020E61000007B4963B48EF253C01D38674469CB4540
A12: 11 | B12: Arrival | C12: 45702.662 | D12: SENTINEL | E12: E | F12: CP | G12: 8934 | H12: 3500 | I12: 43.598984 | J12: -79.769936 | K12: 24.02 | L12: GALT | M12: MEADOWVALE | N12: 14722097045 | O12: 134-13 | P12: CPRS | Q12: CANADA ONTARIO | R12: EAST | S12: TORONTO/NORTH | T12: ON | U12: CA | V12: 6534 | W12: 45702.666 | X12: 0101000020E6100000D600A5A146F153C0E469F981ABCC4540
A13: 12 | B13: Arrival | C13: 45702.661 | D13: SENTINEL | E13: W | F13: CP | G13: 8785 | H13: 5313 | I13: 50.05031 | J13: -97.67517 | K13: 26.18 | L13: CARBERRY | M13: MARQUETTE | N13: 14713929294 | O13: 113-11 | P13: CPRS | Q13: CANADA CENTRAL | R13: WEST | S13: WINNIPEG | T13: MB | U13: CA | V13: 6318 | W13: 45702.666 | X13: 0101000020E6100000614F3BFC356B58C0B554DE8E70064940
A14: 13 | B14: Departure | C14: 45702.662 | D14: SENTINEL | E14: W | F14: CP | G14: 8785 | H14: 5313 | I14: 50.05537 | J14: -97.69462 | K14: 27.14 | L14: CARBERRY | M14: MARQUETTE | N14: 14713929294 | O14: 113-11 | P14: CPRS | Q14: CANADA CENTRAL | R14: WEST | S14: WINNIPEG | T14: MB | U14: CA | V14: 6318 | W14: 45702.666 | X14: 0101000020E610000071C971A7746C58C0FB96395D16074940
A15: 14 | B15: Arrival | C15: 45702.661 | D15: SENTINEL | E15: NULL | F15: CP | G15: 8812 | H15: 9017 | I15: 50.018715 | J15: -114.83303 | K15: 21.42 | L15: FORDING RIVER | M15: GREENHILLS | N15: NULL | O15: NULL | P15: CPRS | Q15: PACIFIC | R15: WEST | S15: KOOTENAY | T15: BC | U15: CA | V15: 6112 | W15: 45702.666 | X15: 0101000020E61000008FA50F5D50B55CC0EA78CC4065024940
A16: 15 | B16: Departure | C16: 45702.661 | D16: SENTINEL | E16: NULL | F16: CP | G16: 8812 | H16: 9017 | I16: 50.018715 | J16: -114.83303 | K16: 21.42 | L16: FORDING RIVER | M16: GREENHILLS | N16: NULL | O16: NULL | P16: CPRS | Q16: PACIFIC | R16: WEST | S16: KOOTENAY | T16: BC | U16: CA | V16: 6112 | W16: 45702.666 | X16: 0101000020E61000008FA50F5D50B55CC0EA78CC4065024940
A17: 16 | B17: Arrival | C17: 45702.661 | D17: SENTINEL | E17: E | F17: CP | G17: 8822 | H17: 5777 | I17: 27.305235 | J17: -98.670815 | K17: 62.34 | L17: LAREDO | M17: HEBBRONVILLE | N17: 14764894316 | O17: 391-838 | P17: CPRS | Q17: SOUTH WEST | R17: MEXICO | S17: SOUTHWEST | T17: TX | U17: US | V17: 6727 | W17: 45702.666 | X17: 0101000020E6100000A4AA09A2EEAA58C0359886E1234E3B40
A18: 17 | B18: Departure | C18: 45702.663 | D18: SENTINEL | E18: E | F18: CP | G18: 8822 | H18: 5777 | I18: 27.30464 | J18: -98.64141 | K18: 64.16 | L18: LAREDO | M18: HEBBRONVILLE | N18: 14764894316 | O18: 391-838 | P18: CPRS | Q18: SOUTH WEST | R18: MEXICO | S18: SOUTHWEST | T18: TX | U18: US | V18: 6727 | W18: 45702.666 | X18: 0101000020E6100000F35487DC0CA958C0AE0D15E3FC4D3B40
A19: 18 | B19: Departure | C19: 45702.647 | D19: SENTINEL | E19: E | F19: CP | G19: 9732 | H19: 4821 | I19: 44.02316 | J19: -91.559746 | K19: 303.9 | L19: RIVER | M19: HOMER | N19: 14758548479 | O19: 730-003 | P19: CPRS | Q19: US EAST | R19: EAST | S19: WISCONSIN | T19: MN | U19: US | V19: 25 | W19: 45702.666 | X19: 0101000020E61000004704E3E0D2E356C0A54929E8F6024640
A20: 19 | B20: Arrival | C20: 45702.66 | D20: SENTINEL | E20: N | F20: KCS | G20: 4575 | H20: 5538 | I20: 28.969788 | J20: -96.66055 | K20: 959.52 | L20: ROSENBERG | M20: EDNA | N20: 14752611853 | O20: 581-012 | P20: CPRS | Q20: SOUTH WEST | R20: MEXICO | S20: SOUTHWEST | T20: TX | U20: US | V20: 6726 | W20: 45702.666 | X20: 0101000020E6100000DCD78173462A58C0A20DC00644F83C40
A21: 20 | B21: Departure | C21: 45702.662 | D21: SENTINEL | E21: N | F21: KCSM | G21: 4724 | H21: 6092 | I21: 49.810787 | J21: -104.16321 | K21: 67.11 | L21: WEYBURN | M21: YELLOW GRASS | N21: 14718021618 | O21: 149-12 | P21: CPRS | Q21: PRAIRIE SOUTH | R21: WEST | S21: SASKATCHEWAN SOUTH | T21: SK | U21: CA | V21: 6375 | W21: 45702.666 | X21: 0101000020E610000055185B08720A5AC0CF8250DEC7E74840
A22: 21 | B22: Arrival | C22: 45702.661 | D22: SENTINEL | E22: N | F22: KCSM | G22: 4724 | H22: 6092 | I22: 49.80844 | J22: -104.15865 | K22: 67.4 | L22: WEYBURN | M22: YELLOW GRASS | N22: 14718021618 | O22: 149-12 | P22: CPRS | Q22: PRAIRIE SOUTH | R22: WEST | S22: SASKATCHEWAN SOUTH | T22: SK | U22: CA | V22: 6375 | W22: 45702.666 | X22: 0101000020E61000000A698D41270A5AC09D6340F67AE74840
A23: 22 | B23: Arrival | C23: 45702.663 | D23: SENTINEL | E23: W | F23: CP | G23: 9824 | H23: 8240 | I23: 51.325478 | J23: -116.03744 | K23: 106.33 | L23: LAGGAN | M23: ELDON | N23: 14709813354 | O23: 101-10 | P23: CPRS | Q23: PRAIRIE NORTH | R23: WEST | S23: CALGARY | T23: AB | U23: CA | V23: 6201 | W23: 45702.666 | X23: 0101000020E6100000FCE3BD6A65025DC0A3C85A43A9A94940
A24: 23 | B24: Departure | C24: 45702.663 | D24: SENTINEL | E24: E | F24: CP | G24: 8912 | H24: 5777 | I24: 27.304638 | J24: -98.641495 | K24: 64.16 | L24: LAREDO | M24: HEBBRONVILLE | N24: 14764894316 | O24: 391-838 | P24: CPRS | Q24: SOUTH WEST | R24: MEXICO | S24: SOUTHWEST | T24: TX | U24: US | V24: 6727 | W24: 45702.666 | X24: 0101000020E61000000B630B410EA958C06D1E87C1FC4D3B40
A25: 24 | B25: Arrival | C25: 45702.661 | D25: SENTINEL | E25: E | F25: CP | G25: 8912 | H25: 5777 | I25: 27.305243 | J25: -98.671486 | K25: 62.3 | L25: LAREDO | M25: HEBBRONVILLE | N25: 14764894316 | O25: 391-838 | P25: CPRS | Q25: SOUTH WEST | R25: MEXICO | S25: SOUTHWEST | T25: TX | U25: US | V25: 6727 | W25: 45702.666 | X25: 0101000020E6100000336E6AA0F9AA58C03B55BE67244E3B40
A26: 25 | B26: Departure | C26: 45702.662 | D26: SENTINEL | E26: E | F26: CP | G26: 8146 | H26: 7445 | I26: 50.885555 | J26: -113.35429 | K26: 138.24 | L26: BROOKS | M26: STRANGMUIR | N26: 14722083441 | O26: 104-13 | P26: CPRS | Q26: PRAIRIE SOUTH | R26: WEST | S26: ALBERTA SOUTH | T26: AB | U26: CA | V26: 6202 | W26: 45702.666 | X26: 0101000020E610000031D3F6AFAC565CC096E7C1DD59714940
A27: 26 | B27: Arrival | C27: 45702.662 | D27: SENTINEL | E27: S | F27: KCS | G27: 4688 | H27: 3005 | I27: 22.285603 | J27: -101.98162 | K27: 37.58 | L27: SALINAS | M27: LORETO | N27: 14728269384 | O27: 386-471 | P27: CPRS | Q27: MEXICO SOUTH | R27: MEXICO | S27: SAN LUIS POTOSI | T27: ZA | U27: MX | V27: 6813 | W27: 45702.666 | X27: 0101000020E61000005F46B1DCD27E59C0B5A338471D493640
A28: 27 | B28: Departure | C28: 45702.661 | D28: SENTINEL | E28: W | F28: CP | G28: 8899 | H28: 9543 | I28: 50.33467 | J28: -115.88236 | K28: 53.8 | L28: WINDERMERE | M28: FAIRMONT | N28: 14757967550 | O28: 801-119 | P28: CPRS | Q28: PACIFIC | R28: WEST | S28: KOOTENAY | T28: BC | U28: CA | V28: 6104 | W28: 45702.666 | X28: 0101000020E6100000931D1B8178F85CC0E6797077D62A4940
... A33: 32 | B33: Arrival | C33: 45702.662 | D33: SENTINEL | E33: E | F33: CP | G33: 8830 | H33: 4396 | I33: 48.761147 | J33: -86.55038 | K33: 75.62 | L33: HERON BAY | M33: COLDWELL | N33: 14709821184 | O33: 118-10 | P33: CPRS | Q33: CANADA CENTRAL | R33: WEST | S33: THUNDER BAY | T33: ON | U33: CA | V33: 6415 | W33: 45702.666 | X33: 0101000020E6100000D717096D39A355C06939D0436D614840
A34: 33 | B34: Departure | C34: 45702.657 | D34: SENTINEL | E34: NULL | F34: CP | G34: 8909 | H34: 672 | I34: 44.94491 | J34: -93.05781 | K34: 408.78 | L34: MERRIAM PARK | M34: HOFFMAN ST PAUL | N34: NULL | O34: NULL | P34: CPRS | Q34: US EAST | R34: EAST | S34: ST PAUL | T34: MN | U34: US | V34: 23 | W34: 45702.666 | X34: 0101000020E61000006FD8B628B34357C0E9D495CFF2784640
A35: 34 | B35: Arrival | C35: 45702.661 | D35: SENTINEL | E35: NULL | F35: CP | G35: 8909 | H35: 667 | I35: 44.958153 | J35: -93.08206 | K35: NULL | L35: MERRIAM PARK | M35: STP ROBERT ST | N35: NULL | O35: NULL | P35: CPRS | Q35: NULL | R35: NULL | S35: NULL | T35: NULL | U35: NULL | V35: NULL | W35: 45702.666 | X35: 0101000020E6100000D3139678404557C03BC8EBC1A47A4640
A36: 35 | B36: Departure | C36: 45702.661 | D36: SENTINEL | E36: NULL | F36: CP | G36: 8909 | H36: 667 | I36: 44.958153 | J36: -93.08206 | K36: NULL | L36: MERRIAM PARK | M36: STP ROBERT ST | N36: NULL | O36: NULL | P36: CPRS | Q36: NULL | R36: NULL | S36: NULL | T36: NULL | U36: NULL | V36: NULL | W36: 45702.666 | X36: 0101000020E6100000D3139678404557C03BC8EBC1A47A4640
A37: 36 | B37: Arrival | C37: 45702.663 | D37: SENTINEL | E37: W | F37: CP | G37: 9814 | H37: 9525 | I37: 51.19739 | J37: -117.74107 | K37: 97.18 | L37: MOUNTAIN | M37: ILLECILLEWAET | N37: 14701083946 | O37: 113-08 | P37: CPRS | Q37: PACIFIC | R37: WEST | S37: MOUNTAIN | T37: BC | U37: CA | V37: 6103 | W37: 45702.666 | X37: 0101000020E61000005D8B16A06D6F5DC05A47551344994940
A38: 37 | B38: Arrival | C38: 45702.66 | D38: SENTINEL | E38: N | F38: CP | G38: 8786 | H38: 5538 | I38: 28.969683 | J38: -96.66074 | K38: 959.53 | L38: ROSENBERG | M38: EDNA | N38: 14752611853 | O38: 581-012 | P38: CPRS | Q38: SOUTH WEST | R38: MEXICO | S38: SOUTHWEST | T38: TX | U38: US | V38: 6726 | W38: 45702.666 | X38: 0101000020E61000002ECA6C90492A58C0B77C24253DF83C40
A39: 38 | B39: Departure | C39: 45702.661 | D39: SENTINEL | E39: W | F39: CP | G39: 8172 | H39: 4944 | I39: 46.05896 | J39: -96.73996 | K39: 197.94 | L39: ELBOW LAKE | M39: OSWALD | N39: 14722100617 | O39: 149-13 | P39: CPRS | Q39: US WEST | R39: EAST | S39: NORTH DAKOTA | T39: ND | U39: US | V39: 3 | W39: 45702.666 | X39: 0101000020E6100000481630815B2F58C0D6E253008C074740
A40: 39 | B40: Arrival | C40: 45702.661 | D40: SENTINEL | E40: W | F40: CP | G40: 8172 | H40: 4944 | I40: 46.05896 | J40: -96.73996 | K40: 197.94 | L40: ELBOW LAKE | M40: OSWALD | N40: 14722100617 | O40: 149-13 | P40: CPRS | Q40: US WEST | R40: EAST | S40: NORTH DAKOTA | T40: ND | U40: US | V40: 3 | W40: 45702.666 | X40: 0101000020E6100000481630815B2F58C0D6E253008C074740
A41: 40 | B41: Departure | C41: 45702.657 | D41: SENTINEL | E41: W | F41: CP | G41: 8172 | H41: 4943 | I41: 46.058777 | J41: -96.69208 | K41: 195.63 | L41: ELBOW LAKE | M41: VEBLEN JCT | N41: 14722100617 | O41: 149-13 | P41: CPRS | Q41: US WEST | R41: EAST | S41: NORTH DAKOTA | T41: ND | U41: US | V41: 3 | W41: 45702.666 | X41: 0101000020E6100000CE8DE9094B2C58C0E560360186074740
A42: 41 | B42: Departure | C42: 45702.662 | D42: SENTINEL | E42: W | F42: CP | G42: 8756 | H42: 4958 | I42: 46.834667 | J42: -97.87316 | K42: 276.85 | L42: CARRINGTON | M42: CUBA | N42: 14736977502 | O42: 645-669 | P42: CPRS | Q42: US WEST | R42: EAST | S42: NORTH DAKOTA | T42: ND | U42: US | V42: 2 | W42: 45702.666 | X42: 0101000020E6100000390B7BDAE17758C07506465ED66A4740
A43: 42 | B43: Departure | C43: 45702.66 | D43: SENTINEL | E43: E | F43: CP | G43: 8631 | H43: 4449 | I43: 48.85172 | J43: -88.4763 | K43: 80.06 | L43: NIPIGON | M43: HURKETT | N43: 14745559614 | O43: 104-10 | P43: CPRS | Q43: CANADA CENTRAL | R43: WEST | S43: THUNDER BAY | T43: ON | U43: CA | V43: 6410 | W43: 45702.666 | X43: 0101000020E61000006DC5FEB27B1E56C0B0AC3429056D4840
A44: 43 | B44: Departure | C44: 45702.662 | D44: SENTINEL | E44: N | F44: CP | G44: 8709 | H44: 4405 | I44: 48.788002 | J44: -87.11636 | K44: 110.83 | L44: HERON BAY | M44: TERRACE BAY | N44: 14718009362 | O44: 113-12 | P44: CPRS | Q44: CANADA CENTRAL | R44: WEST | S44: THUNDER BAY | T44: ON | U44: CA | V44: 6415 | W44: 45702.666 | X44: 0101000020E610000001A4367172C755C05F97E13FDD644840
A45: 44 | B45: Arrival | C45: 45702.661 | D45: SENTINEL | E45: NULL | F45: CP | G45: 8102 | H45: 5298 | I45: 27.969824 | J45: -97.56436 | K45: NULL | L45: UP BROWNSVILLE | M45: ODEM | N45: NULL | O45: NULL | P45: CPRS | Q45: NULL | R45: NULL | S45: NULL | T45: TX | U45: US | V45: NULL | W45: 45702.666 | X45: 0101000020E6100000EACA67791E6458C03BE0BA6246F83B40
A46: 45 | B46: Departure | C46: 45702.662 | D46: SENTINEL | E46: N | F46: CP | G46: 8786 | H46: 5538 | I46: 28.983458 | J46: -96.63404 | K46: 957.66 | L46: ROSENBERG | M46: EDNA | N46: 14752611853 | O46: 581-012 | P46: CPRS | Q46: SOUTH WEST | R46: MEXICO | S46: SOUTHWEST | T46: TX | U46: US | V46: 6726 | W46: 45702.666 | X46: 0101000020E6100000C616821C942858C054FD4AE7C3FB3C40
A47: 46 | B47: Arrival | C47: 45702.662 | D47: SENTINEL | E47: NULL | F47: CP | G47: 8038 | H47: 9642 | I47: 50.4201 | J47: -121.35268 | K47: NULL | L47: THOMPSON | M47: SPENCE'S BRIDGE | N47: NULL | O47: NULL | P47: CPRS | Q47: NULL | R47: NULL | S47: NULL | T47: BC | U47: CA | V47: NULL | W47: 45702.666 | X47: 0101000020E6100000037D224F92565EC0598638D6C5354940
A48: 47 | B48: Arrival | C48: 45702.662 | D48: SENTINEL | E48: E | F48: CP | G48: 8127 | H48: 7427 | I48: 50.38453 | J48: -111.50956 | K48: 45.61 | L48: BROOKS | M48: KININVIE | N48: 14753543967 | O48: 2148-12 | P48: CPRS | Q48: PRAIRIE SOUTH | R48: WEST | S48: ALBERTA SOUTH | T48: AB | U48: CA | V48: 6202 | W48: 45702.666 | X48: 0101000020E610000062D68BA19CE05BC05A2A6F4738314940
A49: 48 | B49: Arrival | C49: 45702.663 | D49: SENTINEL | E49: NULL | F49: CP | G49: 8074 | H49: 9017 | I49: 50.0187 | J49: -114.83309 | K49: 21.42 | L49: FORDING RIVER | M49: GREENHILLS | N49: NULL | O49: NULL | P49: CPRS | Q49: PACIFIC | R49: WEST | S49: KOOTENAY | T49: BC | U49: CA | V49: 6112 | W49: 45702.666 | X49: 0101000020E6100000FA27B85851B55CC0B537F8C264024940
A50: 49 | B50: Departure | C50: 45702.663 | D50: SENTINEL | E50: NULL | F50: CP | G50: 8074 | H50: 9017 | I50: 50.0187 | J50: -114.83309 | K50: 21.42 | L50: FORDING RIVER | M50: GREENHILLS | N50: NULL | O50: NULL | P50: CPRS | Q50: PACIFIC | R50: WEST | S50: KOOTENAY | T50: BC | U50: CA | V50: 6112 | W50: 45702.666 | X50: 0101000020E6100000FA27B85851B55CC0B537F8C264024940
A51: 50 | B51: Departure | C51: 45702.66 | D51: SENTINEL | E51: W | F51: CP | G51: 7056 | H51: 9568 | I51: 50.967407 | J51: -118.36416 | K51: 8.93 | L51: SHUSWAP | M51: CLANWILLIAM | N51: 14752708893 | O51: 611-111 | P51: CPRS | Q51: PACIFIC | R51: WEST | S51: MOUNTAIN | T51: BC | U51: CA | V51: 6101 | W51: 45702.666 | X51: 0101000020E6100000BAA0BE654E975DC0F37519FED37B4940
A52: 51 | B52: Arrival | C52: 45702.661 | D52: SENTINEL | E52: S | F52: CP | G52: 8021 | H52: 5143 | I52: 34.054 | J52: -94.3371 | K52: 432.17 | L52: SHREVEPORT | M52: DE QUEEN | N52: 14718044788 | O52: 262-12 | P52: CPRS | Q52: MIDWEST | R52: SOUTH | S52: PITTSBURG | T52: AR | U52: US | V52: 6708 | W52: 45702.666 | X52: 0101000020E6100000D3DEE00B939557C0F4FDD478E9064140
A53: 52 | B53: Arrival | C53: 45702.66 | D53: SENTINEL | E53: W | F53: CP | G53: 7056 | H53: 9568 | I53: 50.967407 | J53: -118.36416 | K53: 8.93 | L53: SHUSWAP | M53: CLANWILLIAM | N53: 14752708893 | O53: 611-111 | P53: CPRS | Q53: PACIFIC | R53: WEST | S53: MOUNTAIN | T53: BC | U53: CA | V53: 6101 | W53: 45702.666 | X53: 0101000020E6100000BAA0BE654E975DC0F37519FED37B4940
A54: 53 | B54: Arrival | C54: 45702.628 | D54: SENTINEL | E54: N | F54: CP | G54: 7026 | H54: 1125 | I54: 24.31068 | J54: -100.8578 | K54: 477.84 | L54: VANEGAS | M54: EL SALADO | N54: 14722133327 | O54: 293-13 | P54: CPRS | Q54: MEXICO SOUTH | R54: MEXICO | S54: VANEGAS | T54: SL | U54: MX | V54: 6802 | W54: 45702.666 | X54: 0101000020E610000090A0F831E63659C0738577B9884F3840
A55: 54 | B55: Departure | C55: 45702.66 | D55: SENTINEL | E55: W | F55: CP | G55: 7022 | H55: 9656 | I55: 49.792637 | J55: -121.44878 | K55: NULL | L55: CASCADE | M55: CHINA BAR | N55: 14713982417 | O55: 401-11 | P55: CPRS | Q55: NULL | R55: NULL | S55: NULL | T55: NULL | U55: NULL | V55: NULL | W55: 45702.666 | X55: 0101000020E610000054C6BFCFB85C5EC0BE4C142175E54840
A56: 55 | B56: Departure | C56: 45702.653 | D56: WITRONIX | E56: S | F56: KCSM | G56: 4897 | H56: 2617 | I56: 22.148999 | J56: -99.739724 | K56: 244.21 | L56: TAMASOPO | M56: LAS TABLAS | N56: 14764723440 | O56: LEN-139 | P56: CPRS | Q56: MEXICO SOUTH | R56: MEXICO | S56: TAMASOPO | T56: SL | U56: MX | V56: 6815 | W56: 45702.666 | X56: 0101000020E6100000F7917CA157EF58C0D579F1D124263640
A57: 56 | B57: Departure | C57: 45702.66 | D57: WITRONIX | E57: S | F57: KCSM | G57: 4897 | H57: 2619 | I57: 22.048398 | J57: -99.683511 | K57: 252.03 | L57: TAMASOPO | M57: LA CINTA | N57: 14764723440 | O57: LEN-139 | P57: CPRS | Q57: MEXICO SOUTH | R57: MEXICO | S57: TAMASOPO | T57: SL | U57: MX | V57: 6815 | W57: 45702.666 | X57: 0101000020E61000002AF4C9A3BEEB58C0F1873CD5630C3640
A58: 57 | B58: Arrival | C58: 45702.656 | D58: WITRONIX | E58: S | F58: KCSM | G58: 4897 | H58: 2619 | I58: 22.105571 | J58: -99.714903 | K58: 247.61 | L58: TAMASOPO | M58: LA CINTA | N58: 14764723440 | O58: LEN-139 | P58: CPRS | Q58: MEXICO SOUTH | R58: MEXICO | S58: TAMASOPO | T58: SL | U58: MX | V58: 6815 | W58: 45702.666 | X58: 0101000020E6100000E8297AF9C0ED58C0A3F0B0BB061B3640
A59: 58 | B59: Departure | C59: 45702.659 | D59: SENTINEL | E59: W | F59: KCSM | G59: 4719 | H59: 9640 | I59: 50.51658 | J59: -121.28119 | K59: NULL | L59: THOMPSON | M59: TOKETIC | N59: 14718061177 | O59: 401-12 | P59: CPRS | Q59: NULL | R59: NULL | S59: NULL | T59: NULL | U59: NULL | V59: NULL | W59: 45702.666 | X59: 0101000020E6100000957D5704FF515EC043E21E4B1F424940
A60: 59 | B60: Arrival | C60: 45702.623 | D60: WITRONIX | E60: S | F60: KCSM | G60: 4896 | H60: 2615 | I60: 22.304576 | J60: -100.05559 | K60: 220.35 | L60: TAMASOPO | M60: SAN BARTOLO | N60: 14764723440 | O60: LEN-139 | P60: CPRS | Q60: MEXICO SOUTH | R60: MEXICO | S60: TAMASOPO | T60: SL | U60: MX | V60: 6815 | W60: 45702.666 | X60: 0101000020E610000072E2E5C88E0359C0812557B1F84D3640
A61: 60 | B61: Departure | C61: 45702.624 | D61: WITRONIX | E61: S | F61: KCSM | G61: 4896 | H61: 2615 | I61: 22.300006 | J61: -100.0294 | K61: 222.06 | L61: TAMASOPO | M61: SAN BARTOLO | N61: 14764723440 | O61: LEN-139 | P61: CPRS | Q61: MEXICO SOUTH | R61: MEXICO | S61: TAMASOPO | T61: SL | U61: MX | V61: 6815 | W61: 45702.666 | X61: 0101000020E6100000429CC1BEE10159C09D50C22BCD4C3640
A62: 61 | B62: Arrival | C62: 45702.628 | D62: WITRONIX | E62: S | F62: KCSM | G62: 4896 | H62: 2616 | I62: 22.288039 | J62: -99.961147 | K62: 226.5 | L62: TAMASOPO | M62: VIEJO | N62: 14764723440 | O62: LEN-139 | P62: CPRS | Q62: MEXICO SOUTH | R62: MEXICO | S62: TAMASOPO | T62: SL | U62: MX | V62: 6815 | W62: 45702.666 | X62: 0101000020E6100000B143886D83FD58C0E1E07FE9BC493640
A63: 62 | B63: Departure | C63: 45702.632 | D63: WITRONIX | E63: S | F63: KCSM | G63: 4896 | H63: 2616 | I63: 22.277285 | J63: -99.899911 | K63: 230.44 | L63: TAMASOPO | M63: VIEJO | N63: 14764723440 | O63: LEN-139 | P63: CPRS | Q63: MEXICO SOUTH | R63: MEXICO | S63: TAMASOPO | T63: SL | U63: MX | V63: 6815 | W63: 45702.666 | X63: 0101000020E61000000B13FC2598F958C0B502E02BFC463640
A64: 63 | B64: Arrival | C64: 45702.635 | D64: WITRONIX | E64: S | F64: KCSM | G64: 4896 | H64: 2617 | I64: 22.257204 | J64: -99.861795 | K64: 233.43 | L64: TAMASOPO | M64: LAS TABLAS | N64: 14764723440 | O64: LEN-139 | P64: CPRS | Q64: MEXICO SOUTH | R64: MEXICO | S64: TAMASOPO | T64: SL | U64: MX | V64: 6815 | W64: 45702.666 | X64: 0101000020E61000003C1AC1A527F758C08641361CD8413640
A65: 64 | B65: Departure | C65: 45702.653 | D65: WITRONIX | E65: S | F65: KCSM | G65: 4896 | H65: 2617 | I65: 22.149366 | J65: -99.740071 | K65: 244.18 | L65: TAMASOPO | M65: LAS TABLAS | N65: 14764723440 | O65: LEN-139 | P65: CPRS | Q65: MEXICO SOUTH | R65: MEXICO | S65: TAMASOPO | T65: SL | U65: MX | V65: 6815 | W65: 45702.666 | X65: 0101000020E6100000A1DA01535DEF58C03A792EDF3C263640
A66: 65 | B66: Arrival | C66: 45702.656 | D66: WITRONIX | E66: S | F66: KCSM | G66: 4896 | H66: 2619 | I66: 22.105683 | J66: -99.714934 | K66: 247.6 | L66: TAMASOPO | M66: LA CINTA | N66: 14764723440 | O66: LEN-139 | P66: CPRS | Q66: MEXICO SOUTH | R66: MEXICO | S66: TAMASOPO | T66: SL | U66: MX | V66: 6815 | W66: 45702.666 | X66: 0101000020E6100000114A6779C1ED58C01DF0330D0E1B3640
A67: 66 | B67: Departure | C67: 45702.662 | D67: SENTINEL | E67: N | F67: CP | G67: 8702 | H67: 8255 | I67: 51.047543 | J67: -114.01909 | K67: 1.35 | L67: RED DEER | M67: BENGAL | N67: 14749636565 | O67: 614-044 | P67: CPRS | Q67: PRAIRIE NORTH | R67: WEST | S67: CALGARY | T67: AB | U67: CA | V67: 6223 | W67: 45702.666 | X67: 0101000020E6100000906B43C538815CC0AD1397E315864940
A68: 67 | B68: Arrival | C68: 45702.661 | D68: SENTINEL | E68: N | F68: CP | G68: 8702 | H68: 8255 | I68: 51.045475 | J68: -114.01886 | K68: 1.2 | L68: RED DEER | M68: BENGAL | N68: 14749636565 | O68: 614-044 | P68: CPRS | Q68: PRAIRIE NORTH | R68: WEST | S68: CALGARY | T68: AB | U68: CA | V68: 6223 | W68: 45702.666 | X68: 0101000020E6100000F7CC920035815CC08FE4F21FD2854940
A69: 68 | B69: Departure | C69: 45702.66 | D69: WITRONIX | E69: S | F69: KCSM | G69: 4896 | H69: 2619 | I69: 22.048855 | J69: -99.683735 | K69: 252 | L69: TAMASOPO | M69: LA CINTA | N69: 14764723440 | O69: LEN-139 | P69: CPRS | Q69: MEXICO SOUTH | R69: MEXICO | S69: TAMASOPO | T69: SL | U69: MX | V69: 6815 | W69: 45702.666 | X69: 0101000020E6100000521F504FC2EB58C0DB7092C5810C3640
A70: 69 | B70: Departure | C70: 45702.634 | D70: WITRONIX | E70: S | F70: KCSM | G70: 4897 | H70: 2616 | I70: 22.261069 | J70: -99.866633 | K70: 233.01 | L70: TAMASOPO | M70: VIEJO | N70: 14764723440 | O70: LEN-139 | P70: CPRS | Q70: MEXICO SOUTH | R70: MEXICO | S70: TAMASOPO | T70: SL | U70: MX | V70: 6815 | W70: 45702.666 | X70: 0101000020E6100000469582EA76F758C0B1568A70D5423640
A71: 70 | B71: Arrival | C71: 45702.635 | D71: WITRONIX | E71: S | F71: KCSM | G71: 4897 | H71: 2617 | I71: 22.256981 | J71: -99.861555 | K71: 233.45 | L71: TAMASOPO | M71: LAS TABLAS | N71: 14764723440 | O71: LEN-139 | P71: CPRS | Q71: MEXICO SOUTH | R71: MEXICO | S71: TAMASOPO | T71: SL | U71: MX | V71: 6815 | W71: 45702.666 | X71: 0101000020E6100000538768B623F758C057084887C9413640
A72: 71 | B72: Arrival | C72: 45702.658 | D72: SENTINEL | E72: W | F72: KCSM | G72: 4719 | H72: 9640 | I72: 50.529373 | J72: -121.28445 | K72: NULL | L72: THOMPSON | M72: TOKETIC | N72: 14718061177 | O72: 401-12 | P72: CPRS | Q72: NULL | R72: NULL | S72: NULL | T72: BC | U72: CA | V72: NULL | W72: 45702.666 | X72: 0101000020E610000039D6C56D34525EC05531957EC2434940
A73: 72 | B73: Departure | C73: 45702.59 | D73: WITRONIX | E73: S | F73: KCSM | G73: 4896 | H73: 2611 | I73: 22.478847 | J73: -100.35195 | K73: 197.44 | L73: TAMASOPO | M73: MONTANA | N73: 14764723440 | O73: LEN-139 | P73: CPRS | Q73: MEXICO SOUTH | R73: MEXICO | S73: TAMASOPO | T73: SL | U73: MX | V73: 6815 | W73: 45702.666 | X73: 0101000020E610000044B2D351861659C0B37FD8B1957A3640
A74: 73 | B74: Arrival | C74: 45702.597 | D74: WITRONIX | E74: S | F74: KCSM | G74: 4896 | H74: 2612 | I74: 22.427331 | J74: -100.296 | K74: 202.49 | L74: TAMASOPO | M74: CERRITOS | N74: 14764723440 | O74: LEN-139 | P74: CPRS | Q74: MEXICO SOUTH | R74: MEXICO | S74: TAMASOPO | T74: SL | U74: MX | V74: 6815 | W74: 45702.666 | X74: 0101000020E610000019543CAAF11259C02B6CA38D656D3640
A75: 74 | B75: Departure | C75: 45702.614 | D75: WITRONIX | E75: S | F75: KCSM | G75: 4896 | H75: 2612 | I75: 22.350055 | J75: -100.18215 | K75: 211.53 | L75: TAMASOPO | M75: CERRITOS | N75: 14764723440 | O75: LEN-139 | P75: CPRS | Q75: MEXICO SOUTH | R75: MEXICO | S75: TAMASOPO | T75: SL | U75: MX | V75: 6815 | W75: 45702.666 | X75: 0101000020E610000083C6864DA80B59C003DA2D349D593640
A76: 75 | B76: Arrival | C76: 45702.616 | D76: WITRONIX | E76: S | F76: KCSM | G76: 4896 | H76: 2614 | I76: 22.334025 | J76: -100.15782 | K76: 213.45 | L76: TAMASOPO | M76: LA BORREGUITA | N76: 14764723440 | O76: LEN-139 | P76: CPRS | Q76: MEXICO SOUTH | R76: MEXICO | S76: TAMASOPO | T76: SL | U76: MX | V76: 6815 | W76: 45702.666 | X76: 0101000020E61000009D5303AC190A59C0EDC1DEA382553640
A77: 76 | B77: Departure | C77: 45702.617 | D77: WITRONIX | E77: S | F77: KCSM | G77: 4896 | H77: 2614 | I77: 22.32447 | J77: -100.13617 | K77: 214.94 | L77: TAMASOPO | M77: LA BORREGUITA | N77: 14764723440 | O77: LEN-139 | P77: CPRS | Q77: MEXICO SOUTH | R77: MEXICO | S77: TAMASOPO | T77: SL | U77: MX | V77: 6815 | W77: 45702.666 | X77: 0101000020E6100000FC2BB7F6B60859C0863E927110533640
A78: 77 | B78: Departure | C78: 45702.663 | D78: WITRONIX | E78: N | F78: KCSM | G78: 4738 | H78: 4735 | I78: 38.369595 | J78: -94.584262 | K78: 61.04 | L78: PITTSBURG | M78: AMSTERDAM | N78: 14634724304 | O78: 865-903 | P78: CPRS | Q78: MIDWEST | R78: SOUTH | S78: PITTSBURG | T78: MO | U78: US | V78: 6706 | W78: 45702.666 | X78: 0101000020E6100000FF9C7A8B64A557C0196140E54E2F4340
